Workbook

Sheet Índice
B3: ÍNDICE
K7: Página | AA7: 42491
C8: Garantia e Prazo de Fabricação | K8: 01 | AA8: 160
C9: Limpeza e Conservação | K9: 02
C10: Assitência Técnica | K10: 03
C11: Cortina Rolô | K11: 06 | AA11: 192
C12: Linha Premium | K12: 09 | AA12: 140.5
C13: Cortina Romana | K13: 12 | AA13: 169
C14: Cortina Painel | K14: 14 | AA14: 132.4
C15: Cortina de Teto | K15: 16 | AA15: 159
C16: Coleção Soltis (Ferrari ®) | K16: 18
C17: Persiana Vertical | K17: 19 | AA17: 160
C18: Persiana Horizontal de Alumínio | K18: 22 | AA18: 160
C19: Persiana Horizontal de Madeira - Bambu - Sintética - PVC Curve | K19: 25 | AA19: 160
C20: Cortina Celular e Vert Gliss | K20: 27 | AA20: 153.4
C21: Cortina Plissada | K21: 29 | AA21: 153.4
C22: Motorização Amorim | K22: 33 | AA22: 130.1
C23: Motorização Somfy | K23: 37 | AA23: 179.3
AA24: 179.3
AA25: 103.3
AA26: 120.4
AA28: 105.3
AA29: 116.5
AA31: 132.4
AA32: 132.4
AA33: 126.5
AA34: 126.2
AA35: 132.4
AA36: 144.7
AA37: 130.1
... AA58: 111.8
B63: ACESSE NOSSO SITE
B64: www.amorimcortinas.com.br

Sheet Info
K2: Página - 1 | L2: =Rolô!L2 -> 2026 - v.03
B3: GARANTIA E PRAZO DE FABRICAÇÃO
C6: As Cortinas e Persianas Amorim são produtos personalizados, fabricados somente sob encomenda e com medidas especificadas pela revenda. O prazo de garantia é contado a partir da data de entrega do produto ao revendedor. | AA6: 42491
AA7: 160
AA8: 192
C9: Os produtos Amorim possuem 3 anos de garantia, somente para cobertura por defeito originado por falha oculta de fabricação. | AA9: 140.5
AA10: 169
C11: Motores para cortinas e persianas possuem 5 anos de garantia, somente para cobertura por defeito originado por falha oculta de fabricação. | AA11: 132.4
AA12: 159
C13: Acessórios: fonte, receptor e controle possuem 2 anos de garantia, somente para cobertura por defeito originado por falha oculta de fabricação. | AA13: 160
AA14: 160
AA15: 160
AA17: 153.4
B18: PARA MAIS INFORMAÇÕES, SOLICITE O TERMO DE GARANTIA. | AA18: 179.3
B19: PRAZO DE FABRICAÇÃO | AA19: 120.4
C20: Cortina Rolô: 5 dias úteis *ACIMA DE 50 PEÇAS (PRAZO SOB CONSULTA) | AA20: 105.3
C21: Cortina Rolô Motorizada: 5 dias úteis | AA21: 105.3
C22: Cortina Rolô Motorizada: 5 dias úteis | AA22: 116.5
AA23: 132.4
C24: Linha Premium: 10 dias úteis | AA24: 132.4
C25: Passione/ Vert Gliss: 15 dias úteis | AA25: 132.4
C26: Cortina Atena: 5 dias úteis | AA26: 126.5
AA27: 126.2
C28: Cortina Romana (Manual e Motorizada): 7 dias úteis | AA28: 132.4
C29: Cortina Romana Classic (Manual e Motorizada): 10 dias úteis | AA29: 144.7
AA31: 117.9
C32: Cortina Painel Europa: 7 dias úteis | AA32: 111.8
AA33: 137.5
AA34: 125
C35: Cortina de Teto Allure Manual e Monocontrole: 10 dias úteis | AA35: 125
C36: Cortina de Teto Allure Motorizado: 15 dias úteis
AA37: 110.6
C38: Persiana Vertical Tecido e PVC: 5 dias úteis ** | AA38: 125
C39: Persiana Vertical Tecido e PVC com galeria de madeira: 10 dias úteis ** | AA39: 110.6
C40: Persiana Vertical Tecido Motorizada : 5 dias úteis ** | AA40: 116.1
C41: **ACIMA DE 50 PEÇAS (PRAZO SOB CONSULTA) | AA41: 160
AA42: 144.7
C43: Persiana Horizontal de Alumínio 16mm e 25mm Standard e Entre Vidros: 5 dias úteis | AA43: 126.2
C44: Persiana Horizontal de Alumínio 16mm e 25mm Comando Único, Monocontrole e Motorizada: 7 dias úteis | AA44: 160.3
C45: Persiana Horizontal de Alumínio 50mm Standard e Monocontrole: 7 dias úteis | AA45: 139.1
C46: Persiana Horizontal de Alumínio 50mm Motorizada: 7 dias úteis | AA46: 114.8
AA47: 118.3
C48: Persiana Horizontal 50mm Bambu, Wood, Sintética e Curve: 10 dias úteis | AA48: 111.8
AA49: 111.8
C50: Cortina Celular: 7 dias úteis
C51: Cortina Celular com Recorte: 15 dias úteis
C52: Cortina Teto Celular: 15 dias úteis
C54: Cortina Plissada: 7 dias úteis
C55: Cortina Plissada com Recorte: 15 dias úteis
C58: Toldos e Zip System: 10 dias úteis
C61: Trilho Unique: 7 dias úteis
C63: Pérgola: 20 dias úteis
C65: Impressão Amoprint: 10 dias úteis além do prazo de fabricação do produto.
B66: PEDIDO ENVIADO COM PRODUTOS DE PRAZOS DIFERENTES, CONSIDERAR O PRAZO DE FABRICAÇÃO MAIOR.
K67: Página - 2 | L67: =Rolô!L2 -> 2026 - v.03
B68: LIMPEZA E CONSERVAÇÃO
AA72: 42491
C73: Limpar periodicamente, especialmente em locais mais poluídos, sujeitos à maresia e com umidade excessiva. | AA73: 160
AA74: 192
C75: Com a persiana aberta, passe suavemente um pano macio ou um espanador. Repita a operação no lado oposto. | AA75: 140.5
AA76: 169
C77: A limpeza também pode ser feita com um aspirador de pó composto por bocal tipo escova. | AA77: 132.4
AA78: 159
C79: Nunca utilize produtos químicos. | AA79: 160
AA80: 160
C81: O processo de lavagem dos tecidos deve ser realizados somente por empresas especializadas em lavagem ultra-sônica. | AA81: 160
AA82: 153.4
C83: Não utilizar aspirador de pó se o tecido estiver úmido. | AA83: 153.4
AA84: 130.1
C85: Os tecidos Screen e Blackout Pinpoint poderão ser limpos com esponja umedecida em água morna e sabão neutro e a secagem deverá ser feita totalmente a sombra. | AA85: 179.3
AA86: 179.3
AA87: 103.3
C88: Não utilizar máquina de lavar ou vaporizador em nenhum tecido. | AA88: 120.4
AA90: 105.3
AA91: 105.3
AA92: 116.5
AA93: 132.4
AA94: 132.4
AA95: 132.4
AA96: 126.5
AA97: 126.2
AA98: 132.4
AA99: 144.7
AA100: 130.1
AA101: 104.5
... AA121: 111.8

Sheet Assistência Técnica
K2: Página 3 - | L2: =Rolô!L2 -> 2026 - v.03 | N2: * DIGITE A PORCENTAGEM PARA MARKUP
B3: ASSISTÊNCIA TÉCNICA | N3: 0
B6: SERVIÇOS - CORTINA ROLÔ
B7: ITEM | C7: DESCRIÇÃO | J7: VALOR À VISTA (R$) | AA7: 43009 | AB7: 43258 | AC7: 43862 | AD7: 43952 | AE7: 44136
B8: 1 | C8: CORTE NA ALTURA DA CORTINA ROLÔ | J8: =ROUNDUP(((AH8*$N$3)+AH8),1) -> 53.3 | AA8: 33 | AB8: =AA8*1.1 -> 36.3 | AC8: =AB8*1.1 -> 39.93 | AD8: 43.923 | AE8: 48.4 | AH8: =AE8*1.1 -> 53.24
B9: 2 | C9: CORTE NA LARGURA DA CORTINA ROLÔ | J9: =ROUNDUP(((AH9*$N$3)+AH9),1) -> 101.6 | AA9: 66 | AB9: =AA9*1.1 -> 72.6 | AC9: =AB9*1.05 -> 76.23 | AD9: 83.853 | AE9: 92.3 | AH9: =AE9*1.1 -> 101.53
B10: 3 | C10: TROCA DE COMANDO DE CORTINA ROLÔ (VALOR DE MÃO DE OBRA, COMANDO SERÁ COBRADO SEPARADAMENTE) | J10: =ROUNDUP(((AH10*$N$3)+AH10),1) -> 35.6 | AA10: 22 | AB10: =AA10*1.1 -> 24.2 | AC10: =AB10*1.1 -> 26.62 | AD10: 29.282 | AE10: 32.3 | AH10: =AE10*1.1 -> 35.53
B11: 4 | AH11: =AE11*1.1 -> 0
B12: 5 | C12: TROCA DE TECIDO (VALOR DE MÃO DE OBRA, TECIDO SERÁ COBRADO SEPARADAMENTE) | J12: =ROUNDUP(((AH12*$N$3)+AH12),1) -> 35.6 | AA12: 22 | AB12: =AA12*1.1 -> 24.2 | AC12: =AB12*1.1 -> 26.62 | AD12: 29.282 | AE12: 32.3 | AH12: =AE12*1.1 -> 35.53
B13: 6 | C13: CORTE DE TRILHO DE CORRER PARA ROLÔ (TRILHO DEVE SER SOLICIDADO SEPARADAMENTE) | J13: =ROUNDUP(((AH13*$N$3)+AH13),1) -> 53.3 | AA13: 33 | AB13: =AA13*1.1 -> 36.3 | AC13: =AB13*1.1 -> 39.93 | AD13: 43.923 | AE13: 48.4 | AH13: =AE13*1.1 -> 53.24
B14: 7 | C14: CORTE DE BANDÔ OU BARRA NIVELADORA | J14: =ROUNDUP(((AH14*$N$3)+AH14),1) -> 35.6 | AA14: 22 | AB14: =AA14*1.1 -> 24.2 | AC14: =AB14*1.1 -> 26.62 | AD14: 29.282 | AE14: 32.3 | AH14: =AE14*1.1 -> 35.53
B15: 8 | C15: TROCA DE TUBO (VALOR DE MÃO DE OBRA, TUBO SERÁ COBRADO SEPARADAMENTE) | J15: =ROUNDUP(((AH15*$N$3)+AH15),1) -> 35.6 | AA15: 22 | AB15: =AA15*1.1 -> 24.2 | AC15: =AB15*1.1 -> 26.62 | AD15: 29.282 | AE15: 32.3 | AH15: =AE15*1.1 -> 35.53
B16: 9 | C16: REGULAGEM PEÇA MANUAL | J16: =ROUNDUP(((AH16*$N$3)+AH16),1) -> 26.7 | AA16: 16.5 | AB16: =AA16*1.1 -> 18.15 | AC16: =AB16*1.1 -> 19.965 | AD16: 21.9615 | AE16: 24.2 | AH16: =AE16*1.1 -> 26.62
B17: 10 | C17: REGULAGEM PEÇA MOTORIZADA | J17: =ROUNDUP(((AH17*$N$3)+AH17),1) -> 54.5 | AE17: 49.5 | AH17: =AE17*1.1 -> 54.45
B18: 11 | C18: INVESÃO DE ROLAMENTO | J18: =ROUNDUP(((AH18*$N$3)+AH18),1) -> 35.6 | AA18: 22 | AB18: =AA18*1.1 -> 24.2 | AC18: =AB18*1.1 -> 26.62 | AD18: 29.282 | AE18: 32.3 | AH18: =AE18*1.1 -> 35.53
B19: 12 | C19: MOTORIZAÇÃO (VALOR DE MÃO DE OBRA, MOTORIZAÇÃO COBRADA SEPARADAMENTE) | J19: =ROUNDUP(((AH19*$N$3)+AH19),1) -> 60.5 | AA19: 22 | AB19: =AA19*1.1 -> 24.2 | AC19: =AB19*1.1 -> 26.62 | AD19: 29.282 | AE19: 55 | AH19: =AE19*1.1 -> 60.5
B20: 13 | C20: TROCA DE BANDÔ OU BASE (VALOR DE MÃO DE OBRA, BANDÔ OU BASE SERÁ COBRADO SEPARADAMENTE) | J20: =ROUNDUP(((AH20*$N$3)+AH20),1) -> 35.6 | AA20: 27.9 | AB20: =AA20*1.1 -> 30.69 | AC20: =AB20*1.1 -> 33.759 | AD20: 37.1349 | AE20: 32.3 | AH20: =AE20*1.1 -> 35.53
B21: 14 | AH21: =AE21*1.1 -> 0
B22: SERVIÇOS - CORTINA ETERNITY, ETERNITY LINE, GALAXY, ILLUMINÊ, INFINITY, LUMIÉRE E MELÍADE | AH22: =AE22*1.1 -> 0
B23: ITEM | C23: DESCRIÇÃO | J23: VALOR À VISTA (R$) | AH23: =AE23*1.1 -> 0
B24: 15 | C24: CORTE NA ALTURA | J24: =ROUNDUP(((AH24*$N$3)+AH24),1) -> 88.8 | AA24: 55 | AB24: =AA24*1.1 -> 60.5 | AC24: =AB24*1.1 -> 66.55 | AD24: 73.205 | AE24: 80.7 | AH24: =AE24*1.1 -> 88.77
B25: 16 | C25: CORTE NA LARGURA | J25: =ROUNDUP(((AH25*$N$3)+AH25),1) -> 203.1 | AA25: 132 | AB25: =AA25*1.1 -> 145.2 | AC25: =AB25*1.05 -> 152.46 | AD25: 167.706 | AE25: 184.58 | AH25: =AE25*1.1 -> 203.038
B26: 17 | C26: TROCA DE COMANDO (VALOR DE MÃO DE OBRA, COMANDO SERÁ COBRADO SEPARADAMENTE) | J26: =ROUNDUP(((AH26*$N$3)+AH26),1) -> 67.3 | AA26: 41.7 | AB26: =AA26*1.1 -> 45.87 | AC26: =AB26*1.1 -> 50.457 | AD26: 55.5027 | AE26: 61.16 | AH26: =AE26*1.1 -> 67.276
B27: 18 | C27: TROCA DE TECIDO (VALOR DE MÃO DE OBRA, TECIDO SERÁ COBRADO SEPARADAMENTE) | J27: =ROUNDUP(((AH27*$N$3)+AH27),1) -> 88.8 | AA27: 55 | AB27: =AA27*1.1 -> 60.5 | AC27: =AB27*1.1 -> 66.55 | AD27: 73.205 | AE27: 80.7 | AH27: =AE27*1.1 -> 88.77
B28: 19 | C28: CORTE DE BANDÔ OU BARRA NIVELADORA | J28: =ROUNDUP(((AH28*$N$3)+AH28),1) -> 35.5 | AA28: 22 | AB28: =AA28*1.1 -> 24.2 | AC28: =AB28*1.1 -> 26.62 | AD28: 29.282 | AE28: 32.23 | AH28: =AE28*1.1 -> 35.453
B29: 20 | C29: MOTORIZAÇÃO (VALOR DE MÃO DE OBRA, MOTORIZAÇÃO COBRADA SEPARADAMENTE) | J29: =ROUNDUP(((AH29*$N$3)+AH29),1) -> 60.5 | AA29: 16.5 | AB29: =AA29*1.1 -> 18.15 | AC29: =AB29*1.1 -> 19.965 | AD29: 21.9615 | AE29: 55 | AH29: =AE29*1.1 -> 60.5
B30: 21 | C30: REGULAGEM PEÇA MANUAL | J30: =ROUNDUP(((AH30*$N$3)+AH30),1) -> 26.7 | AE30: 24.2 | AH30: =AE30*1.1 -> 26.62
B31: 22 | C31: REGULAGEM PEÇA MOTORIZADA | J31: =ROUNDUP(((AH31*$N$3)+AH31),1) -> 54.5 | AE31: 49.5 | AH31: =AE31*1.1 -> 54.45
B32: 23 | C32: TROCA DE BANDÔ, BARRA NIVELADORA OU BASE (VALOR DE MÃO DE OBRA, BANDÔ, BARRA OU BASE SERÃO COBRADOS SEPARADAMENTE) | J32: =ROUNDUP(((AH32*$N$3)+AH32),1) -> 35.6 | AA32: 22 | AB32: =AA32*1.1 -> 24.2 | AC32: =AB32*1.1 -> 26.62 | AD32: 29.282 | AE32: 32.3 | AH32: =AE32*1.1 -> 35.53
B33: 24
B34: SERVIÇOS - CORTINA ROLÔ STILLO | AH34: =AE34*1.1 -> 0
B35: ITEM | C35: DESCRIÇÃO | J35: VALOR À VISTA (R$) | AH35: =AE35*1.1 -> 0
B36: 25 | C36: CORTE NA ALTURA | J36: =ROUNDUP(((AH36*$N$3)+AH36),1) -> 124.1 | AA36: 77 | AB36: =AA36*1.1 -> 84.7 | AC36: =AB36*1.1 -> 93.17 | AD36: 102.487 | AE36: 112.8 | AH36: =AE36*1.1 -> 124.08
B37: 26 | C37: CORTE NA LARGURA | J37: =ROUNDUP(((AH37*$N$3)+AH37),1) -> 152.3 | AA37: 99 | AB37: =AA37*1.1 -> 108.9 | AC37: =AB37*1.05 -> 114.345 | AD37: 125.7795 | AE37: 138.4 | AH37: =AE37*1.1 -> 152.24
B38: 27 | C38: TROCA DE COMANDO (VALOR DE MÃO DE OBRA, COMANDO SERÁ COBRADO SEPARADAMENTE) | J38: =ROUNDUP(((AH38*$N$3)+AH38),1) -> 63 | AA38: 39 | AB38: =AA38*1.1 -> 42.9 | AC38: =AB38*1.1 -> 47.19 | AD38: 51.909 | AE38: 57.2 | AH38: =AE38*1.1 -> 62.92
B39: 28 | C39: TROCA DE TECIDO (VALOR DE MÃO DE OBRA, TECIDO SERÁ COBRADO SEPARADAMENTE) | J39: =ROUNDUP(((AH39*$N$3)+AH39),1) -> 88.8 | AA39: 55 | AB39: =AA39*1.1 -> 60.5 | AC39: =AB39*1.1 -> 66.55 | AD39: 73.205 | AE39: 80.7 | AH39: =AE39*1.1 -> 88.77
B40: 29 | C40: CORTE DE BANDÔ OU BARRA NIVELADORA | J40: =ROUNDUP(((AH40*$N$3)+AH40),1) -> 35.6 | AA40: 22 | AB40: =AA40*1.1 -> 24.2 | AC40: =AB40*1.1 -> 26.62 | AD40: 29.282 | AE40: 32.3 | AH40: =AE40*1.1 -> 35.53
B41: 30 | C41: REGULAGEM PEÇA MANUAL | J41: =ROUNDUP(((AH41*$N$3)+AH41),1) -> 26.7 | AE41: 24.2 | AH41: =AE41*1.1 -> 26.62
B42: 31 | C42: REGULAGEM PEÇA MOTORIZADA | J42: =ROUNDUP(((AH42*$N$3)+AH42),1) -> 54.5 | AA42: 16.5 | AB42: =AA42*1.1 -> 18.15 | AC42: =AB42*1.1 -> 19.965 | AD42: 21.9615 | AE42: 49.5 | AH42: =AE42*1.1 -> 54.45
B43: 32 | C43: INVERSÃO DE ROLAMENTO | J43: =ROUNDUP(((AH43*$N$3)+AH43),1) -> 35.6 | AE43: 32.3 | AH43: =AE43*1.1 -> 35.53
B44: 33 | C44: MOTORIZAÇÃO (VALOR DE MÃO DE OBRA, MOTORIZAÇÃO COBRADA SEPARADAMENTE) | J44: =ROUNDUP(((AH44*$N$3)+AH44),1) -> 60.5 | AA44: 22 | AB44: =AA44*1.1 -> 24.2 | AC44: =AB44*1.1 -> 26.62 | AD44: 29.282 | AE44: 55 | AH44: =AE44*1.1 -> 60.5
B45: 35 | C45: TROCA DE BANDÔ, BARRA NIVELADORA OU BASE (VALOR DE MÃO DE OBRA, BANDÔ, BARRA OU BASE SERÃO COBRADOS SEPARADAMENTE) | J45: =ROUNDUP(((AH45*$N$3)+AH45),1) -> 35.6 | AE45: 32.3 | AH45: =AE45*1.1 -> 35.53
B46: 36 | AH46: =AE46*1.1 -> 0
B47: SERVIÇOS - CORTINA PASSIONE | AH47: =AE47*1.1 -> 0
B48: ITEM | C48: DESCRIÇÃO | J48: VALOR À VISTA (R$) | AH48: =AE48*1.1 -> 0
B49: 37 | C49: CORTE NA ALTURA (CORTE MÍNIMO DE 7CM) | J49: =ROUNDUP(((AH49*$N$3)+AH49),1) -> 253.8 | AA49: 165 | AB49: =AA49*1.1 -> 181.5 | AC49: =AB49*1.05 -> 190.575 | AD49: 209.6325 | AE49: 230.7 | AH49: =AE49*1.1 -> 253.77
B50: 38 | C50: CORTE NA LARGURA | J50: =ROUNDUP(((AH50*$N$3)+AH50),1) -> 88.8 | AA50: 55 | AB50: =AA50*1.1 -> 60.5 | AC50: =AB50*1.1 -> 66.55 | AD50: 73.205 | AE50: 80.7 | AH50: =AE50*1.1 -> 88.77
B51: 39 | C51: TROCA DE TECIDO (VALOR DE MÃO DE OBRA, TECIDO SERÁ COBRADO SEPARADAMENTE) | J51: =ROUNDUP(((AH51*$N$3)+AH51),1) -> 88.8 | AA51: 55 | AB51: =AA51*1.1 -> 60.5 | AC51: =AB51*1.1 -> 66.55 | AD51: 73.205 | AE51: 80.7 | AH51: =AE51*1.1 -> 88.77
B52: 40 | C52: TROCA DE ABERTURA (VALOR DE MÃO DE OBRA, COMPONENTES SERÃO COBRADOS SEPARADAMENTE) | J52: =ROUNDUP(((AH52*$N$3)+AH52),1) -> 109.9 | AE52: 99.9 | AH52: =AE52*1.1 -> 109.89
B53: 41 | C53: REGULAGEM PEÇA MANUAL | J53: =ROUNDUP(((AH53*$N$3)+AH53),1) -> 26.7 | AA53: 16.5 | AB53: =AA53*1.1 -> 18.15 | AC53: =AB53*1.1 -> 19.965 | AD53: 21.9615 | AE53: 24.2 | AH53: =AE53*1.1 -> 26.62
B54: SERVIÇOS - CORTINA ROMANA | AH54: =AE54*1.1 -> 0
B55: ITEM | C55: DESCRIÇÃO | AA55: 33 | AB55: =AA55*1.1 -> 36.3 | AC55: =AB55*1.1 -> 39.93 | AD55: 43.923 | AE55: 48.4
B56: 42 | C56: CORTE NA ALTURA DA CORTINA ROMANA . (CORTE SOB CONSULTA DA PEÇA) | J56: =ROUNDUP(((AH56*$N$3)+AH56),1) -> 53.3 | AA56: 99 | AB56: =AA56*1.1 -> 108.9 | AC56: =AB56*1.05 -> 114.345 | AD56: 125.7795 | AE56: 138.4 | AH56: =AE55*1.1 -> 53.24
B57: 43 | C57: CORTE NA LARGURA DA CORTINA ROMANA TRADICIONAL (MODELO CLASSIC SOB CONSULTA) | J57: =ROUNDUP(((AH57*$N$3)+AH57),1) -> 152.3 | AA57: 22 | AB57: =AA57*1.1 -> 24.2 | AC57: =AB57*1.1 -> 26.62 | AD57: 29.282 | AE57: 32.3 | AH57: =AE56*1.1 -> 152.24
B58: 44 | C58: TROCA DO COMANDO. (VALOR DE MÃO DE OBRA, COMANDO SERÁ COBRADO SEPARADAMENTE) | J58: =ROUNDUP(((AH58*$N$3)+AH58),1) -> 35.6 | AA58: 22 | AB58: =AA58*1.1 -> 24.2 | AC58: =AB58*1.1 -> 26.62 | AD58: 29.282 | AE58: 32.3 | AH58: =AE57*1.1 -> 35.53
B59: 45 | C59: TROCA DE CABECEIRA (VALORES DE MÃO DE OBRA, COMPONENTES SERÃO COBRADOS SEPARADAMENTE) | J59: =ROUNDUP(((AH59*$N$3)+AH59),1) -> 35.6 | AA59: 22 | AB59: =AA59*1.1 -> 24.2 | AC59: =AB59*1.1 -> 26.62 | AD59: 29.282 | AE59: 32.3 | AH59: =AE58*1.1 -> 35.53
B60: 46 | C60: TROCA DE BASE (VALOR DE MÃO DE OBRA, BASE SERÁ COBRADA SEPARADAMENTE) | J60: =ROUNDUP(((AH60*$N$3)+AH60),1) -> 35.6 | AA60: 33 | AB60: =AA60*1.1 -> 36.3 | AC60: =AB60*1.1 -> 39.93 | AD60: 43.923 | AE60: 48.4 | AH60: =AE59*1.1 -> 35.53
B61: 47 | C61: TROCA DE CORDÃO (VALOR DE MÃO DE OBRA, CORDÃO COBRADO SEPARADAMENTE) | J61: =ROUNDUP(((AH61*$N$3)+AH61),1) -> 53.3 | AA61: 22 | AB61: =AA61*1.1 -> 24.2 | AC61: =AB61*1.1 -> 26.62 | AD61: 29.282 | AE61: 32.3 | AH61: =AE60*1.1 -> 53.24
B62: 48 | C62: TROCA DE LADO DO COMANDO | J62: =ROUNDUP(((AH62*$N$3)+AH62),1) -> 35.6 | AE62: 24.2 | AH62: =AE61*1.1 -> 35.53
B63: 49 | C63: REGULAGEM PEÇA MANUAL | J63: =ROUNDUP(((AH63*$N$3)+AH63),1) -> 26.7 | AE63: 49.5 | AH63: =AE62*1.1 -> 26.62
B64: 50 | C64: REGULAGEM PEÇA MOTORIZADA | J64: =ROUNDUP(((AH64*$N$3)+AH64),1) -> 54.5 | AH64: =AE63*1.1 -> 54.45
K65: Página 4 - | L65: =Rolô!L2 -> 2026 - v.03 | AH65: =AE65*1.1 -> 0
B66: ASSISTÊNCIA TÉCNICA | AH66: =AE66*1.1 -> 0
AH67: =AE67*1.1 -> 0
AH68: =AE68*1.1 -> 0
B69: SERVIÇOS - CORTINA PAINEL | AH69: =AE69*1.1 -> 0
B70: ITEM | C70: DESCRIÇÃO | J70: VALOR À VISTA (R$) | AH70: =AE70*1.1 -> 0
B71: 51 | C71: CORTE NA ALTURA DA CORTINA PAINEL EUROPA (COBRADO POR FOLHA) | J71: =ROUNDUP(((AH71*$N$3)+AH71),1) -> 35.6 | AA71: 22 | AB71: =AA71*1.1 -> 24.2 | AC71: =AB71*1.1 -> 26.62 | AD71: 29.282 | AE71: 32.3 | AH71: =AE71*1.1 -> 35.53
B72: 52 | C72: CORTE NA LARGURA DA CORTINA PAINEL EUROPA (COBRADO POR FOLHA) | J72: =ROUNDUP(((AH72*$N$3)+AH72),1) -> 53.3 | AA72: 33 | AB72: =AA72*1.1 -> 36.3 | AC72: =AB72*1.1 -> 39.93 | AD72: 43.923 | AE72: 48.4 | AH72: =AE72*1.1 -> 53.24
B73: 53 | C73: CORTE NA LARGURA DO TRILHO DESLIZANTE | J73: =ROUNDUP(((AH73*$N$3)+AH73),1) -> 53.3 | AA73: 33 | AB73: =AA73*1.1 -> 36.3 | AC73: =AB73*1.1 -> 39.93 | AD73: 43.923 | AE73: 48.4 | AH73: =AE73*1.1 -> 53.24
B74: 54 | C74: TROCA DE ABERTURA (VALOR DE MÃO DE OBRA, COMPONENTES SERÃO COBRADOS SEPARADAMENTE) | J74: =ROUNDUP(((AH74*$N$3)+AH74),1) -> 35.6 | AA74: 22 | AB74: =AA74*1.1 -> 24.2 | AC74: =AB74*1.1 -> 26.62 | AD74: 29.282 | AE74: 32.3 | AH74: =AE74*1.1 -> 35.53
B75: 55 | C75: TROCA DE BASE (VALOR DE MÃO DE OBRA, BASES SERÃO COBRADOS SEPARADAMENTE) | J75: =ROUNDUP(((AH75*$N$3)+AH75),1) -> 35.6 | AA75: 44 | AB75: =AA75*1.1 -> 48.4 | AC75: =AB75*1.1 -> 53.24 | AD75: 58.564 | AE75: 32.3 | AH75: =AE75*1.1 -> 35.53
B76: SERVIÇOS - CORTINA DE TETO | AH76: =AE76*1.1 -> 0
B77: ITEM | C77: DESCRIÇÃO | J77: VALOR À VISTA (R$) | AH77: =AE77*1.1 -> 0
B78: 56 | C78: CORTE NA ALTURA | J78: =ROUNDUP(((AH78*$N$3)+AH78),1) -> 203.1 | AA78: 132 | AB78: =AA78*1.1 -> 145.2 | AC78: =AB78*1.05 -> 152.46 | AD78: 167.706 | AE78: 184.6 | AH78: =AE78*1.1 -> 203.06
B79: 57 | C79: CORTE NA LARGURA | J79: =ROUNDUP(((AH79*$N$3)+AH79),1) -> 372.2 | AA79: 242 | AB79: =AA79*1.1 -> 266.2 | AC79: =AB79*1.05 -> 279.51 | AD79: 307.461 | AE79: 338.3 | AH79: =AE79*1.1 -> 372.13
B80: 58 | C80: CORTE NA LARGURA E ALTURA | J80: =ROUNDUP(((AH80*$N$3)+AH80),1) -> 473.7 | AA80: 308 | AB80: =AA80*1.1 -> 338.8 | AC80: =AB80*1.05 -> 355.74 | AD80: 391.314 | AE80: 430.6 | AH80: =AE80*1.1 -> 473.66
B81: SERVIÇOS - PERSIANA VERTICAL | AH81: =AE81*1.1 -> 0
B82: ITEM | C82: DESCRIÇÃO | J82: VALOR À VISTA (R$) | AH82: =AE82*1.1 -> 0
B83: 59 | C83: CORTE NA ALTURA PERSIANA VERTICAL - COBRADO O VALOR DE R$1,65 POR LAMINA CORTADA | J83: =ROUNDUP(((AE83*$N$3)+AE83),1) -> 0 | AH83: =AE83*1.1 -> 0
B84: 60 | C84: CORTE DO TRILHO | J84: =ROUNDUP(((AH84*$N$3)+AH84),1) -> 35.6 | AA84: 99 | AB84: =AA84*1.1 -> 108.9 | AC84: =AB84*1.05 -> 114.345 | AD84: 125.7795 | AE84: 32.3 | AH84: =AE84*1.1 -> 35.53
B85: 61 | C85: CORTE DE BANDÔ | J85: =ROUNDUP(((AH85*$N$3)+AH85),1) -> 35.6 | AA85: 99 | AB85: =AA85*1.1 -> 108.9 | AC85: =AB85*1.05 -> 114.345 | AD85: 125.7795 | AE85: 32.3 | AH85: =AE85*1.1 -> 35.53
B86: 62 | C86: REGULAGEM PEÇA MANUAL | J86: =ROUNDUP(((AH86*$N$3)+AH86),1) -> 26.7 | AA86: 22 | AB86: =AA86*1.1 -> 24.2 | AC86: =AB86*1.1 -> 26.62 | AD86: 29.282 | AE86: 24.2 | AH86: =AE86*1.1 -> 26.62
B87: 63 | C87: TROCA DE ABERTURA (VALOR DE MÃO DE OBRA, COMPONENTES SERÃO COBRADOS SEPARADAMENTE) | J87: =ROUNDUP(((AH87*$N$3)+AH87),1) -> 35.6 | AA87: 22 | AB87: =AA87*1.1 -> 24.2 | AC87: =AB87*1.1 -> 26.62 | AD87: 29.282 | AE87: 32.3 | AH87: =AE87*1.1 -> 35.53
B88: 64 | C88: TROCA DE COMANDO (VALOR DE MÃO DE OBRA, COMANDO SERÁ COBRADO SEPARADAMENTE) | J88: =ROUNDUP(((AH88*$N$3)+AH88),1) -> 35.6 | AA88: 16.5 | AB88: =AA88*1.1 -> 18.15 | AC88: =AB88*1.1 -> 19.965 | AD88: 21.9615 | AE88: 32.3 | AH88: =AE88*1.1 -> 35.53
B89: SERVIÇOS - PERSIANA HORIZONTAL DE ALUMÍNIO | AH89: =AE89*1.1 -> 0
B90: ITEM | C90: DESCRIÇÃO | J90: VALOR À VISTA (R$) | AH90: =AE90*1.1 -> 0
B91: 65 | C91: CORTE NA ALTURA PH 16MM, 25MM | J91: =ROUNDUP(((AH91*$N$3)+AH91),1) -> 53.3 | AA91: 33 | AB91: =AA91*1.1 -> 36.3 | AC91: =AB91*1.1 -> 39.93 | AD91: 43.923 | AE91: 48.4 | AH91: =AE91*1.1 -> 53.24
B92: 66 | C92: CORTE NA ALTURA PH 50MM | J92: =ROUNDUP(((AH92*$N$3)+AH92),1) -> 71 | AA92: 44 | AB92: =AA92*1.1 -> 48.4 | AC92: =AB92*1.1 -> 53.24 | AD92: 58.564 | AE92: 64.5 | AH92: =AE92*1.1 -> 70.95
B93: 67 | C93: CORTE NA LARGURA PH 16MM, 25MM (CORTE SOB CONSULTA DA PEÇA) | J93: =ROUNDUP(((AH93*$N$3)+AH93),1) -> 88.8 | AA93: 104.5 | AB93: =AA93*1.1 -> 114.95 | AC93: =AB93*1.05 -> 120.6975 | AD93: 132.76725 | AE93: 80.7 | AH93: =AE93*1.1 -> 88.77
B94: 68 | C94: CORTE NA LARGURA PH 50MM (CORTE SOB CONSULTA DA PEÇA) | J94: =ROUNDUP(((AH94*$N$3)+AH94),1) -> 160.8 | AA94: 55 | AB94: =AA94*1.1 -> 60.5 | AC94: =AB94*1.1 -> 66.55 | AD94: 73.205 | AE94: 146.1 | AH94: =AE94*1.1 -> 160.71
B95: 69 | C95: REGULAGEM PEÇA MANUAL | J95: =ROUNDUP(((AH95*$N$3)+AH95),1) -> 26.7 | AA95: 16.5 | AB95: =AA95*1.1 -> 18.15 | AC95: =AB95*1.1 -> 19.965 | AD95: 21.9615 | AE95: 24.2 | AH95: =AE95*1.1 -> 26.62
B96: 70 | C96: REGULAGEM PEÇA MOTORIZADA | J96: =ROUNDUP(((AH96*$N$3)+AH96),1) -> 54.5 | AA96: 22 | AB96: =AA96*1.1 -> 24.2 | AC96: =AB96*1.1 -> 26.62 | AD96: 29.282 | AE96: 49.5 | AH96: =AE96*1.1 -> 54.45
B97: 71 | C97: TROCA DE LADO DO COMANDO (PARA PERSIANAS STANDARD SERÁ NECESSÁRIO TAMBÉM A TROCA DA CABECEIRA, COBRADA SEPARADAMENTE) | J97: =ROUNDUP(((AH97*$N$3)+AH97),1) -> 35.6 | AE97: 32.3 | AH97: =AE97*1.1 -> 35.53
B98: 72 | AA98: 33 | AB98: =AA98*1.1 -> 36.3 | AC98: =AB98*1.1 -> 39.93 | AD98: 43.923
B99: 73 | C99: TROCA DE COMANDO (VALOR DE MÃO DE OBRA, COMPONENTES SERÃO COBRADOS SEPARADAMENTE) | J99: =ROUNDUP(((AH99*$N$3)+AH99),1) -> 35.6 | AE99: 32.3 | AH99: =AE99*1.1 -> 35.53
B100: 74 | C100: TROCA DE CORDÃO PH 16MM, 25MM (VALOR DE MÃO DE OBRA, CORDÃO SERÁ COBRADO SEPARADAMENTE) | J100: =ROUNDUP(((AH100*$N$3)+AH100),1) -> 53.3 | AA100: 22 | AB100: =AA100*1.1 -> 24.2 | AC100: =AB100*1.1 -> 26.62 | AD100: 29.282 | AE100: 48.4 | AH100: =AE100*1.1 -> 53.24
B101: 75 | AA101: 22 | AB101: =AA101*1.1 -> 24.2 | AC101: =AB101*1.1 -> 26.62 | AD101: 29.282
B102: 76 | C102: TROCA DE CORDÃO PH 50MM (VALOR DE MÃO DE OBRA, CORDÃO SERÁ COBRADO SEPARADAMENTE) | J102: =ROUNDUP(((AH102*$N$3)+AH102),1) -> 73.3 | AA102: 22 | AB102: =AA102*1.1 -> 24.2 | AC102: =AB102*1.1 -> 26.62 | AD102: 29.282 | AE102: 66.6 | AH102: =AE102*1.1 -> 73.26
B103: 77 | C103: TROCA DE CADARÇO (ESCADINHA) PH 16MM, 25MM (VALOR DE MÃO DE OBRA, CADARÇO SERÁ COBRADO SEPARADAMENTE) | J103: =ROUNDUP(((AH103*$N$3)+AH103),1) -> 88.8 | AA103: 33 | AB103: =AA103*1.1 -> 36.3 | AC103: =AB103*1.1 -> 39.93 | AD103: 43.923 | AE103: 80.7 | AH103: =AE103*1.1 -> 88.77
...

Sheet Rolô
K2: Página 6 - | L2: 2026 - v.03 | N2: * DIGITE A PORCENTAGEM PARA MARKUP
N3: 0
B4: PRODUTO EM CONFORMIDADE COM A NORMA ABNT NBR 16234: 2014
B6: ITEM | C6: COLEÇÃO | E6: COR | H6: LAR. MAX. | I6: VALOR À VISTA (R$)/M² | K6: IPI | AA6: 42491 | AB6: 43026 | AC6: 43258 | AE6: 43862 | AH6: 43952 | AI6: 44105 | AJ6: 44256 | AK6: 44287 | AL6: 44317 | AM6: 44348 | AN6: 44378 | AO6: 44501 | AS6: 44682 | AT6: 45383 | BI6: 45658
B7: 1 | C7: SCREEN 1% | E7: 0001, 0005 e 0006, 1010, 1030 e 1031 | H7: 3 | I7: =ROUNDUP(((BJ7*$N$3)+BJ7),1) -> 166.6 | K7: 0 | AA7: 160 | AB7: 160 | AC7: =AB7*1.1 -> 176 | AE7: =AC7*1.06 -> 186.56 | AH7: =AE7*1.1 -> 205.216 | AI7: =AH7 -> 205.216 | AJ7: =AI7 -> 205.216 | AN7: =AJ7 -> 205.216 | AO7: 205.3 | AP7: =AO7*1.06 -> 217.618 | AS7: 185 | AT7: =AS7-((AS7*10)/100) -> 166.5 | AV7: =AT7*1.07 -> 178.155 | BI7: =AV7*1.1 -> 195.9705 | BJ7: =BI7+(BI7-(BI7*1.15)) -> 166.57493
B8: 2 | AA8: 192 | AB8: 192 | AC8: =AB8*1.1 -> 211.2 | AE8: =AC8*1.06 -> 223.872 | AH8: =AE8*1.15 -> 257.4528 | AI8: =AH8*1.08 -> 278.04902 | AJ8: =AI8*1.05 -> 291.95148 | AN8: =AJ8 -> 291.95148 | AO8: 292 | AP8: =AO8*1.06 -> 309.52 | AV8: =AT8*1.07 -> 0 | BI8: =AV8*1.1 -> 0 | BJ8: =BI8+(BI8-(BI8*1.15)) -> 0
B9: 3 | C9: SCREEN 3% | E9: 3001, 3002, 3008, 3017, 3060 e 3061 | H9: 3 | I9: =ROUNDUP(((BJ9*$N$3)+BJ9),1) -> 157.6 | K9: 0 | AA9: 140.5 | AB9: 140.5 | AC9: =AB9*1.1 -> 154.55 | AE9: =AC9*1.06 -> 163.823 | AH9: =AE9 -> 163.823 | AI9: 163.9 | AJ9: =AI9 -> 163.9 | AN9: =AJ9*1.03 -> 168.817 | AO9: 168.9 | AP9: =AO9*1.06 -> 179.034 | AS9: 175 | AT9: =AS9-((AS9*10)/100) -> 157.5 | AV9: =AT9*1.07 -> 168.525 | BI9: =AV9*1.1 -> 185.3775 | BJ9: =BI9+(BI9-(BI9*1.15)) -> 157.57088
B10: 4 | E10: 3009 ao 3011, 3018 e 3019 | H10: 3 | I10: =ROUNDUP(((BJ10*$N$3)+BJ10),1) -> 201.2 | K10: 0 | AA10: 140.5 | AB10: 140.5 | AC10: =AB10*1.1 -> 154.55 | AE10: =AC10*1.06 -> 163.823 | AH10: =AE10*1.05 -> 172.01415 | AI10: =AH10 -> 172.01415 | AJ10: =AI10*1.05 -> 180.61486 | AN10: =AJ10*1.05 -> 189.6456 | AO10: 189.7 | AP10: =AO10*1.06 -> 201.082 | AS10: =AP10 -> 201.082 | AT10: =AS10 -> 201.082 | AV10: =AT10*1.07 -> 215.15774 | BI10: =AV10*1.1 -> 236.67351 | BJ10: =BI10+(BI10-(BI10*1.15)) -> 201.17249
B11: 5 | E11: 3012, 3013 | H11: 3 | I11: =ROUNDUP(((BJ11*$N$3)+BJ11),1) -> 191.7 | K11: 0 | AJ11: 180.61 | AN11: =AJ11 -> 180.61 | AO11: 180.7 | AP11: =AO11*1.06 -> 191.542 | AS11: =AP11 -> 191.542 | AT11: =AS11 -> 191.542 | AV11: =AT11*1.07 -> 204.94994 | BI11: =AV11*1.1 -> 225.44493 | BJ11: =BI11+(BI11-(BI11*1.15)) -> 191.62819
B12: 6 | E12: 3014 e 3015 | H12: 3 | I12: =ROUNDUP(((BJ12*$N$3)+BJ12),1) -> 216.3 | K12: 0 | AE12: 163.9 | AH12: =AE12*1.15 -> 188.485 | AI12: =AH12 -> 188.485 | AJ12: =AI12*1.05 -> 197.90925 | AN12: =AJ12*1.03 -> 203.84653 | AO12: 203.9 | AP12: =AO12*1.06 -> 216.134 | AS12: =AP12 -> 216.134 | AT12: =AS12 -> 216.134 | AV12: =AT12*1.07 -> 231.26338 | BI12: =AV12*1.1 -> 254.38972 | BJ12: =BI12+(BI12-(BI12*1.15)) -> 216.23126
B13: 7 | AA13: 169 | AB13: 169 | AC13: =AB13*1.1 -> 185.9 | AE13: 197.1 | AH13: =AE13*1.15 -> 226.665 | AI13: =AH13*1.08 -> 244.7982 | AJ13: =AI13*1.05 -> 257.03811 | AN13: =AJ13 -> 257.03811 | AO13: 257.1 | AP13: =AO13*1.06 -> 272.526 | AV13: =AT13*1.07 -> 0 | BI13: =AV13*1.1 -> 0 | BJ13: =BI13+(BI13-(BI13*1.15)) -> 0
B14: 8 | C14: SCREEN 5% | E14: 3070 ao 3076, 3078, 3079 | H14: 3 | I14: =ROUNDUP(((BJ14*$N$3)+BJ14),1) -> 142.6 | K14: 0 | AA14: 132.4 | AB14: 132.4 | AC14: =AB14*1.1 -> 145.64 | AE14: =AC14*1.06 -> 154.3784 | AH14: =AE14 -> 154.3784 | AI14: =AH14 -> 154.3784 | AJ14: =AI14 -> 154.3784 | AN14: =AJ14*1.03 -> 159.00975 | AO14: 159.1 | AP14: =AO14*1.06 -> 168.646 | AS14: 158.3 | AT14: =AS14-((AS14*10)/100) -> 142.47 | AV14: =AT14*1.07 -> 152.4429 | BI14: =AV14*1.1 -> 167.68719 | BJ14: =BI14+(BI14-(BI14*1.15)) -> 142.53411
B15: 9 | E15: 3096, 3097 E 3098 | H15: 2.5 | AA15: 159 | AB15: 159 | AC15: =AB15*1.1 -> 174.9 | AE15: =AC15*1.06 -> 185.394 | AH15: =AE15*1.15 -> 213.2031 | AI15: =AH15*1.08 -> 230.25935 | AJ15: =AI15*1.05 -> 241.77232 | AN15: =AJ15 -> 241.77232 | AO15: 241.8 | AP15: =AO15*1.06 -> 256.308 | AV15: =AT15*1.07 -> 0 | BI15: =AV15*1.1 -> 0 | BJ15: =BI15+(BI15-(BI15*1.15)) -> 0
B16: 10 | C16: SCREEN CRISTAL 5% | E16: 3100 | H16: 3 | I16: =ROUNDUP(((BJ16*$N$3)+BJ16),1) -> 228.6 | K16: 0 | AA16: 160 | AB16: 160 | AC16: =AB16*1.1 -> 176 | AE16: =AC16*1.06 -> 186.56 | AH16: =AE16*1.1 -> 205.216 | AI16: =AH16 -> 205.216 | AJ16: =AI16*1.05 -> 215.4768 | AN16: =AJ16 -> 215.4768 | AO16: 215.5 | AP16: =AO16*1.06 -> 228.43 | AS16: =AP16 -> 228.43 | AT16: =AS16 -> 228.43 | AV16: =AT16*1.07 -> 244.4201 | BI16: =AV16*1.1 -> 268.86211 | BJ16: =BI16+(BI16-(BI16*1.15)) -> 228.53279
B17: 11 | C17: SCREEN RÚSTICO 3% | E17: 3150 e 3151 | H17: 3 | I17: =ROUNDUP(((BJ17*$N$3)+BJ17),1) -> 219.1 | K17: 0 | AA17: 153.4 | AB17: 153.4 | AC17: =AB17*1.1 -> 168.74 | AE17: =AC17*1.06 -> 178.8644 | AH17: =AE17*1.1 -> 196.75084 | AI17: =AH17 -> 196.75084 | AJ17: =AI17*1.05 -> 206.58838 | AN17: =AJ17 -> 206.58838 | AO17: 206.6 | AP17: =AO17*1.06 -> 218.996 | AS17: =AP17 -> 218.996 | AT17: =AS17 -> 218.996 | AV17: =AT17*1.07 -> 234.32572 | BI17: =AV17*1.1 -> 257.75829 | BJ17: =BI17+(BI17-(BI17*1.15)) -> 219.09455
B18: 12 | C18: SCREEN RÚSTICO 5% | E18: 3155 e 3156 | H18: 3 | I18: =ROUNDUP(((BJ18*$N$3)+BJ18),1) -> 241.1 | K18: 0 | AI18: 206.59 | AJ18: =AI18*1.1 -> 227.249 | AN18: =AJ18 -> 227.249 | AO18: 227.3 | AP18: =AO18*1.06 -> 240.938 | AS18: =AP18 -> 240.938 | AT18: =AS18 -> 240.938 | AV18: =AT18*1.07 -> 257.80366 | BI18: =AV18*1.1 -> 283.58403 | BJ18: =BI18+(BI18-(BI18*1.15)) -> 241.04642
B19: 13 | E19: 3159, 3160, 3161, 3162 e 3163 | H19: 2.5 | I19: =ROUNDUP(((BJ19*$N$3)+BJ19),1) -> 209.2 | K19: 0 | AE19: =#REF! -> #REF! | AH19: =AE19 -> #REF! | AI19: =AH19*1.05 -> #REF! | AJ19: =AI19*1.05 -> #REF! | AN19: =AJ19 -> #REF! | AO19: 197.2 | AP19: =AO19*1.06 -> 209.032 | AS19: =AP19 -> 209.032 | AT19: =AS19 -> 209.032 | AV19: =AT19*1.07 -> 223.66424 | BI19: =AV19*1.1 -> 246.03066 | BJ19: =BI19+(BI19-(BI19*1.15)) -> 209.12606
B20: 14 | AA20: 179.3 | AB20: 179.3 | AC20: =AB20*1.1 -> 197.23 | AE20: =AC20*1.06 -> 209.0638 | AH20: =AE20*1.15 -> 240.42337 | AI20: =AH20*1.05 -> 252.44454 | AJ20: =AI20*1.05 -> 265.06677 | AN20: =AJ20 -> 265.06677 | AO20: 265.1 | AP20: =AO20*1.06 -> 281.006 | AS20: =AP20 -> 281.006 | AT20: =AS20 -> 281.006 | AV20: =AT20*1.07 -> 300.67642 | BI20: =AV20*1.1 -> 330.74406 | BJ20: =BI20+(BI20-(BI20*1.15)) -> 281.13245
B21: 15 | C21: SCREEN REFLEX | E21: 3121 e 3122 e 3123 | H21: 3 | I21: =ROUNDUP(((BJ21*$N$3)+BJ21),1) -> 256.2 | K21: 0 | AA21: 179.3 | AB21: 179.3 | AC21: =AB21*1.1 -> 197.23 | AE21: =AC21*1.06 -> 209.0638 | AH21: =AE21*1.05 -> 219.51699 | AI21: =AH21 -> 219.51699 | AJ21: =AI21*1.1 -> 241.46869 | AN21: =AJ21 -> 241.46869 | AO21: 241.5 | AP21: =AO21*1.06 -> 255.99 | AS21: =AP21 -> 255.99 | AT21: =AS21 -> 255.99 | AV21: =AT21*1.07 -> 273.9093 | BI21: =AV21*1.1 -> 301.30023 | BJ21: =BI21+(BI21-(BI21*1.15)) -> 256.1052
B22: 16 | C22: SCREEN BK | E22: 3200, 3201 e 3203 | H22: 2.5 | I22: =ROUNDUP(((BJ22*$N$3)+BJ22),1) -> 230.7 | K22: 0 | AS22: 281.1 | AT22: =AS22-((AS22*18)/100) -> 230.502 | AV22: =AT22*1.07 -> 246.63714 | BI22: =AV22*1.1 -> 271.30085 | BJ22: =BI22+(BI22-(BI22*1.15)) -> 230.60573
B23: 17 | C23: IBIZA | E23: 3350, 3351 e 3353 | H23: 2.6 | I23: =ROUNDUP(((BJ23*$N$3)+BJ23),1) -> 153.5 | K23: 0 | AA23: 103.3 | AB23: 111.6 | AC23: =AB23*1.1 -> 122.76 | AE23: =AC23*1.06 -> 130.1256 | AH23: =AE23*1.1 -> 143.13816 | AI23: =AH23*1.08 -> 154.58921 | AJ23: =AI23*1.1 -> 170.04813 | AN23: =AJ23 -> 170.04813 | AO23: 170.1 | AP23: =AO23*1.06 -> 180.306 | AS23: 180.4 | AT23: =AS23-((AS23*15)/100) -> 153.34 | AV23: =AT23*1.07 -> 164.0738 | BI23: =AV23*1.1 -> 180.48118 | BJ23: =BI23+(BI23-(BI23*1.15)) -> 153.409
B24: 18 | C24: BLACKOUT PINPOINT | E24: 0180 ao 0183 e 0186 ao 0190 - larg. especial 2.5 | H24: 2.5 | I24: =ROUNDUP(((BJ24*$N$3)+BJ24),1) -> 148.3 | K24: 0.1 | AA24: 120.4 | AB24: 120.4 | AC24: =AB24*1.1 -> 132.44 | AE24: =AC24*1.06 -> 140.3864 | AH24: =AE24*1.05 -> 147.40572 | AI24: =AH24*1.05 -> 154.77601 | AJ24: =AI24*1.05 -> 162.51481 | AN24: =AJ24*1.05 -> 170.64055 | AO24: 170.7 | AP24: =AO24*1.06 -> 180.942 | AS24: 164.6 | AT24: =AS24-((AS24*10)/100) -> 148.14 | AV24: =AT24*1.07 -> 158.5098 | BI24: =AV24*1.1 -> 174.36078 | BJ24: =BI24+(BI24-(BI24*1.15)) -> 148.20666
B25: 19 | AE25: 140.39 | AH25: =AE25*1.05 -> 147.4095 | AS25: =AP25 -> 0 | AT25: =AS25-((AS25*10)/100) -> 0 | AV25: =AT25*1.07 -> 0 | BI25: =AV25*1.1 -> 0 | BJ25: =BI25+(BI25-(BI25*1.15)) -> 0
B26: 20 | E26: 0180 ao 0183 e 0186, 0187 e 0190 - larg. especial 3 | H26: 3 | I26: =ROUNDUP(((BJ26*$N$3)+BJ26),1) -> 152.8 | K26: 0.1 | AE26: 140.39 | AH26: =AE26*1.1 -> 154.429 | AI26: =AH26*1.05 -> 162.15045 | AJ26: =AI26*1.05 -> 170.25797 | AN26: =AJ26*1.05 -> 178.77087 | AO26: 178.8 | AP26: =AO26*1.06 -> 189.528 | AS26: 169.7 | AT26: =AS26-((AS26*10)/100) -> 152.73 | AV26: =AT26*1.07 -> 163.4211 | BI26: =AV26*1.1 -> 179.76321 | BJ26: =BI26+(BI26-(BI26*1.15)) -> 152.79873
B27: 21 | E27: 0180 ao 0183 e 0186, 0187 e 0190 | H27: 2 | I27: =ROUNDUP(((BJ27*$N$3)+BJ27),1) -> 139.9 | K27: 0.1 | AA27: 105.3 | AB27: 105.3 | AC27: =AB27*1.1 -> 115.83 | AE27: =AC27*1.06 -> 122.7798 | AH27: =AE27*1.05 -> 128.91879 | AI27: =AH27*1.05 -> 135.36473 | AJ27: =AI27*1.1 -> 148.9012 | AN27: =AJ27*1.05 -> 156.34626 | AO27: 156.4 | AP27: =AO27*1.06 -> 165.784 | AS27: 155.3 | AT27: =AS27-((AS27*10)/100) -> 139.77 | AV27: =AT27*1.07 -> 149.5539 | BI27: =AV27*1.1 -> 164.50929 | BJ27: =BI27+(BI27-(BI27*1.15)) -> 139.8329
B28: 22 | AB28: 105.3 | AC28: =AB28*1.1 -> 115.83 | AE28: =AC28*1.06 -> 122.7798 | AH28: =AE28*1.05 -> 128.91879 | AS28: =AP28 -> 0 | AT28: =AS28-((AS28*10)/100) -> 0 | AV28: =AT28*1.07 -> 0 | BI28: =AV28*1.1 -> 0 | BJ28: =BI28+(BI28-(BI28*1.15)) -> 0
B29: 23 | C29: REQUINTE BK | E29: 0088 | H29: 2 | I29: =ROUNDUP(((BJ29*$N$3)+BJ29),1) -> 175.8 | K29: 0 | AH29: 154.2 | AI29: =AH29*1.08 -> 166.536 | AJ29: 174.79 | AN29: =AJ29*1.05 -> 183.5295 | AO29: 183.6 | AP29: =AO29*1.1 -> 201.96 | AS29: =AP29 -> 201.96 | AT29: =AS29-((AS29*13)/100) -> 175.7052 | AV29: =AT29*1.07 -> 188.00456 | BI29: =AV29*1.1 -> 206.80502 | BJ29: =BI29+(BI29-(BI29*1.15)) -> 175.78427
B30: 24 | E30: 0101, 0102, 3042, 3044, 7517 ao 7523 | H30: 3 | I30: =ROUNDUP(((BJ30*$N$3)+BJ30),1) -> 136.2 | K30: 0 | AA30: 116.5 | AB30: 125.9 | AC30: =AB30*1.1 -> 138.49 | AE30: =AC30*1.06 -> 146.7994 | AH30: =AE30 -> 146.7994 | AI30: =AH30*1.08 -> 158.54335 | AJ30: 166.23 | AN30: =AJ30*1.02 -> 169.5546 | AO30: 169.6 | AP30: =AO30*1.1 -> 186.56 | AS30: =AP30 -> 186.56 | AT30: 136.1 | AV30: =AT30*1.07 -> 145.627 | BI30: =AV30*1.1 -> 160.1897 | BJ30: =BI30+(BI30-(BI30*1.15)) -> 136.16125
B31: 25 | E31: 0103 | H31: 2.5 | I31: =ROUNDUP(((BJ31*$N$3)+BJ31),1) -> 136.2 | K31: 0 | AA31: 116.5 | AB31: 125.9 | AC31: =AB31*1.1 -> 138.49 | AE31: =AC31*1.06 -> 146.7994 | AH31: =AE31*1.05 -> 154.13937 | AI31: =AH31 -> 154.13937 | AJ31: =AI31*1.1 -> 169.55331 | AN31: =AJ31 -> 169.55331 | AO31: 169.6 | AP31: =AO31*1.06 -> 179.776 | AS31: 151.2 | AT31: =AS31-((AS31*10)/100) -> 136.08 | AV31: =AT31*1.07 -> 145.6056 | BI31: =AV31*1.1 -> 160.16616 | BJ31: =BI31+(BI31-(BI31*1.15)) -> 136.14124
B32: 26 | E32: 0105, 7511 ao 7516 | H32: 3 | I32: =ROUNDUP(((BJ32*$N$3)+BJ32),1) -> 162.3 | K32: 0 | AT32: 162.2 | AV32: =AT32*1.07 -> 173.554 | BI32: =AV32*1.1 -> 190.9094 | BJ32: =BI32+(BI32-(BI32*1.15)) -> 162.27299
B33: 27 | E33: 0106 e 0107 | H33: 2.4 | I33: =ROUNDUP(((BJ33*$N$3)+BJ33),1) -> 162.3 | K33: 0 | AA33: 116.5 | AB33: 125.9 | AC33: =AB33*1.1 -> 138.49 | AE33: =AC33*1.06 -> 146.7994 | AH33: =AE33*1.05 -> 154.13937 | AI33: =AH33 -> 154.13937 | AJ33: =AI33*1.15 -> 177.26028 | AN33: =AJ33 -> 177.26028 | AO33: 177.3 | AP33: =AO33*1.06 -> 187.938 | AS33: 162.2 | AT33: =AS33 -> 162.2 | AV33: =AT33*1.07 -> 173.554 | BI33: =AV33*1.1 -> 190.9094 | BJ33: =BI33+(BI33-(BI33*1.15)) -> 162.27299
B34: 28 | E34: 3031 | H34: 2.4 | I34: =ROUNDUP(((BJ34*$N$3)+BJ34),1) -> 204.2 | K34: 0 | AA34: 126.5 | AB34: 136.7 | AC34: =AB34*1.1 -> 150.37 | AE34: =AC34*1.06 -> 159.3922 | AH34: =AE34*1.05 -> 167.36181 | AI34: =AH34 -> 167.36181 | AJ34: =AI34*1.15 -> 192.46608 | AN34: =AJ34 -> 192.46608 | AO34: 192.5 | AP34: =AO34*1.06 -> 204.05 | AS34: =AP34 -> 204.05 | AT34: =AS34 -> 204.05 | AV34: =AT34*1.07 -> 218.3335 | BI34: =AV34*1.1 -> 240.16685 | BJ34: =BI34+(BI34-(BI34*1.15)) -> 204.14182
B35: 29 | E35: 3038 | H35: 3 | I35: =ROUNDUP(((BJ35*$N$3)+BJ35),1) -> 155.8 | K35: 0 | AA35: 132.4 | AB35: 143 | AC35: =AB35*1.1 -> 157.3 | AE35: =AC35*1.1 -> 173.03 | AH35: =AE35*1.1 -> 190.333 | AI35: =AH35*1.08 -> 205.55964 | AJ35: 226.14 | AN35: =AJ35*1.01 -> 228.4014 | AO35: 228.5 | AP35: =AO35*1.06 -> 242.21 | AS35: 207.6 | AT35: =AS35-((AS35*25)/100) -> 155.7 | AV35: =AT35*1.07 -> 166.599 | BI35: =AV35*1.1 -> 183.2589 | BJ35: =BI35+(BI35-(BI35*1.15)) -> 155.77007
B36: 30 | E36: 3037 | H36: 3 | I36: =ROUNDUP(((BJ36*$N$3)+BJ36),1) -> 155.8 | K36: 0 | AT36: 155.7 | AV36: =AT36*1.07 -> 166.599 | BI36: =AV36*1.1 -> 183.2589 | BJ36: =BI36+(BI36-(BI36*1.15)) -> 155.77007
B37: 31 | E37: 3040 | H37: 2.8 | I37: =ROUNDUP(((BJ37*$N$3)+BJ37),1) -> 207.7 | K37: 0 | AA37: 116.5 | AB37: 125.9 | AC37: =AB37*1.1 -> 138.49 | AE37: =AC37*1.1 -> 152.339 | AH37: =AE37*1.15 -> 175.18985 | AI37: =AH37*1.08 -> 189.20504 | AJ37: =AI37*1.15 -> 217.58579 | AN37: =AJ37*1.05 -> 228.46508 | AO37: 228.5 | AP37: =AO37*1.06 -> 242.21 | AS37: 207.6 | AT37: =AS37 -> 207.6 | AV37: =AT37*1.07 -> 222.132 | BI37: =AV37*1.1 -> 244.3452 | BJ37: =BI37+(BI37-(BI37*1.15)) -> 207.69342
B38: 32 | E38: 3039 | H38: 3 | I38: =ROUNDUP(((BJ38*$N$3)+BJ38),1) -> 207.7 | K38: 0 | AT38: 207.6 | AV38: =AT38*1.07 -> 222.132 | BI38: =AV38*1.1 -> 244.3452 | BJ38: =BI38+(BI38-(BI38*1.15)) -> 207.69342
B39: 33 | E39: 3043 | H39: 2.5 | I39: =ROUNDUP(((BJ39*$N$3)+BJ39),1) -> 188.1 | K39: 0 | AC39: 138.49 | AE39: =AC39*1.06 -> 146.7994 | AH39: =AE39*1.05 -> 154.13937 | AI39: =AH39*1.08 -> 166.47052 | AJ39: 174.66 | AN39: =AJ39*1.015 -> 177.2799 | AO39: 177.3 | AP39: =AO39*1.06 -> 187.938 | AS39: =AP39 -> 187.938 | AT39: =AS39 -> 187.938 | AV39: =AT39*1.07 -> 201.09366 | BI39: =AV39*1.1 -> 221.20303 | BJ39: =BI39+(BI39-(BI39*1.15)) -> 188.02257
B40: 34 | E40: 3041 | H40: 2.5 | I40: =ROUNDUP(((BJ40*$N$3)+BJ40),1) -> 162.3 | K40: 0 | AA40: 116.5 | AB40: 125.9 | AC40: =AB40*1.1 -> 138.49 | AE40: =AC40*1.06 -> 146.7994 | AH40: =AE40*1.05 -> 154.13937 | AI40: =AH40 -> 154.13937 | AJ40: 174.66 | AN40: =AJ40*1.015 -> 177.2799 | AO40: 177.3 | AP40: =AO40*1.06 -> 187.938 | AS40: 162.2 | AT40: =AS40 -> 162.2 | AV40: =AT40*1.07 -> 173.554 | BI40: =AV40*1.1 -> 190.9094 | BJ40: =BI40+(BI40-(BI40*1.15)) -> 162.27299
B41: 35 | E41: 0090, 0096, 7500, 7501, 7504 e 7508 | H41: 2.8 | I41: =ROUNDUP(((BJ41*$N$3)+BJ41),1) -> 175.9 | K41: 0 | AA41: 116.5 | AB41: 125.9 | AC41: =AB41*1.1 -> 138.49 | AE41: =AC41*1.06 -> 146.7994 | AH41: =AE41*1.05 -> 154.13937 | AI41: =AH41*1.08 -> 166.47052 | AJ41: =AI41*1.05 -> 174.79405 | AN41: =AJ41*1.05 -> 183.53375 | AO41: 183.6 | AP41: =AO41*1.1 -> 201.96 | AS41: 202 | AT41: =AS41-((AS41*13)/100) -> 175.74 | AV41: =AT41*1.07 -> 188.0418 | BI41: =AV41*1.1 -> 206.84598 | BJ41: =BI41+(BI41-(BI41*1.15)) -> 175.81908
B42: 36 | C42: OXFORD BLACKOUT | E42: 0410, 0411 e 0414 | H42: 3 | I42: =ROUNDUP(((BJ42*$N$3)+BJ42),1) -> 166.2 | K42: 0 | AA42: 144.7 | AB42: 156.3 | AC42: =AB42*1.1 -> 171.93 | AE42: =AC42*1.06 -> 182.2458 | AH42: =AE42 -> 182.2458 | AI42: =AH42*1.05 -> 191.35809 | AJ42: =AI42 -> 191.35809 | AN42: =AJ42 -> 191.35809 | AO42: 191.4 | AP42: =AO42*1.06 -> 202.884 | AS42: 184.5 | AT42: =AS42-((AS42*10)/100) -> 166.05 | AV42: =AT42*1.07 -> 177.6735 | BI42: =AV42*1.1 -> 195.44085 | BJ42: =BI42+(BI42-(BI42*1.15)) -> 166.12472
B43: 37 | C43: FLORENÇA | E43: 0356 | H43: 2 | I43: =ROUNDUP(((BJ43*$N$3)+BJ43),1) -> 149.5 | K43: 0 | AA43: 99.8 | AB43: 107.8 | AC43: =AB43*1.1 -> 118.58 | AE43: =AC43*1.06 -> 125.6948 | AH43: =AE43 -> 125.6948 | AI43: =AH43*1.08 -> 135.75038 | AJ43: =AI43 -> 135.75038 | AN43: =AJ43 -> 135.75038 | AO43: 135.8 | AP43: =AO43*1.1 -> 149.38 | AS43: =AP43 -> 149.38 | AT43: =AS43 -> 149.38 | AV43: =AT43*1.07 -> 159.8366 | BI43: =AV43*1.1 -> 175.82026 | BJ43: =BI43+(BI43-(BI43*1.15)) -> 149.44722
B44: 38 | C44: RUSTIC | E44: 0053 | H44: 2 | I44: =ROUNDUP(((BJ44*$N$3)+BJ44),1) -> 176.7 | K44: 0 | AA44: 117.9 | AB44: 127.4 | AC44: =AB44*1.1 -> 140.14 | AE44: =AC44*1.06 -> 148.5484 | AH44: =AE44 -> 148.5484 | AI44: =AH44*1.08 -> 160.43227 | AJ44: =AI44 -> 160.43227 | AN44: =AJ44 -> 160.43227 | AO44: 160.5 | AP44: =AO44*1.1 -> 176.55 | AS44: =AP44 -> 176.55 | AT44: =AS44 -> 176.55 | AV44: =AT44*1.07 -> 188.9085 | BI44: =AV44*1.1 -> 207.79935 | BJ44: =BI44+(BI44-(BI44*1.15)) -> 176.62945
B45: 39 | C45: ELEGANCY | E45: 0162 | H45: 2 | I45: =ROUNDUP(((BJ45*$N$3)+BJ45),1) -> 127 | K45: 0 | AA45: 99.8 | AB45: 107.8 | AC45: =AB45*1.1 -> 118.58 | AE45: =AC45*1.06 -> 125.6948 | AH45: =AE45 -> 125.6948 | AI45: =AH45*1.08 -> 135.75038 | AJ45: =AI45 -> 135.75038 | AN45: =AJ45 -> 135.75038 | AO45: 135.8 | AP45: =AO45*1.1 -> 149.38 | AS45: 126.9 | AT45: =AS45 -> 126.9 | AV45: =AT45*1.07 -> 135.783 | BI45: =AV45*1.1 -> 149.3613 | BJ45: =BI45+(BI45-(BI45*1.15)) -> 126.95711
B46: 40 | E46: 0161 | H46: 3 | I46: =ROUNDUP(((BJ46*$N$3)+BJ46),1) -> 127 | K46: 0 | AA46: 99.8 | AB46: 107.8 | AC46: =AB46*1.1 -> 118.58 | AE46: =AC46*1.06 -> 125.6948 | AH46: =AE46 -> 125.6948 | AI46: =AH46*1.08 -> 135.75038 | AJ46: =AI46 -> 135.75038 | AN46: =AJ46 -> 135.75038 | AO46: 135.8 | AP46: =AO46*1.1 -> 149.38 | AS46: 126.9 | AT46: =AS46 -> 126.9 | AV46: =AT46*1.07 -> 135.783 | BI46: =AV46*1.1 -> 149.3613 | BJ46: =BI46+(BI46-(BI46*1.15)) -> 126.95711
B47: 41 | E47: 0126 | H47: 2.5 | I47: =ROUNDUP(((BJ47*$N$3)+BJ47),1) -> 116.9 | K47: 0 | AA47: 99.8 | AB47: 107.8 | AC47: =AB47*1.1 -> 118.58 | AE47: =AC47*1.06 -> 125.6948 | AH47: =AE47 -> 125.6948 | AI47: =AH47*1.08 -> 135.75038 | AJ47: =AI47 -> 135.75038 | AN47: =AJ47 -> 135.75038 | AO47: 135.8 | AP47: =AO47*1.06 -> 143.948 | AS47: 116.8 | AT47: =AS47 -> 116.8 | AV47: =AT47*1.07 -> 124.976 | BI47: =AV47*1.1 -> 137.4736 | BJ47: =BI47+(BI47-(BI47*1.15)) -> 116.85256
B48: 42 | E48: 0128 | H48: 2.5 | I48: =ROUNDUP(((BJ48*$N$3)+BJ48),1) -> 116.9 | K48: 0 | AC48: 118.58 | AE48: =AC48*1.06 -> 125.6948 | AH48: =AE48 -> 125.6948 | AI48: =AH48*1.08 -> 135.75038 | AJ48: =AI48 -> 135.75038 | AN48: =AJ48 -> 135.75038 | AO48: 135.8 | AP48: =AO48*1.06 -> 143.948 | AS48: 116.8 | AT48: =AS48 -> 116.8 | AV48: =AT48*1.07 -> 124.976 | BI48: =AV48*1.1 -> 137.4736 | BJ48: =BI48+(BI48-(BI48*1.15)) -> 116.85256
B49: 43 | E49: 0170, 0177 | H49: 3 | I49: =ROUNDUP(((BJ49*$N$3)+BJ49),1) -> 127 | K49: 0 | BI49: 149.3613 | BJ49: =BI49+(BI49-(BI49*1.15)) -> 126.95711
B50: 44 | E50: 0169, 0171 e 0178 | H50: 2.5 | I50: =ROUNDUP(((BJ50*$N$3)+BJ50),1) -> 127 | K50: 0 | AS50: 126.9 | AT50: =AS50 -> 126.9 | AV50: =AT50*1.07 -> 135.783 | BI50: =AV50*1.1 -> 149.3613 | BJ50: =BI50+(BI50-(BI50*1.15)) -> 126.95711
B51: 45 | C51: VENEZA | E51: 0076 e 0077 | H51: 2.5 | I51: =ROUNDUP(((BJ51*$N$3)+BJ51),1) -> 126.3 | K51: 0 | AA51: 110.6 | AB51: 119.5 | AC51: =AB51*1.1 -> 131.45 | AE51: =AC51*1.06 -> 139.337 | AH51: =AE51 -> 139.337 | AI51: =AH51*1.08 -> 150.48396 | AJ51: =AI51 -> 150.48396 | AN51: =AJ51 -> 150.48396 | AO51: 150.5 | AP51: =AO51*1.06 -> 159.53 | AS51: 126.2 | AT51: =AS51 -> 126.2 | AV51: =AT51*1.07 -> 135.034 | BI51: =AV51*1.1 -> 148.5374 | BJ51: =BI51+(BI51-(BI51*1.15)) -> 126.25679
B52: 46 | C52: DUBAI | E52: 0221 e 0227 | H52: 2.6 | I52: =ROUNDUP(((BJ52*$N$3)+BJ52),1) -> 241.2 | K52: 0 | AA52: 144.7 | AB52: 156.3 | AC52: =AB52*1.1 -> 171.93 | AE52: =AC52*1.06 -> 182.2458 | AH52: =AE52*1.1 -> 200.47038 | AI52: =AH52*1.08 -> 216.50801 | AJ52: =AI52*1.05 -> 227.33341 | AN52: =AJ52 -> 227.33341 | AO52: 227.4 | AP52: =AO52*1.06 -> 241.044 | AS52: =AP52 -> 241.044 | AT52: =AS52 -> 241.044 | AV52: =AT52*1.07 -> 257.91708 | BI52: =AV52*1.1 -> 283.70879 | BJ52: =BI52+(BI52-(BI52*1.15)) -> 241.15247
B53: 47 | AA53: 126.2 | AB53: 136.3 | AC53: =AB53*1.1 -> 149.93 | AD53: =50*1.1 -> 55 | AE53: =AD53*1.06 -> 58.3 | AH53: =AE53*1.1 -> 64.13 | AI53: =AH53*1.05 -> 67.3365 | AJ53: =AI53 -> 67.3365 | AN53: =AJ53 -> 67.3365 | AO53: 67.4 | AP53: =AO53*1.06 -> 71.444 | AS53: =AP53 -> 71.444 | AT53: =AS53 -> 71.444 | AV53: =AT53*1.07 -> 76.44508 | BI53: =AV53*1.1 -> 84.089588 | BJ53: =BI53+(BI53-(BI53*1.15)) -> 71.47615
B54: 48 | C54: MANHATTAN | E54: 0485 ao 0489 | H54: 2.8 | I54: =ROUNDUP(((BJ54*$N$3)+BJ54),1) -> 149.1 | K54: 0 | AA54: 0 | AB54: 121.4 | AC54: =AB54*1.1 -> 133.54 | AE54: =AC54*1.06 -> 141.5524 | AH54: =AE54*1.05 -> 148.63002 | AI54: =AH54 -> 148.63002 | AJ54: =AI54*1.05 -> 156.06152 | AN54: =AJ54 -> 156.06152 | AO54: 156.1 | AP54: =AO54*1.06 -> 165.466 | AS54: 165.5 | AT54: =AS54-((AS54*10)/100) -> 148.95 | AV54: =AT54*1.07 -> 159.3765 | BI54: =AV54*1.1 -> 175.31415 | BJ54: =BI54+(BI54-(BI54*1.15)) -> 149.01703
B55: 49 | C55: SEVILHA | E55: 3354, 3355, 3356, 3357, 3358, 3359, 3360, 3361 | H55: 2.5 | I55: =ROUNDUP(((BJ55*$N$3)+BJ55),1) -> 114.4 | K55: 0 | AS55: 126.2 | AT55: =AS55-((AS55*9.4)/100) -> 114.3372 | AV55: =AT55*1.07 -> 122.3408 | BI55: =AV55*1.1 -> 134.57488 | BJ55: =BI55+(BI55-(BI55*1.15)) -> 114.38865
B56: 50 | C56: LISBOA | E56: 3380, 3381, 3382, 3383, 3384, 3385, 3386 | H56: 2.8 | I56: =ROUNDUP(((BJ56*$N$3)+BJ56),1) -> 114.4 | K56: 0 | AS56: 126.9 | AT56: =AS56-((AS56*9.9)/100) -> 114.3369 | AV56: =AT56*1.07 -> 122.34048 | BI56: =AV56*1.1 -> 134.57453 | BJ56: =BI56+(BI56-(BI56*1.15)) -> 114.38835
B57: 51 | C57: BARCELONA | E57: 3390, 3391, 3392, 3393, 3394 | H57: 2.8 | I57: =ROUNDUP(((BJ57*$N$3)+BJ57),1) -> 149.1 | K57: 0 | AS57: 165.5 | AT57: =AS57-((AS57*10)/100) -> 148.95 | AV57: =AT57*1.07 -> 159.3765 | BI57: =AV57*1.1 -> 175.31415 | BJ57: =BI57+(BI57-(BI57*1.15)) -> 149.01703
B58: 52 | C58: FINESSE BK | E58: 6500 ao 6808 | H58: 3 | I58: =ROUNDUP(((BJ58*$N$3)+BJ58),1) -> 207.8 | K58: 0 | AV58: 222.2 | BI58: =AV58*1.1 -> 244.42 | BJ58: =BI58+(BI58-(BI58*1.15)) -> 207.757
B59: 53 | C59: TRANCOSO | E59: 8800 ao 8804 | H59: 3 | I59: =ROUNDUP(((BJ59*$N$3)+BJ59),1) -> 125.3 | K59: 0 | BI59: 147.3 | BJ59: =BI59+(BI59-(BI59*1.15)) -> 125.205
B60: 54 | C60: CARAÍVA BK | E60: 8900 ao 8904 | H60: 3 | I60: =ROUNDUP(((BJ60*$N$3)+BJ60),1) -> 173.5 | K60: 0 | BI60: 204.1 | BJ60: =BI60+(BI60-(BI60*1.15)) -> 173.485
B61: 55 | C61: CAMBURI BK | E61: 9200 ao 9209 | H61: 3 | I61: =ROUNDUP(((BJ61*$N$3)+BJ61),1) -> 173.5 | K61: 0 | BI61: 204.1 | BJ61: =BI61+(BI61-(BI61*1.15)) -> 173.485
B62: 56 | C62: MARAGOGI BK | E62: 7600 ao 7604 | H62: 2.8 | I62: =ROUNDUP(((BJ62*$N$3)+BJ62),1) -> 225.6 | K62: 0 | BI62: 265.3 | BJ62: =BI62+(BI62-(BI62*1.15)) -> 225.505
B63: 57 | C63: IPANEMA | E63: 7800 ao 7804 | H63: 2.8 | I63: =ROUNDUP(((BJ63*$N$3)+BJ63),1) -> 159.2 | K63: 0 | BI63: 187.2 | BJ63: =BI63+(BI63-(BI63*1.15)) -> 159.12
B64: 58 | C64: NORONHA | E64: 8600 ao 8606 | H64: 2.8 | I64: =ROUNDUP(((BJ64*$N$3)+BJ64),1) -> 159.2 | K64: 0 | BI64: 187.2 | BJ64: =BI64+(BI64-(BI64*1.15)) -> 159.12
B65: 59 | C65: LEBLON | E65: 8200 ao 8205 | H65: 2.8 | I65: =ROUNDUP(((BJ65*$N$3)+BJ65),1) -> 159.2 | K65: 0 | BI65: 187.2 | BJ65: =BI65+(BI65-(BI65*1.15)) -> 159.12
B66: 60
B67: 61
B68: 62
B69: 63
B70: 64
K71: Página 7 - | L71: =L2 -> 2026 - v.03
B73: PRODUTO EM CONFORMIDADE COM A NORMA ABNT NBR 16234: 2014
B75: 65 | C75: ACESSÓRIOS | N75: * DIGITE A PORCENTAGEM PARA MARKUP - ACESSÓRIOS
B76: 66
B77: 67
B78: 68 | N78: 0
B79: 69 | C79: DESCRIÇÃO DO ACESSÓRIO | H79: COR | I79: UNIDADE | J79: VALOR À VISTA (R$) | L79: IPI | AA79: 42491 | AB79: 43026 | AD79: 43862 | AE79: 43952 | AI79: 44105 | AJ79: 44256 | AN79: 44378 | AV79: 45658
B80: 70 | C80: BASES: Chata, Redonda e Slim | H80: - | I80: - | J80: =ROUNDUP(((AS80*$N$78)+AS80),1) -> 0 | L80: 0 | N80: * Legenda de Cores: | AS80: 0 | AT80: =AS80*1.1 -> 0 | AV80: =AT80*1.1 -> 0
B81: 71 | C81: PESO BASE SLIM (Obrigatório para tubos de 70MM e 80MM) | H81: - | I81: ML | J81: =ROUNDUP(((AV81*$N$78)+AV81),1) -> 41.6 | L81: 0 | N81: MR = Marrom | AS81: 35.3 | AT81: =AS81*1.07 -> 37.771 | AV81: =AT81*1.1 -> 41.5481
B82: 72 | C82: GUIA LATERAL 60mm - INCLUSO OS DOIS LADOS (USO OBRIGATÓRIO DE BASE CHATA). | H82: vide linha 164 | I82: ML | J82: =ROUNDUP(((AV82*$N$78)+AV82),1) -> 129.3 | L82: 0 | N82: B = Branco | AA82: 54.2 | AB82: 58.6 | AC82: =AB82*1.1 -> 64.46 | AD82: =AC82*1.1 -> 70.906 | AE82: =AD82*1.1 -> 77.9966 | AI82: =AE82*1.05 -> 81.89643 | AJ82: =AI82*1.1 -> 90.086073 | AN82: =AJ82*1.15 -> 103.59898 | AO82: 103.6 | AP82: =AO82*1.06 -> 109.816 | AS82: =AP82 -> 109.816 | AT82: =AS82*1.07 -> 117.50312 | AV82: =AT82*1.1 -> 129.25343
B83: 73 | N83: M = Marfim | AS83: =AP83 -> 0 | AT83: =AS83*1.07 -> 0 | AV83: =AT83*1.1 -> 0
B84: 74 | C84: GUIA LATERAL 80mm - INCLUSO OS DOIS LADOS (USO OBRIGATÓRIO DE BASE CHATA). | H84: vide linha 164 | I84: ML | J84: =ROUNDUP(((AV84*$N$78)+AV84),1) -> 206.2 | L84: 0 | N84: P = Preto | AA84: 86.4 | AB84: 93.4 | AC84: =AB84*1.1 -> 102.74 | AD84: =AC84*1.1 -> 113.014 | AE84: =AD84*1.1 -> 124.3154 | AI84: =AE84*1.05 -> 130.53117 | AJ84: =AI84*1.1 -> 143.58429 | AN84: =AJ84*1.15 -> 165.12193 | AO84: 165.2 | AP84: =AO84*1.06 -> 175.112 | AS84: =AP84 -> 175.112 | AT84: =AS84*1.07 -> 187.36984 | AV84: =AT84*1.1 -> 206.10682
B85: 75 | N85: C = Cinza | AS85: =AP85 -> 0 | AT85: =AS85*1.07 -> 0 | AV85: =AT85*1.1 -> 0
B86: 76 | C86: BANDÔ CONJUGADO PARA CORTINA ROLÔ (LARGURA MÁXIMA 3,50M). | H86: vide linha 164 | I86: ML | J86: =ROUNDUP(((AV86*$N$78)+AV86),1) -> 106.6 | L86: 0 | N86: BZ = Bronze | AA86: 46.75 | AB86: 50.5 | AC86: =AB86*1.1 -> 55.55 | AD86: =AC86*1.1 -> 61.105 | AE86: =AD86*1.1 -> 67.2155 | AI86: =AE86*1.05 -> 70.576275 | AJ86: =AI86*1.1 -> 77.633903 | AN86: =AJ86*1.1 -> 85.397293 | AO86: 85.4 | AP86: =AO86*1.06 -> 90.524 | AS86: =AP86 -> 90.524 | AT86: =AS86*1.07 -> 96.86068 | AV86: =AT86*1.1 -> 106.54675
B87: 77 | C87: BANDÔ FLAT | H87: B - M - P | I87: ML | J87: =ROUNDUP(((AV87*$N$78)+AV87),1) -> 122.9 | L87: 0 | AS87: 104.4 | AT87: =AS87*1.07 -> 111.708 | AV87: =AT87*1.1 -> 122.8788
B88: 78 | C88: BANDÔ FLAT REVESTIDO | H88: B - M - P | I88: ML | J88: =ROUNDUP(((AV88*$N$78)+AV88),1) -> 163.2 | L88: 0 | AS88: 138.63 | AT88: =AS88*1.07 -> 148.3341 | AV88: =AT88*1.1 -> 163.16751
B89: 79 | C89: BANDÔ CURVADO COM FRENTE DE 11CM (PARA PERSIANAS COM TUBO DE até 50MM) NÃO POSSUI TAMPAS LATERAIS. | H89: B-M-P | I89: ML | J89: =ROUNDUP(((AV89*$N$78)+AV89),1) -> 54.1 | L89: 0 | AA89: 28.5 | AB89: 30.8 | AC89: =AB89*1.1 -> 33.88 | AD89: =AC89*1.1 -> 37.268 | AE89: =AD89*1.1 -> 40.9948 | AI89: =AE89*1.05 -> 43.04454 | AJ89: =AI89*1.1 -> 47.348994 | AN89: =AJ89*1.15 -> 54.451343 | AO89: 54.5 | AP89: =AO89*1.06 -> 57.77 | AS89: 45.9 | AT89: =AS89*1.07 -> 49.113 | AV89: =AT89*1.1 -> 54.0243
B90: 80 | AN90: =AJ90 -> 0 | AS90: =AP90 -> 0 | AT90: =AS90*1.07 -> 0 | AV90: =AT90*1.1 -> 0
B91: 81 | C91: BANDÔ BOX 70 PARA CORTINA ROLÔ. APENAS PARA CORTINAS COM TUBOS DE 32MM. | H91: vide linha 164 | I91: ML | J91: =ROUNDUP(((AV91*$N$78)+AV91),1) -> 138.4 | L91: 0 | AC91: 72.1 | AD91: =AC91*1.1 -> 79.31 | AE91: =AD91*1.1 -> 87.241 | AI91: =AE91*1.05 -> 91.60305 | AJ91: =AI91*1.1 -> 100.76336 | AN91: =AJ91*1.1 -> 110.83969 | AO91: 110.9 | AP91: =AO91*1.06 -> 117.554 | AS91: =AP91 -> 117.554 | AT91: =AS91*1.07 -> 125.78278 | AV91: =AT91*1.1 -> 138.36106
B92: 82 | AS92: =AP92 -> 0 | AT92: =AS92*1.07 -> 0 | AV92: =AT92*1.1 -> 0
B93: 83 | C93: BANDÔ BOX 90 (LARGURA MÁXIMA 3,50M) - PARA CORTINA ROLÔ. | H93: vide linha 164 | I93: ML | J93: =ROUNDUP(((AV93*$N$78)+AV93),1) -> 163.2 | L93: 0 | AA93: 71.5 | AB93: 77.3 | AC93: =AB93*1.1 -> 85.03 | AD93: =AC93*1.1 -> 93.533 | AE93: =AD93*1.1 -> 102.8863 | AI93: =AE93*1.05 -> 108.03062 | AJ93: =AI93*1.1 -> 118.83368 | AN93: =AJ93*1.1 -> 130.71704 | AO93: 130.8 | AP93: =AO93*1.06 -> 138.648 | AS93: =AP93 -> 138.648 | AT93: =AS93*1.07 -> 148.35336 | AV93: =AT93*1.1 -> 163.1887
B94: 84 | C94: BANDÔ BOX GRANDE- PARA TUBOS DE 53MM ATÉ 88MM. | H94: vide linha 164 | I94: ML | J94: =ROUNDUP(((AV94*$N$78)+AV94),1) -> 341.9 | L94: 0 | AA94: 150 | AB94: 162 | AC94: =AB94*1.1 -> 178.2 | AD94: =AC94*1.1 -> 196.02 | AE94: =AD94*1.1 -> 215.622 | AI94: =AE94*1.05 -> 226.4031 | AJ94: =AI94*1.1 -> 249.04341 | AN94: =AJ94*1.1 -> 273.94775 | AO94: 274 | AP94: =AO94*1.06 -> 290.44 | AS94: =AP94 -> 290.44 | AT94: =AS94*1.07 -> 310.7708 | AV94: =AT94*1.1 -> 341.84788
B95: 85 | C95: BANDÔ SEMI BOX - PARA TUBOS DE 53MM ATÉ 88MM. | H95: vide linha 164 | I95: ML | J95: =ROUNDUP(((AV95*$N$78)+AV95),1) -> 239.3 | L95: 0 | AA95: 105 | AB95: 113.4 | AC95: =AB95*1.1 -> 124.74 | AD95: =AC95*1.1 -> 137.214 | AE95: =AD95*1.1 -> 150.9354 | AI95: =AE95*1.05 -> 158.48217 | AJ95: =AI95*1.1 -> 174.33039 | AN95: =AJ95*1.1 -> 191.76343 | AO95: 191.8 | AP95: =AO95*1.06 -> 203.308 | AS95: =AP95 -> 203.308 | AT95: =AS95*1.07 -> 217.53956 | AV95: =AT95*1.1 -> 239.29352
B96: 86 | C96: BARRA NIVELADORA - PARA TUBOS DE 32MM E 38MM | H96: vide linha 164 | I96: ML | J96: =ROUNDUP(((AV96*$N$78)+AV96),1) -> 17.6 | L96: 0 | AA96: 15.2 | AB96: 16.5 | AC96: =AB96*1.1 -> 18.15 | AD96: =AC96*1.1 -> 19.965 | AE96: =AD96*1.1 -> 21.9615 | AI96: =AE96*1.05 -> 23.059575 | AJ96: =AI96*1.1 -> 25.365533 | AN96: =AJ96*1.1 -> 27.902086 | AO96: 28 | AP96: =AO96*1.06 -> 29.68 | AS96: 14.9 | AT96: =AS96*1.07 -> 15.943 | AV96: =AT96*1.1 -> 17.5373
B97: 87 | C97: BARRA NIVELADORA LARGA - PARA TUBOS DE 53MM. | H97: vide linha 164 | I97: ML | J97: =ROUNDUP(((AV97*$N$78)+AV97),1) -> 22.9 | L97: 0 | AC97: 23.7 | AD97: =AC97*1.1 -> 26.07 | AE97: =AD97*1.1 -> 28.677 | AI97: =AE97*1.05 -> 30.11085 | AJ97: =AI97*1.1 -> 33.121935 | AN97: =AJ97*1.1 -> 36.434129 | AO97: 36.5 | AP97: =AO97*1.06 -> 38.69 | AS97: 19.4 | AT97: =AS97*1.07 -> 20.758 | AV97: =AT97*1.1 -> 22.8338
B98: 88 | C98: BARRA NIVELADORA GRANDE - PARA TUBOS DE 70MM ATÉ 88MM. | H98: vide linha 164 | I98: ML | J98: =ROUNDUP(((AV98*$N$78)+AV98),1) -> 148.3 | L98: 0 | AA98: 65 | AB98: 70.2 | AC98: =AB98*1.1 -> 77.22 | AD98: =AC98*1.1 -> 84.942 | AE98: =AD98*1.1 -> 93.4362 | AI98: =AE98*1.05 -> 98.10801 | AJ98: =AI98*1.1 -> 107.91881 | AN98: =AJ98*1.1 -> 118.71069 | AO98: 118.8 | AP98: =AO98*1.06 -> 125.928 | AS98: =AP98 -> 125.928 | AT98: =AS98*1.07 -> 134.74296 | AV98: =AT98*1.1 -> 148.21726
B99: 89 | C99: TRILHO DE CORRER PARA CORTINA ROLÔ (LARGURA MÁXIMA 3,50M) PARA ROLÔ COM LARGURA MÁXIMA DE 1,50M. | H99: B - M - P | I99: ML | J99: =ROUNDUP(((AV99*$N$78)+AV99),1) -> 120.3 | L99: 0 | AA99: 116 | AB99: 125.3 | AC99: =AB99*1.1 -> 137.83 | AD99: =AC99*1.1 -> 151.613 | AE99: =AD99*1.1 -> 166.7743 | AI99: =AE99*1.05 -> 175.11302 | AJ99: =AI99*1.1 -> 192.62432 | AN99: =AJ99*1.15 -> 221.51796 | AO99: 221.6 | AP99: =AO99*1.06 -> 234.896 | AS99: 102.2 | AT99: =AS99*1.07 -> 109.354 | AV99: =AT99*1.1 -> 120.2894
B100: 90 | AS100: =AP100 -> 0 | AT100: =AS100*1.07 -> 0 | AV100: =AT100*1.1 -> 0
B101: 91 | C101: TRILHO DE ROLO - DESLOCAMENTO FRONTAL (OBRIGATÓRIO O USO DE BARRA NIVELADORA QUE É COBRADA SEPARADAMENTE) | H101: Branco | I101: ML | J101: =ROUNDUP(((AV102*$N$78)+AV102),1) -> 358.9 | L101: 0 | AT101: =AS101*1.07 -> 0 | AV101: =AT101*1.1 -> 0
B102: 92 | AS102: 304.9 | AT102: =AS102*1.07 -> 326.243 | AV102: =AT102*1.1 -> 358.8673
B103: 93 | C103: CORRENTE METÁLICA - COBRADO 2X O TAMANHO DO COMANDO (TC). (LANÇAMENTOS) | H103: Inox - Bronze - Ouro Velho - Preto Niquelado | I103: ML | J103: =ROUNDUP(((AV103*$N$78)+AV103),1) -> 17.4 | L103: 0 | AA103: 6.6 | AB103: 7.2 | AC103: =AB103*1.1 -> 7.92 | AD103: =AC103*1.2 -> 9.504 | AE103: =AD103*1.1 -> 10.4544 | AI103: =AE103*1.05 -> 10.97712 | AJ103: =AI103*1.1 -> 12.074832 | AN103: =AJ103*1.15 -> 13.886057 | AO103: 13.9 | AP103: =AO103*1.06 -> 14.734 | AS103: =AP103 -> 14.734 | AT103: =AS103*1.07 -> 15.76538 | AV103: =AT103*1.1 -> 17.341918
B104: 94
...

Sheet Premium
K2: Página 9 - | L2: =Rolô!L2 -> 2026 - v.03 | N2: * DIGITE A PORCENTAGEM PARA MARKUP
B3: CORTINAS LINHA PREMIUM | N3: 0
B4: PRODUTO EM CONFORMIDADE COM A NORMA ABNT NBR 16234: 2014
B6: ITEM | C6: COLEÇÃO | E6: COR | H6: LAR. MAX. | I6: VALOR À VISTA (R$)/M² | K6: IPI | AA6: 42491 | AC6: 42583 | AD6: 43026 | AE6: 43258 | AG6: 43862 | AH6: 43952 | AI6: 44105 | AJ6: 44256 | AK6: 44378 | AL6: 44501 | AO6: 44682 | AQ6: 45658 | AS6: 46082
B7: 1 | C7: ILLUMINÊ | E7: 0630 ao 0633 | H7: 2.8 | I7: =ROUNDUP(((AS7*$N$3)+AS7),1) -> 404.3 | K7: 0 | AA7: 222.6 | AD7: 240.5 | AE7: 264.6 | AG7: =AE7*1.06 -> 280.476 | AH7: =AG7*1.1 -> 308.5236 | AI7: =AH7 -> 308.5236 | AJ7: =AI7*1.05 -> 323.94978 | AK7: =AJ7 -> 323.94978 | AL7: 324 | AM7: =AL7*1.06 -> 343.44 | AO7: =AM7 -> 343.44 | AP7: =AO7*1.07 -> 367.4808 | AQ7: =AP7*1.1 -> 404.22888 | AS7: =AQ7 -> 404.22888
B8: 2 | C8: MELÍADE | E8: 0571, 0581 e 0582 | H8: 2.8 | I8: =ROUNDUP(((AS8*$N$3)+AS8),1) -> 661.9 | K8: 0 | AA8: 364.7 | AD8: 393.9 | AE8: 433.3 | AG8: =AE8*1.06 -> 459.298 | AH8: =AG8*1.1 -> 505.2278 | AI8: =AH8 -> 505.2278 | AJ8: =AI8*1.05 -> 530.48919 | AK8: =AJ8 -> 530.48919 | AL8: 530.5 | AM8: =AL8*1.06 -> 562.33 | AO8: =AM8 -> 562.33 | AP8: =AO8*1.07 -> 601.6931 | AQ8: =AP8*1.1 -> 661.86241 | AS8: =AQ8 -> 661.86241
B9: 3 | E9: 0580 | H9: 3 | K9: 0 | AK9: =AJ9*1.05 -> 0 | AO9: =AM9 -> 0 | AP9: =AO9*1.07 -> 0 | AQ9: =AP9*1.1 -> 0 | AS9: =AQ9 -> 0
B10: 4 | C10: LUMIÉRE 50MM LINEA | E10: 0601, 0606, 0607 | H10: 3 | I10: =ROUNDUP(((AS10*$N$3)+AS10),1) -> 302.7 | K10: 0 | AA10: 238.2 | AD10: 257.3 | AE10: 283.1 | AG10: =AE10*1.06 -> 300.086 | AH10: =AG10*1.1 -> 330.0946 | AI10: =AH10 -> 330.0946 | AJ10: =AI10*1.05 -> 346.59933 | AK10: =AJ10 -> 346.59933 | AL10: 346.6 | AM10: =AL10*1.06 -> 367.396 | AO10: =AM10 -> 367.396 | AP10: =AO10*1.07 -> 393.11372 | AQ10: =AP10*1.1 -> 432.42509 | AS10: =AQ10+(AQ10-(AQ10*1.3)) -> 302.69756
B11: 5 | E11: 0602, 0608 e 0609 | H11: 2.8 | K11: 0 | AK11: =AJ11*1.05 -> 0 | AO11: =AM11 -> 0 | AP11: =AO11*1.07 -> 0 | AQ11: =AP11*1.1 -> 0 | AS11: =AQ11+(AQ11-(AQ11*1.3)) -> 0
B12: 6 | C12: LUMIÉRE 60MM BRISE | E12: 0612 e 0613 | H12: 3 | I12: =ROUNDUP(((AS12*$N$3)+AS12),1) -> 302.7 | K12: 0 | AO12: 367.4 | AP12: =AO12*1.07 -> 393.118 | AQ12: =AP12*1.1 -> 432.4298 | AS12: =302.69 -> 302.69
B13: 7 | C13: LUMIÉRE 55MM BK | E13: 0750, 0751 e 0752 | H13: 3 | I13: =ROUNDUP(((AS13*$N$3)+AS13),1) -> 404.3 | K13: 0 | AO13: 429.3 | AP13: =AO13*1.07 -> 459.351 | AQ13: =AP13*1.1 -> 505.2861 | AS13: =AQ13+(AQ13-(AQ13*1.2)) -> 404.22888
B14: 8 | C14: LUMIÉRE 70MM LUMINA | E14: 0595 ao 0600 | H14: 2.8 | I14: =ROUNDUP(((AS14*$N$3)+AS14),1) -> 338 | K14: 0 | AA14: 248.2 | AD14: 268.1 | AE14: 295 | AG14: =AE14*1.06 -> 312.7 | AH14: =AG14*1.1 -> 343.97 | AI14: =AH14 -> 343.97 | AJ14: =AI14*1.05 -> 361.1685 | AK14: =AJ14 -> 361.1685 | AL14: 361.2 | AM14: =AL14*1.06 -> 382.872 | AO14: =AM14 -> 382.872 | AP14: =AO14*1.07 -> 409.67304 | AQ14: =AP14*1.1 -> 450.64034 | AS14: =AQ14+(AQ14-(AQ14*1.25)) -> 337.98026
B15: 9 | C15: LUMIÉRE 50MM DIAMANTE | E15: 0592, 0593 e 0594 e 0591 (LANÇAMENTO) | H15: 2.8 | I15: =ROUNDUP(((AS15*$N$3)+AS15),1) -> 338 | K15: 0 | AA15: 248.2 | AD15: 268.1 | AE15: 295 | AG15: =AE15*1.06 -> 312.7 | AH15: =AG15*1.1 -> 343.97 | AI15: =AH15 -> 343.97 | AJ15: =AI15*1.05 -> 361.1685 | AK15: =AJ15 -> 361.1685 | AL15: 361.2 | AM15: =AL15*1.06 -> 382.872 | AO15: =AM15 -> 382.872 | AP15: =AO15*1.07 -> 409.67304 | AQ15: =AP15*1.1 -> 450.64034 | AS15: =AQ15+(AQ15-(AQ15*1.25)) -> 337.98026
B16: 10 | C16: LUMIÉRE 50MM ARMONNE | E16: 0823, 0824, 0825, 0826 E 0827 (LANÇAMENTOS) | H16: 2.8 | I16: =ROUNDUP(((AS16*$N$3)+AS16),1) -> 353.8 | K16: 0 | AQ16: 505.3 | AS16: =AQ16+(AQ16-(AQ16*1.3)) -> 353.71
B17: 11 | C17: LUMIÉRE 70MM MALORIE | E17: 0550, 0551, 0552 e 0553 (LANÇAMENTOS) | H17: 3 | I17: =ROUNDUP(((AS17*$N$3)+AS17),1) -> 324.4 | K17: 0 | AQ17: 463.4 | AS17: =AQ17+(AQ17-(AQ17*1.3)) -> 324.38
B18: 12 | C18: LUMIÉRE 70MM ENVELINE | E18: 0730, 0731, 0732, 0733, 0734 e 0735 (LANÇAMENTOS) | H18: 3 | I18: =ROUNDUP(((AS18*$N$3)+AS18),1) -> 315.5 | K18: 0 | AQ18: 450.7 | AS18: =AQ18+(AQ18-(AQ18*1.3)) -> 315.49
B19: 13 | C19: LUMIÉRE 50MM VIVANCE | E19: 0820, 0821 e 0822 (LANÇAMENTOS) | H19: 2.8 | I19: =ROUNDUP(((AS19*$N$3)+AS19),1) -> 353.8 | K19: 0 | AQ19: 505.3 | AS19: =AQ19+(AQ19-(AQ19*1.3)) -> 353.71
B20: 14 | C20: INFINITY | E20: 0620 ao 0622 | H20: 2.5 | I20: =ROUNDUP(((AS20*$N$3)+AS20),1) -> 411.9 | K20: 0 | AA20: 238.2 | AD20: 257.3 | AE20: 283.1 | AG20: =AE20*1.06 -> 300.086 | AH20: =AG20*1.1 -> 330.0946 | AI20: =AH20 -> 330.0946 | AJ20: =AI20 -> 330.0946 | AK20: =AJ20 -> 330.0946 | AL20: 330.1 | AM20: =AL20*1.06 -> 349.906 | AO20: =AM20 -> 349.906 | AP20: =AO20*1.07 -> 374.39942 | AQ20: =AP20*1.1 -> 411.83936 | AS20: =AQ20 -> 411.83936
B21: 15 | C21: ETERNITY | E21: 0611 | H21: 2.5 | I21: =ROUNDUP(((AS21*$N$3)+AS21),1) -> 411.9 | K21: 0 | AA21: 238.2 | AD21: 257.3 | AE21: 283.1 | AG21: =AE21*1.06 -> 300.086 | AH21: =AG21*1.1 -> 330.0946 | AI21: =AH21 -> 330.0946 | AJ21: =AI21 -> 330.0946 | AK21: =AJ21 -> 330.0946 | AL21: 330.1 | AM21: =AL21*1.06 -> 349.906 | AO21: =AM21 -> 349.906 | AP21: =AO21*1.07 -> 374.39942 | AQ21: =AP21*1.1 -> 411.83936 | AS21: =AQ21 -> 411.83936
B22: 16 | C22: ETERNITY LINE | E22: 0615 e 0616 | H22: 2.5 | I22: =ROUNDUP(((AS22*$N$3)+AS22),1) -> 411.9 | K22: 0 | AA22: 238.2 | AD22: 257.3 | AE22: 283.1 | AG22: =AE22*1.06 -> 300.086 | AH22: =AG22*1.1 -> 330.0946 | AI22: =AH22 -> 330.0946 | AJ22: =AI22 -> 330.0946 | AK22: =AJ22 -> 330.0946 | AL22: 330.1 | AM22: =AL22*1.06 -> 349.906 | AO22: =AM22 -> 349.906 | AP22: =AO22*1.07 -> 374.39942 | AQ22: =AP22*1.1 -> 411.83936 | AS22: =AQ22 -> 411.83936
B23: 17 | C23: GALAXY | E23: 0641 - PROMOÇÃO | H23: 2.5 | I23: =ROUNDUP(((AS23*$N$3)+AS23),1) -> 108.2 | K23: 0 | AA23: 80 | AD23: 86.4 | AE23: 74.3 | AF23: =67.5*1.1 -> 74.25 | AG23: 78.8 | AH23: =AG23*1.1 -> 86.68 | AI23: 86.63 | AJ23: =AI23 -> 86.63 | AK23: =AJ23 -> 86.63 | AL23: 86.7 | AM23: =AL23*1.06 -> 91.902 | AO23: =AM23 -> 91.902 | AP23: =AO23*1.07 -> 98.33514 | AQ23: =AP23*1.1 -> 108.16865 | AS23: =AQ23 -> 108.16865
B24: 18 | C24: PASSIONE | E24: 0670 e 0672 | H24: - | I24: =ROUNDUP(((AS24*$N$3)+AS24),1) -> 409.2 | K24: 0 | AA24: 298 | AD24: 321.9 | AE24: 354.1 | AG24: =AE24*1.06 -> 375.346 | AH24: =AG24*1.04 -> 390.35984 | AI24: =AH24 -> 390.35984 | AJ24: =AI24*1.05 -> 409.87783 | AK24: =AJ24 -> 409.87783 | AL24: 409.9 | AM24: =AL24*1.06 -> 434.494 | AO24: =AM24 -> 434.494 | AP24: =AO24*1.07 -> 464.90858 | AQ24: =AP24*1.1 -> 511.39944 | AS24: =AQ24+(AQ24-(AQ24*1.2)) -> 409.11955
B25: 19 | E25: 0671 | H25: - | I25: =ROUNDUP(((AS25*$N$3)+AS25),1) -> 286.5 | K25: 0 | AA25: 208.6 | AD25: 225.3 | AE25: 247.9 | AG25: =AE25*1.06 -> 262.774 | AH25: =AG25*1.04 -> 273.28496 | AI25: =AH25 -> 273.28496 | AJ25: =AI25*1.05 -> 286.94921 | AK25: =AJ25 -> 286.94921 | AL25: 287 | AM25: =AL25*1.06 -> 304.22 | AO25: =AM25 -> 304.22 | AP25: =AO25*1.07 -> 325.5154 | AQ25: =AP25*1.1 -> 358.06694 | AS25: =AQ25+(AQ25-(AQ25*1.2)) -> 286.45355
B26: 20 | C26: L'AMOUR | E26: 0980, 0981, 0982,0983 e 0984 | H26: 7.2 | I26: =ROUNDUP(((AS26*$N$3)+AS26),1) -> 253.3 | K26: 0 | AP26: 255.8 | AQ26: =AP26*1.1 -> 281.38 | AS26: =AQ26+(AQ26-(AQ26*1.1)) -> 253.242
B27: 21 | C27: ROLÔ STILLO | AO27: =AM27 -> 0 | AP27: =AO27*1.07 -> 0 | AQ27: =AP27*1.1 -> 0 | AS27: 46082
B28: 22 | C28: STILLO BASIC | E28: 0110, 0111 e 0129 | H28: 2.7 | I28: =ROUNDUP(((AS28*$N$3)+AS28),1) -> 169.7 | K28: 0 | AA28: 160.2 | AC28: 129.78 | AD28: 135 | AE28: 148.5 | AG28: =AE28*1.06 -> 157.41 | AH28: =AG28*1.07 -> 168.4287 | AI28: =AH28*1.08 -> 181.903 | AJ28: =AI28*1.05 -> 190.99815 | AK28: =AJ28 -> 190.99815 | AL28: 191 | AM28: =AL28*1.06 -> 202.46 | AO28: 182.3 | AP28: =AO28*1.07 -> 195.061 | AQ28: =AP28*1.1 -> 214.5671 | AR28: =(AQ28*(-7%))+AQ28 -> 199.5474 | AS28: =AR28+(AR28-(AR28*1.15)) -> 169.61529
B29: 23 | E29: 0127 | H29: 3 | I29: =ROUNDUP(((AS29*$N$3)+AS29),1) -> 169.7 | K29: 0 | AQ29: 214.6 | AR29: =(AQ29*(-7%))+AQ29 -> 199.578 | AS29: =AR29+(AR29-(AR29*1.15)) -> 169.6413
B30: 24 | E30: 0113, 0116 e 0119 | H30: 2.15 | I30: =ROUNDUP(((AS30*$N$3)+AS30),1) -> 214.6 | K30: 0 | AE30: 148.5 | AG30: =AE30*1.06 -> 157.41 | AH30: =AG30*1.07 -> 168.4287 | AI30: =AH30*1.08 -> 181.903 | AJ30: =AI30*1.05 -> 190.99815 | AK30: =AJ30 -> 190.99815 | AL30: 191 | AM30: =AL30*1.06 -> 202.46 | AO30: 182.3 | AP30: =AO30*1.07 -> 195.061 | AQ30: =AP30*1.1 -> 214.5671 | AR30: =AQ30 -> 214.5671 | AS30: 214.6
B31: 25 | E31: 0115 | H31: 2.15 | I31: =ROUNDUP(((AS31*$N$3)+AS31),1) -> 169.7 | AQ31: 214.56 | AR31: =(AQ31*(-7%))+AQ31 -> 199.5408 | AS31: =AR31+(AR31-(AR31*1.15)) -> 169.60968
B32: 26 | C32: STILLO COLOR SEMI-BK | E32: 0202 ao 0207, 0217, 0218 e 0219 | H32: 2.8 | I32: =ROUNDUP(((AS32*$N$3)+AS32),1) -> 188.4 | K32: 0 | AJ32: 268.4 | AK32: =AJ32 -> 268.4 | AL32: 268.4 | AM32: =AL32*1.06 -> 284.504 | AO32: =AM32 -> 284.504 | AP32: =AO32*1.07 -> 304.41928 | AQ32: =AP32*1.1 -> 334.86121 | AR32: =(AQ32*(-25%))+AQ32 -> 251.14591 | AS32: =AR32+(AR32-(AR32*1.25)) -> 188.35943
B33: 27 | E33: 0213 | H33: 2.7 | I33: =ROUNDUP(((AS33*$N$3)+AS33),1) -> 317.3 | K33: 0 | AO33: 322 | AP33: =AO33*1.07 -> 344.54 | AQ33: =AP33*1.1 -> 378.994 | AR33: =(AQ33*(-7%))+AQ33 -> 352.46442 | AS33: =AR33+(AR33-(AR33*1.1)) -> 317.21798
B34: 28 | C34: STILLO SCREEN | E34: 0320, 0321 e 0323 | H34: 2.4 | I34: =ROUNDUP(((AS34*$N$3)+AS34),1) -> 266.4 | K34: 0 | AA34: 165.5 | AD34: 172.2 | AE34: 189.5 | AG34: =AE34*1.06 -> 200.87 | AH34: =AG34*1.1 -> 220.957 | AI34: =AH34*1.08 -> 238.63356 | AJ34: =AI34*1.1 -> 262.49692 | AK34: =AJ34*1.05 -> 275.62176 | AL34: 275.7 | AM34: =AL34*1.06 -> 292.242 | AO34: =AM34 -> 292.242 | AP34: =AO34*1.07 -> 312.69894 | AQ34: =AP34*1.1 -> 343.96883 | AR34: =(AQ34*(-12%))+AQ34 -> 302.69257 | AS34: =AR34+(AR34-(AR34*1.12)) -> 266.36947
B35: 29 | C35: STILLO ACCORDIAN | E35: 0201 | H35: 2.6 | I35: =ROUNDUP(((AS35*$N$3)+AS35),1) -> 202.1 | K35: 0 | AA35: 129.8 | AD35: 135 | AE35: 148.5 | AG35: =AE35*1.06 -> 157.41 | AH35: =AG35*1.1 -> 173.151 | AI35: =AH35 -> 173.151 | AJ35: =AI35*1.1 -> 190.4661 | AK35: =AJ35 -> 190.4661 | AL35: 190.5 | AM35: =AL35*1.06 -> 201.93 | AO35: 171.7 | AP35: =AO35*1.07 -> 183.719 | AQ35: =AP35*1.1 -> 202.0909 | AR35: =AQ35 -> 202.0909 | AS35: 202.1
B36: 30 | AO36: =AM36 -> 0 | AP36: =AO36*1.07 -> 0 | AQ36: =AP36*1.1 -> 0 | AR36: =(AQ36*(-7%))+AQ36 -> 0 | AS36: =AR36+(AR36-(AR36*1.15)) -> 0
B37: 31 | C37: STILLO VERNACCIA | E37: 0270, 0271, 0275 e 0277 | H37: 2.7 | I37: =ROUNDUP(((AS37*$N$3)+AS37),1) -> 214.6 | K37: 0 | AA37: 148.2 | AD37: 154.2 | AE37: 169.7 | AG37: =AE37*1.06 -> 179.882 | AH37: =AG37*1.07 -> 192.47374 | AI37: =AH37 -> 192.47374 | AJ37: =AI37*1.05 -> 202.09743 | AK37: =AJ37 -> 202.09743 | AL37: 202.1 | AM37: =AL37*1.06 -> 214.226 | AO37: 182.3 | AP37: =AO37*1.07 -> 195.061 | AQ37: =AP37*1.1 -> 214.5671 | AR37: =AQ37 -> 214.5671 | AS37: 214.6
B38: 32 | E38: 0274 - PROMOÇÃO | H38: 2.5 | I38: =ROUNDUP(((AS38*$N$3)+AS38),1) -> 108.2 | K38: 0 | AA38: 148.2 | AD38: 154.2 | AE38: 74.3 | AF38: =67.5*1.1 -> 74.25 | AG38: =AE38*1.06 -> 78.758 | AH38: =AG38*1.1 -> 86.6338 | AI38: =AH38 -> 86.6338 | AJ38: =AI38 -> 86.6338 | AK38: =AJ38 -> 86.6338 | AL38: 86.7 | AM38: =AL38*1.06 -> 91.902 | AO38: =AM38 -> 91.902 | AP38: =AO38*1.07 -> 98.33514 | AQ38: =AP38*1.1 -> 108.16865 | AR38: =AQ38 -> 108.16865 | AS38: 108.2
B39: 33 | C39: AVALON | E39: 0526, 0527, 0528, 0529 e 0530 | H39: 2.7 | I39: =ROUNDUP(((AS39*$N$3)+AS39),1) -> 120.3 | K39: 0 | AH39: 120 | AI39: =AH39 -> 120 | AJ39: =AI39*1.05 -> 126 | AK39: =AJ39 -> 126 | AL39: 126 | AM39: =AL39*1.06 -> 133.56 | AO39: =AM39 -> 133.56 | AP39: =AO39*1.07 -> 142.9092 | AQ39: =AP39*1.1 -> 157.20012 | AR39: =(AQ39*(-10%))+AQ39 -> 141.48011 | AS39: =AR39+(AR39-(AR39*1.15)) -> 120.25809
B40: 34 | E40: 0518 | H40: 2.7 | I40: =ROUNDUP(((AS40*$N$3)+AS40),1) -> 151 | K40: 0 | AO40: 167.6 | AP40: =AO40*1.07 -> 179.332 | AQ40: =AP40*1.1 -> 197.2652 | AR40: =(AQ40*(-10%))+AQ40 -> 177.53868 | AS40: =AR40+(AR40-(AR40*1.15)) -> 150.90788
B41: 35 | C41: SANTORINI | E41: 0534 ao 0536 | H41: 2.7 | I41: =ROUNDUP(((AS41*$N$3)+AS41),1) -> 170.7 | K41: 0 | AD41: 141.1 | AE41: 155.3 | AG41: =AE41*1.06 -> 164.618 | AH41: =AG41*1.07 -> 176.14126 | AI41: =AH41 -> 176.14126 | AJ41: =AI41*1.05 -> 184.94832 | AK41: =AJ41 -> 184.94832 | AL41: 185 | AM41: =AL41*1.06 -> 196.1 | AO41: =AM41 -> 196.1 | AP41: =AO41*1.07 -> 209.827 | AQ41: =AP41*1.1 -> 230.8097 | AR41: =(AQ41*(-13%))+AQ41 -> 200.80444 | AS41: =AR41+(AR41-(AR41*1.15)) -> 170.68377
B42: 36 | C42: LEVANZO | E42: 0545 ao 0549 | H42: 2.7 | I42: =ROUNDUP(((AS42*$N$3)+AS42),1) -> 196.7 | K42: 0 | AD42: 148.5 | AE42: 163.4 | AG42: =AE42*1.06 -> 173.204 | AH42: =AG42*1.07 -> 185.32828 | AI42: =AH42 -> 185.32828 | AJ42: =AI42*1.05 -> 194.59469 | AK42: =AJ42 -> 194.59469 | AL42: 194.6 | AM42: =AL42*1.06 -> 206.276 | AO42: =AM42 -> 206.276 | AP42: =AO42*1.07 -> 220.71532 | AQ42: =AP42*1.1 -> 242.78685 | AR42: =(AQ42*(-10%))+AQ42 -> 218.50817 | AS42: =AR42+(AR42-(AR42*1.1)) -> 196.65735
B43: 37 | C43: CRETA | E43: 0557 ao 0561 | H43: 2.7 | I43: =ROUNDUP(((AS43*$N$3)+AS43),1) -> 185.8 | K43: 0 | AD43: 148.5 | AE43: 163.4 | AG43: =AE43*1.06 -> 173.204 | AH43: =AG43*1.07 -> 185.32828 | AI43: =AH43 -> 185.32828 | AJ43: =AI43*1.05 -> 194.59469 | AK43: =AJ43 -> 194.59469 | AL43: 194.6 | AM43: =AL43*1.06 -> 206.276 | AO43: =AM43 -> 206.276 | AP43: =AO43*1.07 -> 220.71532 | AQ43: =AP43*1.1 -> 242.78685 | AR43: =(AQ43*(-10%))+AQ43 -> 218.50817 | AS43: =AR43+(AR43-(AR43*1.15)) -> 185.73194
B44: 38 | AE44: =AE43 -> 163.4 | AG44: =AE44*1.06 -> 173.204 | AH44: =AG44*1.07 -> 185.32828 | AI44: =AH44 -> 185.32828 | AJ44: =AI44*1.05 -> 194.59469 | AK44: =AJ44 -> 194.59469 | AL44: 194.6 | AM44: =AL44*1.06 -> 206.276 | AO44: =AM44 -> 206.276 | AP44: =AO44*1.07 -> 220.71532 | AS44: =AR44+(AR44-(AR44*1.15)) -> 0
B45: 39 | C45: ISTAMBUL | E45: 1200, 1201, 1202, 1203, 1204 | H45: 2.8 | I45: =ROUNDUP(((AS45*$N$3)+AS45),1) -> 176.6 | K45: 0 | AO45: 196.1 | AP45: =AO45*1.07 -> 209.827 | AQ45: =AP45*1.1 -> 230.8097 | AR45: =(AQ45*(-10%))+AQ45 -> 207.72873 | AS45: =AR45+(AR45-(AR45*1.15)) -> 176.56942
B46: 40 | C46: ITACARÉ SEMI BK | E46: 0890 ao 0895 - LANÇAMENTOS | H46: 2.8 | I46: =ROUNDUP(((AS46*$N$3)+AS46),1) -> 292.3 | K46: 0 | AP46: 292.3 | AQ46: =AP46 -> 292.3 | AR46: =AQ46 -> 292.3 | AS46: 292.3
B47: 41 | C47: *** OS TECIDOS PROMOCIONAIS SÃO CONDICIONADOS A DISPONIBILIDADE NO ESTOQUE.
B48: 42 | C48: *** SOB ESTES VALORES PROMOCIONAIS NÃO INCIDIRÃO EVENTUAIS DESCONTOS. DESCONTO NÃO SE APLICA A ACESSÓRIOS SOLICITADOS COM A PEÇA. | N48: * DIGITE A PORCENTAGEM PARA MARKUP - ATENA
B49: 43 | C49: CORTINA ATENA | N49: 0 | AA49: Wave | AB49: Painel | AC49: Wave | AD49: Painel | AE49: Wave | AF49: Painel | AG49: Wave | AH49: Painel | AI49: Wave | AJ49: Painel | AK49: Wave | AL49: Painel | AM49: Wave | AN49: Painel | AO49: Wave | AP49: Painel | AQ49: Wave | AR49: Painel | AU49: Wave | AV49: Painel
B50: 44 | C50: CORTINA ATENA - WAVE | G50: CORTINA ATENA - PAINEL | K50: IPI | AA50: 385 | AB50: 143 | AC50: 415.8 | AD50: 154.44 | AE50: =AC50*1.1 -> 457.38 | AF50: =AD50*1.1 -> 169.884 | AG50: =AE50*1.1 -> 503.118 | AH50: =AF50*1.1 -> 186.8724 | AI50: =AG50*1.05 -> 528.2739 | AJ50: =AH50*1.05 -> 196.21602 | AK50: =AI50*1.05 -> 554.6876 | AL50: =AJ50*1.05 -> 206.02682 | AM50: 528.3 | AN50: 196.3 | AO50: =AM50*1.06 -> 559.998 | AP50: =AN50*1.06 -> 208.078 | AQ50: =AO50*1.07 -> 599.19786 | AR50: =AP50*1.07 -> 222.64346 | AU50: =AQ50*1.1 -> 659.11765 | AV50: =AR50*1.1 -> 244.90781
B51: 45 | C51: LARG. (M) | D51: À VISTA (R$)/ML | G51: MÓDULOS | H51: À VISTA (R$)/UN | K51: 0 | AA51: 385 | AB51: 154 | AC51: 415.8 | AD51: 166.32 | AE51: =AC51*1.1 -> 457.38 | AF51: =AD51*1.1 -> 182.952 | AG51: =AE51*1.1 -> 503.118 | AH51: =AF51*1.1 -> 201.2472 | AI51: =AG51*1.05 -> 528.2739 | AJ51: =AH51*1.05 -> 211.30956 | AK51: =AI51*1.05 -> 554.6876 | AL51: =AJ51*1.05 -> 221.87504 | AM51: 792.5 | AN51: 211.4 | AO51: 840.1 | AP51: =AN51*1.06 -> 224.084 | AQ51: =AO51*1.07 -> 898.907 | AR51: =AP51*1.07 -> 239.76988 | AU51: =AQ51*1.1 -> 988.7977 | AV51: =AR51*1.1 -> 263.74687
B52: 46 | C52: 1 | D52: =ROUNDUP((((AU50*$N$49)+AU50)*C52),1) -> 659.2 | G52: Até 70CM | H52: =ROUNDUP(((AV50*$N$49)+AV50),1) -> 245 | AA52: 385 | AB52: 165 | AC52: 415.8 | AD52: 178.2 | AE52: =AC52*1.1 -> 457.38 | AF52: =AD52*1.1 -> 196.02 | AG52: =AE52*1.1 -> 503.118 | AH52: =AF52*1.1 -> 215.622 | AI52: =AG52*1.05 -> 528.2739 | AJ52: =AH52*1.05 -> 226.4031 | AK52: =AI52*1.05 -> 554.6876 | AL52: =AJ52*1.05 -> 237.72326 | AM52: 1056.6 | AN52: 226.5 | AO52: =AM52*1.06 -> 1119.996 | AP52: =AN52*1.06 -> 240.09 | AQ52: =AO52*1.07 -> 1198.3957 | AR52: =AP52*1.07 -> 256.8963 | AU52: =AQ52*1.1 -> 1318.2353 | AV52: =AR52*1.1 -> 282.58593
B53: 47 | C53: 1.5 | D53: =ROUNDUP((((AU50*$N$49)+AU50)*C53),1) -> 988.7 | G53: Até 80CM | H53: =ROUNDUP(((AV51*$N$49)+AV51),1) -> 263.8 | AA53: 385 | AC53: 415.8 | AE53: =AC53*1.1 -> 457.38 | AF53: 208.1 | AG53: =AE53*1.1 -> 503.118 | AH53: =AF53*1.1 -> 228.91 | AI53: =AG53*1.05 -> 528.2739 | AJ53: =AH53*1.05 -> 240.3555 | AK53: =AI53*1.05 -> 554.6876 | AL53: =AJ53*1.05 -> 252.37328 | AM53: 1320.7 | AN53: 240.4 | AO53: =AM53*1.06 -> 1399.942 | AP53: =AN53*1.06 -> 254.824 | AQ53: =AO53*1.07 -> 1497.9379 | AR53: =AP53*1.07 -> 272.66168 | AU53: =AQ53*1.1 -> 1647.7317 | AV53: =AR53*1.1 -> 299.92785
B54: 48 | C54: 2 | D54: =ROUNDUP((((AU50*$N$49)+AU50)*C54),1) -> 1318.3 | G54: Até 90CM | H54: =ROUNDUP(((AV52*$N$49)+AV52),1) -> 282.6 | AA54: 385 | AC54: 415.8 | AE54: =AC54*1.1 -> 457.38 | AG54: =AE54*1.1 -> 503.118 | AI54: =AG54*1.05 -> 528.2739 | AK54: =AI54*1.05 -> 554.6876 | AM54: 1584.9 | AO54: =AM54*1.06 -> 1679.994 | AQ54: =AO54*1.07 -> 1797.5936 | AR54: =AP54*1.07 -> 0 | AU54: =AQ54*1.1 -> 1977.3529 | AV54: =AR54*1.1 -> 0
B55: 49 | C55: 2.5 | D55: =ROUNDUP((((AU50*$N$49)+AU50)*C55),1) -> 1647.8 | G55: Até 1M | H55: =ROUNDUP(((AV53*$N$49)+AV53),1) -> 300 | AA55: 385 | AC55: 415.8 | AE55: =AC55*1.1 -> 457.38 | AG55: =AE55*1.1 -> 503.118 | AI55: =AG55*1.05 -> 528.2739 | AK55: =AI55*1.05 -> 554.6876 | AM55: 1849 | AO55: =AM55*1.06 -> 1959.94 | AQ55: =AO55*1.07 -> 2097.1358 | AR55: =AP55*1.07 -> 0 | AU55: =AQ55*1.1 -> 2306.8494 | AV55: =AR55*1.1 -> 0
B56: 50 | C56: 3 | D56: =ROUNDUP((((AU50*$N$49)+AU50)*C56),1) -> 1977.4 | G56: CORES: | H56: 7001 AO 7004 | AA56: 385 | AC56: 415.8 | AE56: =AC56*1.1 -> 457.38 | AG56: =AE56*1.1 -> 503.118 | AI56: =AG56*1.05 -> 528.2739 | AK56: =AI56*1.05 -> 554.6876 | AM56: 2113.1 | AO56: =AM56*1.06 -> 2239.886 | AQ56: =AO56*1.07 -> 2396.678 | AR56: =AP56*1.07 -> 0 | AU56: =AQ56*1.1 -> 2636.3458 | AV56: =AR56*1.1 -> 0
B57: 51 | C57: 3.5 | D57: =ROUNDUP((((AU50*$N$49)+AU50)*C57),1) -> 2307 | AA57: 385 | AC57: 415.8 | AE57: =AC57*1.1 -> 457.38 | AG57: =AE57*1.1 -> 503.118 | AI57: =AG57*1.05 -> 528.2739 | AK57: =AI57*1.05 -> 554.6876 | AM57: 2377.3 | AO57: =AM57*1.06 -> 2519.938 | AQ57: =AO57*1.07 -> 2696.3337 | AR57: =AP57*1.07 -> 0 | AU57: =AQ57*1.1 -> 2965.967 | AV57: =AR57*1.1 -> 0
B58: 52 | C58: 4 | D58: =ROUNDUP((((AU50*$N$49)+AU50)*C58),1) -> 2636.5 | AA58: 385 | AC58: 415.8 | AE58: =AC58*1.1 -> 457.38 | AG58: =AE58*1.1 -> 503.118 | AI58: =AG58*1.05 -> 528.2739 | AK58: =AI58*1.05 -> 554.6876 | AM58: 2641.4 | AO58: =AM58*1.06 -> 2799.884 | AQ58: =AO58*1.07 -> 2995.8759 | AR58: =AP58*1.07 -> 0 | AU58: =AQ58*1.1 -> 3295.4635 | AV58: =AR58*1.1 -> 0
B59: 53 | C59: 4.5 | D59: =ROUNDUP((((AU50*$N$49)+AU50)*C59),1) -> 2966.1 | AA59: 385 | AC59: 415.8 | AE59: =AC59*1.1 -> 457.38 | AG59: =AE59*1.1 -> 503.118 | AI59: =AG59*1.05 -> 528.2739 | AK59: =AI59*1.05 -> 554.6876 | AM59: 2905.6 | AO59: =AM59*1.06 -> 3079.936 | AQ59: =AO59*1.07 -> 3295.5315 | AR59: =AP59*1.07 -> 0 | AU59: =AQ59*1.1 -> 3625.0847 | AV59: =AR59*1.1 -> 0
B60: 54 | C60: 5 | D60: =ROUNDUP((((AU50*$N$49)+AU50)*C60),1) -> 3295.6 | AA60: 385 | AC60: 415.8 | AE60: =AC60*1.1 -> 457.38 | AG60: =AE60*1.1 -> 503.118 | AI60: =AG60*1.05 -> 528.2739 | AK60: =AI60*1.05 -> 554.6876 | AM60: 3169.7 | AO60: =AM60*1.06 -> 3359.882 | AQ60: =AO60*1.07 -> 3595.0737 | AR60: =AP60*1.07 -> 0 | AU60: =AQ60*1.1 -> 3954.5811 | AV60: =AR60*1.1 -> 0
B61: 55 | C61: 5.5 | D61: =ROUNDUP((((AU50*$N$49)+AU50)*C61),1) -> 3625.2
B62: 56 | C62: 6 | D62: =ROUNDUP((((AU50*$N$49)+AU50)*C62),1) -> 3954.8
B63: 57 | C63: CORES: | D63: 7001 AO 7004
B64: 58 | C64: TRILHOS PARA CORTINA ATENA PAINEL | H64: COR | I64: UNIDADE | J64: VALOR À VISTA (R$)/ML | L64: IPI | AE64: 43258 | AF64: 43868 | AG64: 43958 | AH64: 43958 | AI64: 44111 | AJ64: 44256 | AK64: 44378 | AL64: 44501 | AO64: 45658
B65: 59 | C65: TRILHO DESLIZANTES DE 2 VIAS | H65: B - M - P | I65: ML | J65: =ROUNDUP(((AO65*$N$49)+AO65),1) -> 101.4 | L65: 0 | AA65: 42.5 | AC65: 42.5 | AD65: 45.9 | AE65: 50.5 | AF65: =AE65*1.1 -> 55.55 | AG65: =AF65*1.1 -> 61.105 | AH65: =AG65 -> 61.105 | AI65: =AH65*1.05 -> 64.16025 | AJ65: =AI65*1.1 -> 70.576275 | AK65: =AJ65 -> 70.576275 | AL65: 70.6 | AM65: 86.1 | AN65: =AM65*1.07 -> 92.127 | AO65: =AN65*1.1 -> 101.3397
B66: 60 | C66: TRILHO DESLIZANTES DE 3 VIAS | H66: B - M - P | I66: ML | J66: =ROUNDUP(((AO66*$N$49)+AO66),1) -> 120.3 | L66: 0 | AA66: 50.4 | AC66: 50.4 | AD66: 54.5 | AE66: 60 | AF66: =AE66*1.1 -> 66 | AG66: =AF66*1.1 -> 72.6 | AH66: =AG66 -> 72.6 | AI66: =AH66*1.05 -> 76.23 | AJ66: =AI66*1.1 -> 83.853 | AK66: =AJ66 -> 83.853 | AL66: 83.9 | AM66: 102.2 | AN66: =AM66*1.07 -> 109.354 | AO66: =AN66*1.1 -> 120.2894
B67: 61 | C67: TRILHO DESLIZANTES DE 4 VIAS | H67: B - M - P | I67: ML | J67: =ROUNDUP(((AO67*$N$49)+AO67),1) -> 136.5 | L67: 0 | AA67: 57.2 | AC67: 57.2 | AD67: 61.8 | AE67: 68 | AF67: =AE67*1.1 -> 74.8 | AG67: =AF67*1.1 -> 82.28 | AH67: =AG67 -> 82.28 | AI67: =AH67*1.05 -> 86.394 | AJ67: =AI67*1.1 -> 95.0334 | AK67: =AJ67 -> 95.0334 | AL67: 95.1 | AM67: 115.9 | AN67: =AM67*1.07 -> 124.013 | AO67: =AN67*1.1 -> 136.4143
B68: 62 | C68: TRILHO DESLIZANTES DE 5 VIAS | H68: B - M - P | I68: ML | J68: =ROUNDUP(((AO68*$N$49)+AO68),1) -> 156.4 | L68: 0 | AA68: 65.5 | AC68: 65.5 | AD68: 70.8 | AE68: 77.9 | AF68: =AE68*1.1 -> 85.69 | AG68: =AF68*1.1 -> 94.259 | AH68: =AG68 -> 94.259 | AI68: =AH68*1.05 -> 98.97195 | AJ68: =AI68*1.1 -> 108.86915 | AK68: =AJ68 -> 108.86915 | AL68: 108.9 | AM68: 132.8 | AN68: =AM68*1.07 -> 142.096 | AO68: =AN68*1.1 -> 156.3056
B69: 63 | C69: INFORMAÇÕES GERAIS - CORTINA ATENA
B70: 64 | C70: ALTURA MÁXIMA: 3,20M. - LARGURA MÁXIMA: 6,00M. TRILHO 4001 SOMENTE NA COR BRANCA.
B71: 65 | C71: TRILHO SUPERIOR MODELO 4001. VALOR DO TRILHO JÁ INCLUSO NO MODELO CORTINA ATENA WAVE MANUAL (TRILHO 4001)
B72: 66 | C72: CORDÃO E PÊNDULO ACOMPANHAM A COR APROXIMADA DO TECIDO. ENTREGA: 5 DIAS ÚTEIS. ATENÇÃO: A CORTINA ATENA WAVE É COBRADA POR METRO LINEAR.
B73: 67 | C73: ATENÇÃO: A CORTINA ATENA PAINEL É COBRADA PELA QUANTIDADE DE MÓDULOS + O METRO LINEAR DO TRILHO DESLIZANTE.
K74: Página 10 - | L74: =Rolô!L2 -> 2026 - v.03 | N74: * DIGITE A PORCENTAGEM PARA MARKUP - ACESSÓRIOS
B75: CORTINAS LINHA PREMIUM | N75: 0
B76: PRODUTO EM CONFORMIDADE COM A NORMA ABNT NBR 16234: 2014
B78: 68 | C78: ACESSÓRIOS
B79: 69 | C79: DESCRIÇÃO DO ACESSÓRIO | H79: COR | I79: UNIDADE | J79: VALOR À VISTA (R$) | L79: IPI | N79: * Legenda de Cores: | AA79: 42491 | AC79: 42491 | AE79: 43862 | AF79: 43952 | AG79: 44105 | AH79: 44256 | AI79: 44287 | AJ79: 44501
B80: 70 | C80: CORTINAS DA LINHA PREMIUM (EXCETO PASSIONE) NOS MODELOS DUPLEX OU TRIPLEX ACRESCER VALOR POR PEÇA (QUANDO INSTALADAS NO MESMO BANDÔ OU BARRA NIVELADORA) | H80: - | I80: - | J80: =ROUNDUP(((AM81*$N$75)+AM81),1) -> 33.2 | L80: - | N80: B = Branco | AA80: 15 | AC80: 15 | AD80: =AC80*1.1 -> 16.5 | AM80: 45658
B81: 71 | N81: M = Marfim | AE81: =AD80*1.1 -> 18.15 | AF81: =AE81*1.1 -> 19.965 | AG81: =AF81*1.05 -> 20.96325 | AH81: =AG81*1.1 -> 23.059575 | AI81: =AH81*1.15 -> 26.518511 | AJ81: 26.6 | AK81: =AJ81*1.06 -> 28.196 | AL81: =AK81*1.07 -> 30.16972 | AM81: =AL81*1.1 -> 33.186692
B82: 72 | N82: P = Preto | AK82: =AJ82*1.06 -> 0 | AL82: =AK82*1.07 -> 0 | AM82: =AL82*1.1 -> 0
B83: 73 | C83: BANDÔ CONJUGADO PARA CORTINAS PREMIUM (LARGURA MÁXIMA 3,50M) | H83: vide linha 153 | I83: ML | J83: =ROUNDUP(((AM84*$N$75)+AM84),1) -> 106.6 | L83: 0 | N83: C = Cinza | AA83: 46.75 | AC83: 50.5 | AD83: =AC83*1.1 -> 55.55 | AE83: =AD83*1.1 -> 61.105 | AF83: =AE83*1.1 -> 67.2155 | AG83: =AF83*1.05 -> 70.576275 | AH83: =AG83*1.1 -> 77.633903 | AI83: =AH83*1.1 -> 85.397293 | AK83: =AJ83*1.06 -> 0 | AL83: =AK83*1.07 -> 0 | AM83: =AL83*1.1 -> 0
B84: 74 | N84: MR = Marrom | AJ84: 85.4 | AK84: =AJ84*1.06 -> 90.524 | AL84: =AK84*1.07 -> 96.86068 | AM84: =AL84*1.1 -> 106.54675
B85: 75 | C85: BARRA NIVELADORA - PARA TUBOS DE 32MM E 38MM | H85: vide linha 153 | I85: ML | J85: =ROUNDUP(((AM85*$N$75)+AM85),1) -> 17.6 | L85: 0 | AA85: 15.2 | AC85: 16.5 | AD85: =AC85*1.1 -> 18.15 | AE85: =AD85*1.1 -> 19.965 | AF85: =AE85*1.1 -> 21.9615 | AG85: =AF85*1.05 -> 23.059575 | AH85: =AG85*1.1 -> 25.365533 | AI85: =AH85*1.1 -> 27.902086 | AJ85: 28 | AK85: 14.9 | AL85: =AK85*1.07 -> 15.943 | AM85: =AL85*1.1 -> 17.5373
B86: 76 | C86: BARRA NIVELADORA LARGA - PARA TUBOS DE 53MM. | H86: vide linha 153 | I86: ML | J86: =ROUNDUP(((AM86*$N$75)+AM86),1) -> 22.9 | L86: 0 | AD86: 23.7 | AE86: =AD86*1.1 -> 26.07 | AF86: =AE86*1.1 -> 28.677 | AG86: =AF86*1.05 -> 30.11085 | AH86: =AG86*1.1 -> 33.121935 | AI86: =AH86*1.1 -> 36.434129 | AJ86: 36.5 | AK86: 19.4 | AL86: =AK86*1.07 -> 20.758 | AM86: =AL86*1.1 -> 22.8338
B87: 77 | C87: BANDÔ SEMI BOX - PARA TUBOS DE 53MM ATÉ 88MM. | H87: vide linha 153 | I87: ML | J87: =ROUNDUP(((AM87*$N$75)+AM87),1) -> 239.3 | L87: 0 | AD87: 124.8 | AE87: =AD87*1.1 -> 137.28 | AF87: 150.9 | AG87: 158.51 | AH87: =AG87*1.1 -> 174.361 | AI87: =AH87*1.1 -> 191.7971 | AJ87: 191.8 | AK87: =AJ87*1.06 -> 203.308 | AL87: =AK87*1.07 -> 217.53956 | AM87: =AL87*1.1 -> 239.29352
B88: 78 | C88: BANDÔ BOX - PARA TUBOS DE 53MM ATÉ 88MM. | H88: vide linha 153 | I88: UN | J88: =ROUNDUP(((AM88*$N$75)+AM88),1) -> 341.9 | L88: 0 | AD88: 178.2 | AE88: =AD88*1.1 -> 196.02 | AF88: =AE88*1.1 -> 215.622 | AG88: =AF88*1.05 -> 226.4031 | AH88: =AG88*1.1 -> 249.04341 | AI88: =AH88*1.1 -> 273.94775 | AJ88: 274 | AK88: =AJ88*1.06 -> 290.44 | AL88: =AK88*1.07 -> 310.7708 | AM88: =AL88*1.1 -> 341.84788
B89: 79 | AL89: =AK89*1.07 -> 0 | AM89: =AL89*1.1 -> 0
B90: 80 | C90: CORRENTE METÁLICA - COBRADO 2X O TAMANHO DO COMANDO (TC). (LANÇAMENTOS) | H90: Inox - Bronze - Ouro Velho - Preto Niquelado | I90: ML | J90: =ROUNDUP(((AM90*$N$75)+AM90),1) -> 17.4 | L90: 0 | AA90: 6.6 | AC90: 7.2 | AD90: =AC90*1.1 -> 7.92 | AE90: =AD90*1.2 -> 9.504 | AF90: =AE90*1.1 -> 10.4544 | AG90: =AF90*1.05 -> 10.97712 | AH90: =AG90*1.1 -> 12.074832 | AI90: =AH90*1.15 -> 13.886057 | AJ90: 13.9 | AK90: =AJ90*1.06 -> 14.734 | AL90: =AK90*1.07 -> 15.76538 | AM90: =AL90*1.1 -> 17.341918
B91: 81
B92: 82 | C92: SUPORTE REDUTOR DE FRESTAS SEM JUNÇÃO (DUAS PEÇAS COM COMANDOS INDEPENDENTES) | H92: B - M - P | I92: UN | J92: =ROUNDUP(((AM92*$N$75)+AM92),1) -> 53 | L92: 0.1 | AA92: 35.4 | AC92: 38.3 | AD92: =AC92*1.1 -> 42.13 | AE92: =AD92*1.2 -> 50.556 | AF92: =AE92*1.1 -> 55.6116 | AG92: =AF92*1.05 -> 58.39218 | AH92: =AG92*1.1 -> 64.231398 | AI92: =AH92*1.15 -> 73.866108 | AJ92: 73.9 | AK92: 45 | AL92: =AK92*1.07 -> 48.15 | AM92: =AL92*1.1 -> 52.965
B93: 83 | AK93: =AJ93*1.06 -> 0 | AL93: =AK93*1.07 -> 0 | AM93: =AL93*1.1 -> 0
B94: 84 | C94: REDUTOR DE PESO 38MM COM MOLA (COMANDO REDONDO) | H94: vide linha 153 | I94: UN | J94: =ROUNDUP(((AM94*$N$75)+AM94),1) -> 47.1 | L94: 0 | AA94: 78.3 | AC94: 84.6 | AD94: =AC94*1.1 -> 93.06 | AE94: =AD94*1.1 -> 102.366 | AF94: =AE94*1.1 -> 112.6026 | AG94: =AF94*1.05 -> 118.23273 | AH94: =AG94*1.1 -> 130.056 | AI94: =AH94*1.1 -> 143.0616 | AJ94: 143.1 | AK94: 40 | AL94: =AK94*1.07 -> 42.8 | AM94: =AL94*1.1 -> 47.08
B95: 85 | C95: SUPORTE AFASTADOR 4 X 6 | H95: B - M - P | I95: UN | J95: =ROUNDUP(((AM95*$N$75)+AM95),1) -> 6.4 | L95: 0.1 | AA95: 2.4 | AC95: 2.6 | AD95: =AC95*1.1 -> 2.86 | AE95: =AD95*1.2 -> 3.432 | AF95: =AE95*1.1 -> 3.7752 | AG95: =AF95*1.05 -> 3.96396 | AH95: =AG95*1.1 -> 4.360356 | AI95: =AH95*1.15 -> 5.0144094 | AJ95: 5.1 | AK95: =AJ95*1.06 -> 5.406 | AL95: =AK95*1.07 -> 5.78442 | AM95: =AL95*1.1 -> 6.362862
B96: 86 | C96: SUPORTE AFASTADOR 6 X 9 | H96: B - M - P | I96: CJ | J96: =ROUNDUP(((AM96*$N$75)+AM96),1) -> 8 | L96: 0.1 | AA96: 3 | AC96: 3.3 | AD96: =AC96*1.1 -> 3.63 | AE96: =AD96*1.2 -> 4.356 | AF96: =AE96*1.1 -> 4.7916 | AG96: =AF96*1.05 -> 5.03118 | AH96: =AG96*1.1 -> 5.534298 | AI96: =AH96*1.15 -> 6.3644427 | AJ96: 6.4 | AK96: =AJ96*1.06 -> 6.784 | AL96: =AK96*1.07 -> 7.25888 | AM96: =AL96*1.1 -> 7.984768
B97: 87 | C97: SUPORTE ALONGADO 38MM | H97: Branco | I97: UN | J97: =ROUNDUP(((AM97*$N$75)+AM97),1) -> 64.3 | L97: 0 | AA97: 22.4 | AC97: 24.2 | AD97: 29.4 | AE97: 35.24 | AF97: =AE97*1.1 -> 38.764 | AG97: =AF97*1.05 -> 40.7022 | AH97: =AG97*1.1 -> 44.77242 | AI97: =AH97*1.15 -> 51.488283 | AJ97: 51.5 | AK97: =AJ97*1.06 -> 54.59 | AL97: =AK97*1.07 -> 58.4113 | AM97: =AL97*1.1 -> 64.25243
B98: 88 | C98: BANDÔ DE PERSIANA VERTICAL PARA CORTINA PASSIONE (REVESTIDO COM O PRÓPRIO TECIDO DA CORTINA) | H98: B - M - P | I98: ML | J98: =ROUNDUP(((AM98*$N$75)+AM98),1) -> 53.3 | L98: 0 | AA98: 21.3 | AC98: 23.1 | AD98: =AC98*1.1 -> 25.41 | AE98: =AD98*1.1 -> 27.951 | AF98: =AE98*1.1 -> 30.7461 | AG98: =AF98*1.05 -> 32.283405 | AH98: =AG98*1.1 -> 35.511746 | AI98: =AH98*1.2 -> 42.614095 | AJ98: 42.7 | AK98: =AJ98*1.06 -> 45.262 | AL98: =AK98*1.07 -> 48.43034 | AM98: =AL98*1.1 -> 53.273374
B99: 89 | AK99: =AJ99*1.06 -> 0 | AL99: =AK99*1.07 -> 0 | AM99: =AL99*1.1 -> 0
B100: 90 | C100: SUPORTE 10 X 20 PARA CORTINA PASSIONE COM BANDÔ | H100: Natural | I100: UN | J100: =ROUNDUP(((AM100*$N$75)+AM100),1) -> 18.5 | L100: 0.1 | AA100: 5.2 | AC100: 5.7 | AD100: =AC100*1.1 -> 6.27 | AE100: =AD100*1.5 -> 9.405 | AF100: =AE100*1.1 -> 10.3455 | AG100: =AF100*1.05 -> 10.862775 | AH100: =AG100*1.1 -> 11.949053 | AI100: =AH100*1.15 -> 13.74141 | AJ100: 13.8 | AK100: 15.7 | AL100: =AK100*1.07 -> 16.799 | AM100: =AL100*1.1 -> 18.4789
B101: 91 | C101: SUPORTE 8 X 13 SEM ENCAIXE PARA CORTINA PASSIONE | H101: Natural | I101: UN | J101: =ROUNDUP(((AM101*$N$75)+AM101),1) -> 5.8 | L101: 0.1 | AA101: 1.8 | AC101: 2 | AD101: =AC101*1.1 -> 2.2 | AE101: =AD101*1.5 -> 3.3 | AF101: =AE101*1.1 -> 3.63 | AG101: =AF101*1.05 -> 3.8115 | AH101: =AG101*1.1 -> 4.19265 | AI101: =AH101*1.15 -> 4.8215475 | AJ101: 4.9 | AK101: 4.85 | AL101: =AK101*1.07 -> 5.1895 | AM101: =AL101*1.1 -> 5.70845
B102: 92 | C102: MECANISMO DE 53MM SEM REDUTOR DE PESO. | H102: - | I102: ML | J102: =ROUNDUP(((AM102*$N$75)+AM102),1) -> 86.3 | L102: 0 | AF102: 108.7 | AG102: =AF102*1.05 -> 114.135 | AH102: =AG102*1.1 -> 125.5485 | AI102: =AH102*1.1 -> 138.10335 | AJ102: 138.2 | AK102: 73.3 | AL102: =AK102*1.07 -> 78.431 | AM102: =AL102*1.1 -> 86.2741
B103: 93 | C103: BANDÔ FLAT | H103: - | I103: ML | J103: =ROUNDUP(((AM103*$N$75)+AM103),1) -> 122.9 | L103: 0 | AF103: 77.5 | AG103: =AF103*1.05 -> 81.375 | AH103: =AG103*1.1 -> 89.5125 | AI103: =AH103*1.1 -> 98.46375 | AJ103: 98.5 | AK103: =AJ103*1.06 -> 104.41 | AL103: =AK103*1.07 -> 111.7187 | AM103: =AL103*1.1 -> 122.89057
...

Sheet Romana
K2: Página 12 - | L2: =Rolô!L2 -> 2026 - v.03 | N2: * DIGITE A PORCENTAGEM PARA MARKUP
B3: CORTINA ROMANA | N3: 0
B4: PRODUTO EM CONFORMIDADE COM A NORMA ABNT NBR 16234: 2014
B6: ITEM | C6: COLEÇÃO | E6: COR | H6: LAR. MAX. | I6: VALOR À VISTA (R$)/M² | K6: IPI | AA6: 42491 | AB6: 43026 | AC6: 43258 | AE6: 43862 | AF6: 43891 | AG6: 43952 | AH6: 44105 | AI6: 44256 | AJ6: 44287 | AK6: 44501 | AN6: 44682 | AP6: desc/acres | AU6: 45658
B7: 1 | C7: SCREEN 1% | E7: 0001, 0005 e 0006, 1010, 1030 e 1031 | H7: 3 | I7: =ROUNDUP(((AV7*$N$3)+AV7),1) -> 211 | K7: 0 | AA7: 146.1 | AB7: 157.8 | AC7: 173.6 | AE7: =AC7*1.06 -> 184.016 | AG7: =AE7*1.1 -> 202.4176 | AH7: =AG7 -> 202.4176 | AI7: =AH7 -> 202.4176 | AJ7: =AI7 -> 202.4176 | AK7: 202.5 | AL7: =AK7*1.06 -> 214.65 | AN7: =Rolô!I7*1.14 -> 189.924 | AO7: 210.9 | AP7: =AN7-AL7 -> -24.726 | AQ7: =AO7*1.07 -> 225.663 | AU7: =AQ7*1.1 -> 248.2293 | AV7: =AU7+(AU7-(AU7*1.15)) -> 210.99491
B8: 2 | C8: SCREEN FIBER GLASS 1% | E8: 6001 | H8: 3 | I8: =ROUNDUP(((AV8*$N$3)+AV8),1) -> 304.8 | K8: 0 | AA8: 175 | AB8: 189 | AC8: 207.9 | AE8: =AC8*1.06 -> 220.374 | AG8: =AE8*1.15 -> 253.4301 | AH8: =AG8*1.08 -> 273.70451 | AI8: =AH8*1.05 -> 287.38973 | AJ8: =AI8 -> 287.38973 | AK8: 287.4 | AL8: =AK8*1.06 -> 304.644 | AN8: =AL8 -> 304.644 | AO8: 304.644 | AP8: =AN8-AL8 -> 0 | AQ8: =AO8*1.07 -> 325.96908 | AU8: =AQ8*1.1 -> 358.56599 | AV8: =AU8+(AU8-(AU8*1.15)) -> 304.78109
B9: 3 | C9: SCREEN 3% | E9: 3001, 3002, 3008, 3017, 3060 e 3061 | H9: 3 | I9: =ROUNDUP(((AV9*$N$3)+AV9),1) -> 190.9 | K9: 0 | AA9: 128.4 | AB9: 138.7 | AC9: 152.6 | AE9: =AC9*1.06 -> 161.756 | AG9: =AE9*1.08 -> 174.69648 | AH9: =AG9 -> 174.69648 | AI9: =AH9 -> 174.69648 | AJ9: =AI9*1.03 -> 179.93737 | AK9: 180 | AL9: =AK9*1.06 -> 190.8 | AN9: =AL9 -> 190.8 | AO9: 190.8 | AP9: =AN9-AL9 -> 0 | AQ9: =AO9*1.07 -> 204.156 | AU9: =AQ9*1.1 -> 224.5716 | AV9: =AU9+(AU9-(AU9*1.15)) -> 190.88586
B10: 4 | E10: 3009 ao 3011, 3018 e 3019 | H10: 3 | I10: =ROUNDUP(((AV10*$N$3)+AV10),1) -> 204.4 | K10: 0 | AA10: 128.4 | AB10: 138.7 | AC10: 152.6 | AE10: =AC10*1.06 -> 161.756 | AG10: =AE10*1.08 -> 174.69648 | AH10: =AG10 -> 174.69648 | AI10: =AH10*1.05 -> 183.4313 | AJ10: =AI10*1.05 -> 192.60287 | AK10: 192.7 | AL10: =AK10*1.06 -> 204.262 | AN10: =AL10 -> 204.262 | AO10: 204.262 | AP10: =AN10-AL10 -> 0 | AQ10: =AO10*1.07 -> 218.56034 | AU10: =AQ10*1.1 -> 240.41637 | AV10: =AU10+(AU10-(AU10*1.15)) -> 204.35392
B11: 5 | E11: 3012 e 3013 | H11: 3 | I11: =ROUNDUP(((AV11*$N$3)+AV11),1) -> 194.6 | K11: 0 | AI11: 183.43 | AJ11: =AI11 -> 183.43 | AK11: 183.5 | AL11: =AK11*1.06 -> 194.51 | AN11: =AL11 -> 194.51 | AO11: 194.51 | AP11: =AN11-AL11 -> 0 | AQ11: =AO11*1.07 -> 208.1257 | AU11: =AQ11*1.1 -> 228.93827 | AV11: =AU11+(AU11-(AU11*1.15)) -> 194.59753
B12: 6 | E12: 3014, 3015 | H12: 3 | I12: =ROUNDUP(((AV12*$N$3)+AV12),1) -> 213.4 | K12: 0 | AE12: =AE10 -> 161.756 | AG12: =AE12*1.15 -> 186.0194 | AH12: =AG12 -> 186.0194 | AI12: =AH12*1.05 -> 195.32037 | AJ12: =AI12*1.03 -> 201.17998 | AK12: 201.2 | AL12: =AK12*1.06 -> 213.272 | AN12: =AL12 -> 213.272 | AO12: 213.272 | AP12: =AN12-AL12 -> 0 | AQ12: =AO12*1.07 -> 228.20104 | AU12: =AQ12*1.1 -> 251.02114 | AV12: =AU12+(AU12-(AU12*1.15)) -> 213.36797
B13: 7 | C13: SCREEN FIBER GLASS 3% | E13: 6101 | H13: 3 | I13: =ROUNDUP(((AV13*$N$3)+AV13),1) -> 268.6 | K13: 0 | AA13: 154 | AB13: 166.4 | AC13: 183.1 | AE13: =AC13*1.06 -> 194.086 | AG13: =AE13*1.15 -> 223.1989 | AH13: =AG13*1.08 -> 241.05481 | AI13: =AH13*1.05 -> 253.10755 | AJ13: =AI13 -> 253.10755 | AK13: 253.2 | AL13: =AK13*1.06 -> 268.392 | AN13: =AL13 -> 268.392 | AO13: 268.392 | AP13: =AN13-AL13 -> 0 | AQ13: =AO13*1.07 -> 287.17944 | AU13: =AQ13*1.1 -> 315.89738 | AV13: =AU13+(AU13-(AU13*1.15)) -> 268.51278
B14: 8 | C14: SCREEN 5% | E14: 3070 ao 3076, 3078 e 3079 | H14: 3 | I14: =ROUNDUP(((AV14*$N$3)+AV14),1) -> 178.2 | K14: 0 | AA14: 119.8 | AB14: 129.4 | AC14: 142.4 | AE14: =AC14*1.06 -> 150.944 | AG14: =AE14*1.08 -> 163.01952 | AH14: =AG14 -> 163.01952 | AI14: =AH14 -> 163.01952 | AJ14: =AI14*1.03 -> 167.91011 | AK14: 168 | AL14: =AK14*1.06 -> 178.08 | AN14: =AL14 -> 178.08 | AO14: 178.08 | AP14: =AN14-AL14 -> 0 | AQ14: =AO14*1.07 -> 190.5456 | AU14: =AQ14*1.1 -> 209.60016 | AV14: =AU14+(AU14-(AU14*1.15)) -> 178.16014
B15: 9 | E15: 3096, 3097 e 3098 | H15: 2.5 | AQ15: =AO15*1.07 -> 0 | AU15: =AQ15*1.1 -> 0 | AV15: =AU15+(AU15-(AU15*1.15)) -> 0
B16: 10 | C16: SCREEN FIBER GLASS 5% | E16: 6202 | H16: 3 | I16: =ROUNDUP(((AV16*$N$3)+AV16),1) -> 250.7 | K16: 0 | AA16: 143.8 | AB16: 155.4 | AC16: 171 | AE16: =AC16*1.06 -> 181.26 | AG16: =AE16*1.15 -> 208.449 | AH16: =AG16*1.08 -> 225.12492 | AI16: =AH16*1.05 -> 236.38117 | AJ16: =AI16 -> 236.38117 | AK16: 236.4 | AL16: =AK16*1.06 -> 250.584 | AN16: =AL16 -> 250.584 | AO16: 250.584 | AP16: =AN16-AL16 -> 0 | AQ16: =AO16*1.07 -> 268.12488 | AU16: =AQ16*1.1 -> 294.93737 | AV16: =AU16+(AU16-(AU16*1.15)) -> 250.69676
B17: 11 | C17: SCREEN CRISTAL 5% | E17: 3100 | H17: 3 | I17: =ROUNDUP(((AV17*$N$3)+AV17),1) -> 229.6 | K17: 0 | AA17: 146.1 | AB17: 157.8 | AC17: 173.6 | AE17: =AC17*1.06 -> 184.016 | AG17: =AE17*1.12 -> 206.09792 | AH17: =AG17 -> 206.09792 | AI17: =AH17*1.05 -> 216.40282 | AJ17: =AI17 -> 216.40282 | AK17: 216.5 | AL17: =AK17*1.06 -> 229.49 | AN17: =AL17 -> 229.49 | AO17: 229.49 | AP17: =AN17-AL17 -> 0 | AQ17: =AO17*1.07 -> 245.5543 | AU17: =AQ17*1.1 -> 270.10973 | AV17: =AU17+(AU17-(AU17*1.15)) -> 229.59327
B18: 12 | C18: SCREEN RÚSTICO 3% | E18: 3150 e 3151 | H18: 3 | I18: =ROUNDUP(((AV18*$N$3)+AV18),1) -> 205.3 | K18: 0 | AA18: 127.1 | AB18: 137.3 | AC18: 151.1 | AE18: =AC18*1.06 -> 160.166 | AG18: =AE18*1.15 -> 184.1909 | AH18: =AG18 -> 184.1909 | AI18: =AH18*1.05 -> 193.40044 | AJ18: =AI18 -> 193.40044 | AK18: 193.5 | AL18: =AK18*1.06 -> 205.11 | AN18: =AL18 -> 205.11 | AO18: 205.11 | AP18: =AN18-AL18 -> 0 | AQ18: =AO18*1.07 -> 219.4677 | AU18: =AQ18*1.1 -> 241.41447 | AV18: =AU18+(AU18-(AU18*1.15)) -> 205.2023
B19: 13 | C19: SCREEN RÚSTICO 5% | E19: 3159, 3160, 3161, 3162 e 3163 | H19: 2.5 | I19: =ROUNDUP(((AV19*$N$3)+AV19),1) -> 202.4 | K19: 0 | AE19: =#REF! -> #REF! | AG19: =AE19*1.08 -> #REF! | AH19: =AG19*1.05 -> #REF! | AI19: =AH19*1.05 -> #REF! | AJ19: =AI19 -> #REF! | AK19: 190.8 | AL19: =AK19*1.06 -> 202.248 | AN19: =AL19 -> 202.248 | AO19: 202.248 | AP19: =AN19-AL19 -> 0 | AQ19: =AO19*1.07 -> 216.40536 | AU19: =AQ19*1.1 -> 238.0459 | AV19: =AU19+(AU19-(AU19*1.15)) -> 202.33901
B20: 14 | E20: 3155 e 3156 | H20: 3 | I20: =ROUNDUP(((AV20*$N$3)+AV20),1) -> 225.7 | K20: 0 | AA20: 127.1 | AB20: 137.3 | AC20: 151.1 | AE20: =AC20*1.06 -> 160.166 | AG20: =AE20*1.15 -> 184.1909 | AH20: =AG20*1.05 -> 193.40044 | AI20: =AH20*1.1 -> 212.74049 | AJ20: =AI20 -> 212.74049 | AK20: 212.8 | AL20: =AK20*1.06 -> 225.568 | AN20: =AL20 -> 225.568 | AO20: 225.568 | AP20: =AN20-AL20 -> 0 | AQ20: =AO20*1.07 -> 241.35776 | AU20: =AQ20*1.1 -> 265.49354 | AV20: =AU20+(AU20-(AU20*1.15)) -> 225.66951
B21: 15 | C21: SCREEN REFLEX | E21: 3121, 3122 e 3123 | H21: 3 | I21: =ROUNDUP(((AV21*$N$3)+AV21),1) -> 275 | K21: 0 | AA21: 167 | AB21: 180.4 | AC21: 198.5 | AE21: =AC21*1.06 -> 210.41 | AG21: =AE21*1.12 -> 235.6592 | AH21: =AG21 -> 235.6592 | AI21: =AH21*1.1 -> 259.22512 | AJ21: =AI21 -> 259.22512 | AK21: 259.3 | AL21: =AK21*1.06 -> 274.858 | AN21: =AL21 -> 274.858 | AO21: 274.858 | AP21: =AN21-AL21 -> 0 | AQ21: =AO21*1.07 -> 294.09806 | AU21: =AQ21*1.1 -> 323.50787 | AV21: =AU21+(AU21-(AU21*1.15)) -> 274.98169
B22: 16 | C22: SCREEN BK | E22: 3200, 3201 e 3203 | H22: 2.5 | I22: =ROUNDUP(((AV22*$N$3)+AV22),1) -> 283.1 | K22: 0 | AO22: 282.9 | AQ22: =AO22*1.07 -> 302.703 | AU22: =AQ22*1.1 -> 332.9733 | AV22: =AU22+(AU22-(AU22*1.15)) -> 283.02731
B23: 17 | C23: IBIZA | E23: 3350, 3351 e 3353 | H23: 2.6 | I23: =ROUNDUP(((AV23*$N$3)+AV23),1) -> 202.5 | K23: 0 | AA23: 110.9 | AB23: 119.8 | AC23: 131.8 | AE23: =AC23*1.06 -> 139.708 | AG23: =AE23*1.15 -> 160.6642 | AH23: =AG23*1.08 -> 173.51734 | AI23: =AH23*1.1 -> 190.86907 | AJ23: =AI23 -> 190.86907 | AK23: 190.9 | AL23: =AK23*1.06 -> 202.354 | AN23: =AL23 -> 202.354 | AO23: 202.354 | AP23: =AN23-AL23 -> 0 | AQ23: =AO23*1.07 -> 216.51878 | AU23: =AQ23*1.1 -> 238.17066 | AV23: =AU23+(AU23-(AU23*1.15)) -> 202.44506
B24: 18 | C24: BLACKOUT PINPOINT | E24: 0180 ao 0183 e 0186 ao 0190 - larg. especial 2.5 | H24: 2.5 | I24: =ROUNDUP(((AV24*$N$3)+AV24),1) -> 187.8 | K24: 0.1 | AA24: 127.6 | AB24: 137.9 | AC24: 151.7 | AE24: =AC24*1.06 -> 160.802 | AG24: =AE24*1.12 -> 180.09824 | AH24: =AG24*1.05 -> 189.10315 | AI24: =AH24*1.05 -> 198.55831 | AJ24: =AI24*1.05 -> 208.48623 | AK24: 208.5 | AL24: =AK24*1.06 -> 221.01 | AN24: =Rolô!I24*1.14 -> 169.062 | AO24: 187.644 | AP24: =AN24-AL24 -> -51.948 | AQ24: =AO24*1.07 -> 200.77908 | AU24: =AQ24*1.1 -> 220.85699 | AV24: =AU24+(AU24-(AU24*1.15)) -> 187.72844
B25: 19 | AE25: =AE24 -> 160.802 | AG25: =AE25*1.12 -> 180.09824 | AQ25: =AO25*1.07 -> 0 | AU25: =AQ25*1.1 -> 0 | AV25: =AU25+(AU25-(AU25*1.15)) -> 0
B26: 20 | E26: 0180 ao 0183 e 0186, 0187 e 0190 - larg. especial 3 | H26: 3 | I26: =ROUNDUP(((AV26*$N$3)+AV26),1) -> 193.6 | K26: 0.1 | AE26: =AE25 -> 160.802 | AG26: =AE26*1.15 -> 184.9223 | AH26: =AG26*1.05 -> 194.16841 | AI26: =AH26*1.05 -> 203.87684 | AJ26: =AI26*1.05 -> 214.07068 | AK26: 214.1 | AL26: =AK26*1.06 -> 226.946 | AN26: =Rolô!I26*1.14 -> 174.192 | AO26: 193.458 | AP26: =AN26-AL26 -> -52.754 | AQ26: =AO26*1.07 -> 207.00006 | AU26: =AQ26*1.1 -> 227.70007 | AV26: =AU26+(AU26-(AU26*1.15)) -> 193.54506
B27: 21 | E27: 0180 ao 0183 e 0186, 0187 e 0190 | H27: 2 | I27: =ROUNDUP(((AV27*$N$3)+AV27),1) -> 177.2 | K27: 0.1 | AA27: 114.1 | AB27: 123.3 | AC27: 135.7 | AE27: =AC27*1.06 -> 143.842 | AG27: =AE27*1.12 -> 161.10304 | AH27: =AG27*1.05 -> 169.15819 | AI27: =AH27*1.1 -> 186.07401 | AJ27: =AI27*1.05 -> 195.37771 | AK27: 195.4 | AL27: =AK27*1.06 -> 207.124 | AN27: =Rolô!I27*1.14 -> 159.486 | AO27: 177.042 | AP27: =AN27-AL27 -> -47.638 | AQ27: =AO27*1.07 -> 189.43494 | AU27: =AQ27*1.1 -> 208.37843 | AV27: =AU27+(AU27-(AU27*1.15)) -> 177.12167
B28: 22 | AB28: 123.3 | AC28: 135.7 | AE28: =AC28*1.06 -> 143.842 | AG28: =AE28*1.12 -> 161.10304 | AQ28: =AO28*1.07 -> 0 | AU28: =AQ28*1.1 -> 0 | AV28: =AU28+(AU28-(AU28*1.15)) -> 0
B29: 23 | C29: REQUINTE BK | E29: 0088 | H29: 2 | I29: =ROUNDUP(((AV29*$N$3)+AV29),1) -> 212.8 | K29: 0 | AA29: 115 | AB29: 124.2 | AC29: 136.7 | AE29: =AC29*1.06 -> 144.902 | AG29: =AE29*1.12 -> 162.29024 | AH29: =AG29*1.08 -> 175.27346 | AI29: =AH29*1.05 -> 184.03713 | AJ29: =AI29*1.05 -> 193.23899 | AK29: 193.3 | AL29: =AK29*1.1 -> 212.63 | AN29: =AL29 -> 212.63 | AO29: 212.63 | AP29: =AN29-AL29 -> 0 | AQ29: =AO29*1.07 -> 227.5141 | AU29: =AQ29*1.1 -> 250.26551 | AV29: =AU29+(AU29-(AU29*1.15)) -> 212.72568
B30: 24 | E30: 0101, 0102, 3042, 3044, 7517 ao 7523) | H30: 3 | I30: =ROUNDUP(((AV30*$N$3)+AV30),1) -> 172.5 | K30: 0 | AO30: 172.4 | AP30: 172.4 | AQ30: =AO30*1.07 -> 184.468 | AU30: =AQ30*1.1 -> 202.9148 | AV30: =AU30+(AU30-(AU30*1.15)) -> 172.47758
B31: 25 | E31: 0103 | H31: 2.5 | I31: =ROUNDUP(((AV31*$N$3)+AV31),1) -> 172.5 | K31: 0 | AA31: 115 | AB31: 124.2 | AC31: 136.7 | AE31: =AC31*1.06 -> 144.902 | AG31: =AE31*1.08 -> 156.49416 | AH31: =AG31 -> 156.49416 | AI31: =AH31*1.05 -> 164.31887 | AJ31: =AI31 -> 164.31887 | AK31: 164.4 | AL31: =AK31*1.06 -> 174.264 | AN31: =Rolô!I31*1.14 -> 155.268 | AO31: 172.368 | AP31: =AN31-AL31 -> -18.996 | AQ31: =AO31*1.07 -> 184.43376 | AU31: =AQ31*1.1 -> 202.87714 | AV31: =AU31+(AU31-(AU31*1.15)) -> 172.44557
B32: 26 | E32: 0105, 7511 ao 7516 | H32: 3 | I32: =ROUNDUP(((AV32*$N$3)+AV32),1) -> 174.4 | K32: 0 | AO32: 174.3 | AQ32: =AO32*1.07 -> 186.501 | AU32: =AQ32*1.1 -> 205.1511 | AV32: =AU32+(AU32-(AU32*1.15)) -> 174.37844
B33: 27 | E33: 0106 e 0107 | H33: 2.4 | I33: =ROUNDUP(((AV33*$N$3)+AV33),1) -> 174.4 | K33: 0 | AA33: 115 | AB33: 124.2 | AC33: 136.7 | AE33: =AC33*1.06 -> 144.902 | AG33: =AE33*1.08 -> 156.49416 | AH33: =AG33 -> 156.49416 | AI33: =AH33*1.05 -> 164.31887 | AJ33: =AI33 -> 164.31887 | AK33: 164.4 | AL33: =AK33*1.06 -> 174.264 | AN33: =AL33 -> 174.264 | AO33: 174.264 | AP33: =AN33-AL33 -> 0 | AQ33: =AO33*1.07 -> 186.46248 | AU33: =AQ33*1.1 -> 205.10873 | AV33: =AU33+(AU33-(AU33*1.15)) -> 174.34242
B34: 28 | E34: 3031 | H34: 2.4 | I34: =ROUNDUP(((AV34*$N$3)+AV34),1) -> 221.3 | K34: 0 | AA34: 146 | AB34: 157.7 | AC34: 173.5 | AE34: =AC34*1.06 -> 183.91 | AG34: =AE34*1.08 -> 198.6228 | AH34: =AG34 -> 198.6228 | AI34: =AH34*1.05 -> 208.55394 | AJ34: =AI34 -> 208.55394 | AK34: 208.6 | AL34: =AK34*1.06 -> 221.116 | AN34: =AL34 -> 221.116 | AO34: 221.116 | AP34: =AN34-AL34 -> 0 | AQ34: =AO34*1.07 -> 236.59412 | AU34: =AQ34*1.1 -> 260.25353 | AV34: =AU34+(AU34-(AU34*1.15)) -> 221.2155
B35: 29 | E35: 3040 | H35: 2.8 | I35: =ROUNDUP(((AV35*$N$3)+AV35),1) -> 218.5 | K35: 0 | AO35: 218.4 | AQ35: =AO35*1.07 -> 233.688 | AU35: =AQ35*1.1 -> 257.0568 | AV35: =AU35+(AU35-(AU35*1.15)) -> 218.49828
B36: 30 | E36: 3037, 3038 e 3039 | H36: 3 | I36: =ROUNDUP(((AV36*$N$3)+AV36),1) -> 218.5 | K36: 0 | AA36: 146 | AB36: 157.7 | AC36: 173.5 | AE36: =AC36*1.1 -> 190.85 | AG36: =AE36*1.12 -> 213.752 | AH36: =AG36*1.08 -> 230.85216 | AI36: 206 | AJ36: =AI36 -> 206 | AK36: 206 | AL36: =AK36*1.06 -> 218.36 | AN36: =AL36 -> 218.36 | AO36: 218.36 | AP36: =AN36-AL36 -> 0 | AQ36: =AO36*1.07 -> 233.6452 | AU36: =AQ36*1.1 -> 257.00972 | AV36: =AU36+(AU36-(AU36*1.15)) -> 218.45826
B37: 31 | E37: 3043 | H37: 2.5 | I37: =ROUNDUP(((AV37*$N$3)+AV37),1) -> 214.5 | K37: 0 | AN37: =Rolô!I39*1.14 -> 214.434 | AO37: 214.32 | AP37: =AN37-AL37 -> 214.434 | AQ37: =AO37*1.07 -> 229.3224 | AU37: =AQ37*1.1 -> 252.25464 | AV37: =AU37+(AU37-(AU37*1.15)) -> 214.41644
B38: 32 | E38: 3041 | H38: 2.5 | I38: =ROUNDUP(((AV38*$N$3)+AV38),1) -> 174.4 | K38: 0 | AC38: 136.7 | AE38: =AC38*1.06 -> 144.902 | AG38: =AE38*1.08 -> 156.49416 | AH38: =AG38*1.08 -> 169.01369 | AI38: 164.4 | AJ38: =AI38 -> 164.4 | AK38: 164.4 | AL38: =AK38*1.06 -> 174.264 | AN38: =AL38 -> 174.264 | AO38: 174.264 | AP38: =AN38-AL38 -> 0 | AQ38: =AO38*1.07 -> 186.46248 | AU38: =AQ38*1.1 -> 205.10873 | AV38: =AU38+(AU38-(AU38*1.15)) -> 174.34242
B39: 33 | AA39: 115 | AB39: 124.2 | AC39: 136.7 | AE39: =AC39*1.06 -> 144.902 | AG39: =AE39*1.08 -> 156.49416 | AH39: =AG39 -> 156.49416 | AI39: =AH39*1.05 -> 164.31887 | AJ39: =AI39 -> 164.31887 | AQ39: =AO39*1.07 -> 0 | AU39: =AQ39*1.1 -> 0 | AV39: =AU39+(AU39-(AU39*1.15)) -> 0
B40: 34 | E40: 7500 e 7501 | H40: 2.8 | I40: =ROUNDUP(((AV40*$N$3)+AV40),1) -> 212.8 | K40: 0 | AA40: 115 | AB40: 124.2 | AC40: 136.7 | AE40: =AC40*1.06 -> 144.902 | AG40: =AE40*1.12 -> 162.29024 | AH40: =AG40*1.08 -> 175.27346 | AI40: =AH40*1.05 -> 184.03713 | AJ40: =AI40*1.05 -> 193.23899 | AK40: 193.3 | AL40: =AK40*1.1 -> 212.63 | AN40: =AL40 -> 212.63 | AO40: 212.63 | AP40: =AN40-AL40 -> 0 | AQ40: =AO40*1.07 -> 227.5141 | AU40: =AQ40*1.1 -> 250.26551 | AV40: =AU40+(AU40-(AU40*1.15)) -> 212.72568
B41: 35 | E41: 0090, 0096, 7504 e 7508 | H41: 2.8 | I41: =ROUNDUP(((AV41*$N$3)+AV41),1) -> 181 | K41: 0 | AA41: 115 | AB41: 124.2 | AC41: 136.7 | AE41: =AC41*1.06 -> 144.902 | AG41: =AE41*1.08 -> 156.49416 | AH41: =AG41*1.08 -> 169.01369 | AI41: 164.4 | AJ41: =AI41 -> 164.4 | AK41: 164.4 | AL41: =AK41*1.1 -> 180.84 | AN41: =AL41 -> 180.84 | AO41: 180.84 | AP41: =AN41-AL41 -> 0 | AQ41: =AO41*1.07 -> 193.4988 | AU41: =AQ41*1.1 -> 212.84868 | AV41: =AU41+(AU41-(AU41*1.15)) -> 180.92138
B42: 36 | C42: OXFORD BLACKOUT | E42: 0410, 0411 e 0414 | H42: 3 | I42: =ROUNDUP(((AV42*$N$3)+AV42),1) -> 210.5 | K42: 0 | AA42: 151 | AB42: 163.1 | AC42: 179.5 | AE42: =AC42*1.06 -> 190.27 | AG42: =AE42 -> 190.27 | AH42: =AG42*1.05 -> 199.7835 | AI42: =AH42 -> 199.7835 | AJ42: =AI42 -> 199.7835 | AK42: 199.8 | AL42: =AK42*1.06 -> 211.788 | AN42: =Rolô!I42*1.14 -> 189.468 | AO42: 210.33 | AP42: =AN42-AL42 -> -22.32 | AQ42: =AO42*1.07 -> 225.0531 | AU42: =AQ42*1.1 -> 247.55841 | AV42: =AU42+(AU42-(AU42*1.15)) -> 210.42465
B43: 37 | C43: FLORENÇA | E43: 0356 | H43: 2 | I43: =ROUNDUP(((AV43*$N$3)+AV43),1) -> 161.5 | K43: 0 | AA43: 99.8 | AB43: 107.8 | AC43: 118.6 | AE43: =AC43*1.06 -> 125.716 | AG43: =AE43*1.08 -> 135.77328 | AH43: =AG43*1.08 -> 146.63514 | AI43: =AH43 -> 146.63514 | AJ43: =AI43 -> 146.63514 | AK43: 146.7 | AL43: =AK43*1.1 -> 161.37 | AN43: =AL43 -> 161.37 | AO43: 161.37 | AP43: =AN43-AL43 -> 0 | AQ43: =AO43*1.07 -> 172.6659 | AU43: =AQ43*1.1 -> 189.93249 | AV43: =AU43+(AU43-(AU43*1.15)) -> 161.44262
B44: 38 | C44: RUSTIC | E44: 0053 | H44: 2 | I44: =ROUNDUP(((AV44*$N$3)+AV44),1) -> 185.7 | K44: 0 | AA44: 123.9 | AB44: 133.9 | AC44: 147.3 | AE44: =AC44*1.06 -> 156.138 | AG44: =AE44 -> 156.138 | AH44: =AG44*1.08 -> 168.62904 | AI44: =AH44 -> 168.62904 | AJ44: =AI44 -> 168.62904 | AK44: 168.7 | AL44: =AK44*1.1 -> 185.57 | AN44: =AL44 -> 185.57 | AO44: 185.57 | AP44: =AN44-AL44 -> 0 | AQ44: =AO44*1.07 -> 198.5599 | AU44: =AQ44*1.1 -> 218.41589 | AV44: =AU44+(AU44-(AU44*1.15)) -> 185.65351
B45: 39 | C45: ELEGANCY | E45: 0162 | H45: 2 | I45: =ROUNDUP(((AV45*$N$3)+AV45),1) -> 144.8 | K45: 0 | AA45: 99.8 | AB45: 107.8 | AC45: 118.6 | AE45: =AC45*1.06 -> 125.716 | AG45: =AE45*1.08 -> 135.77328 | AH45: =AG45*1.08 -> 146.63514 | AI45: =AH45 -> 146.63514 | AJ45: =AI45 -> 146.63514 | AK45: 146.7 | AL45: =AK45*1.1 -> 161.37 | AN45: =Rolô!I45*1.14 -> 144.78 | AO45: 144.666 | AP45: =AN45-AL45 -> -16.59 | AQ45: =AO45*1.07 -> 154.79262 | AU45: =AQ45*1.1 -> 170.27188 | AV45: =AU45+(AU45-(AU45*1.15)) -> 144.7311
B46: 40 | E46: 0161 | H46: 3 | I46: =ROUNDUP(((AV46*$N$3)+AV46),1) -> 144.8 | K46: 0 | AC46: 118.6 | AE46: =AC46*1.06 -> 125.716 | AG46: =AE46*1.08 -> 135.77328 | AH46: =AG46*1.08 -> 146.63514 | AI46: =AH46 -> 146.63514 | AJ46: =AI46 -> 146.63514 | AK46: 146.7 | AL46: =AK46*1.1 -> 161.37 | AN46: =Rolô!I46*1.14 -> 144.78 | AO46: 144.666 | AP46: =AN46-AL46 -> -16.59 | AQ46: =AO46*1.07 -> 154.79262 | AU46: =AQ46*1.1 -> 170.27188 | AV46: =AU46+(AU46-(AU46*1.15)) -> 144.7311
B47: 41 | E47: 0126 | H47: 2.5 | I47: =ROUNDUP(((AV47*$N$3)+AV47),1) -> 133.3 | K47: 0 | AA47: 99.8 | AB47: 107.8 | AC47: 118.6 | AE47: =AC47*1.06 -> 125.716 | AG47: =AE47*1.08 -> 135.77328 | AH47: =AG47*1.08 -> 146.63514 | AI47: =AH47 -> 146.63514 | AJ47: =AI47 -> 146.63514 | AK47: 146.7 | AL47: =AK47*1.06 -> 155.502 | AN47: =Rolô!I47*1.14 -> 133.266 | AO47: 133.152 | AP47: =AN47-AL47 -> -22.236 | AQ47: =AO47*1.07 -> 142.47264 | AU47: =AQ47*1.1 -> 156.7199 | AV47: =AU47+(AU47-(AU47*1.15)) -> 133.21192
B48: 42 | E48: 0128 | H48: 2.5 | I48: =ROUNDUP(((AV48*$N$3)+AV48),1) -> 133.3 | K48: 0 | AC48: 118.6 | AE48: =AC48*1.06 -> 125.716 | AG48: =AE48*1.08 -> 135.77328 | AH48: =AG48*1.08 -> 146.63514 | AI48: =AH48 -> 146.63514 | AJ48: =AI48 -> 146.63514 | AK48: 146.7 | AL48: =AK48*1.06 -> 155.502 | AN48: =Rolô!I48*1.14 -> 133.266 | AO48: 133.152 | AP48: =AN48-AL48 -> -22.236 | AQ48: =AO48*1.07 -> 142.47264 | AU48: =AQ48*1.1 -> 156.7199 | AV48: =AU48+(AU48-(AU48*1.15)) -> 133.21192
B49: 43 | E49: 0170 e 0177 | H49: 3 | I49: =ROUNDUP(((AV49*$N$3)+AV49),1) -> 144.8 | K49: 0 | AU49: 170.31 | AV49: =AU49+(AU49-(AU49*1.15)) -> 144.7635
B50: 44 | E50: 0169, 0171 e 0178 | H50: 2.5 | I50: =ROUNDUP(((AV50*$N$3)+AV50),1) -> 144.8 | K50: 0 | AO50: 144.7 | AQ50: =AO50*1.07 -> 154.829 | AU50: =AQ50*1.1 -> 170.3119 | AV50: =AU50+(AU50-(AU50*1.15)) -> 144.76512
B51: 45 | C51: VENEZA | E51: 0060 | H51: 2.5 | I51: =ROUNDUP(((AV51*$N$3)+AV51),1) -> 172.3 | K51: 0 | AC51: 136.7 | AE51: =AC51*1.06 -> 144.902 | AG51: =AE51 -> 144.902 | AH51: =AG51*1.08 -> 156.49416 | AI51: =AH51 -> 156.49416 | AJ51: =AI51 -> 156.49416 | AK51: 156.5 | AL51: =AK51*1.1 -> 172.15 | AN51: =AL51 -> 172.15 | AO51: 172.15 | AP51: =AN51-AL51 -> 0 | AQ51: =AO51*1.07 -> 184.2005 | AU51: =AQ51*1.1 -> 202.62055 | AV51: =AU51+(AU51-(AU51*1.15)) -> 172.22747
B52: 46 | E52: 0076 e 0077 | H52: 2.5 | I52: =ROUNDUP(((AV52*$N$3)+AV52),1) -> 144 | K52: 0 | AA52: 115 | AB52: 124.2 | AC52: 136.7 | AE52: =AC52*1.06 -> 144.902 | AG52: =AE52 -> 144.902 | AH52: =AG52*1.08 -> 156.49416 | AI52: =AH52 -> 156.49416 | AJ52: =AI52 -> 156.49416 | AK52: 156.5 | AL52: =AK52*1.06 -> 165.89 | AN52: =Rolô!I51*1.14 -> 143.982 | AO52: 143.868 | AP52: =AN52-AL52 -> -21.908 | AQ52: =AO52*1.07 -> 153.93876 | AU52: =AQ52*1.1 -> 169.33264 | AV52: =AU52+(AU52-(AU52*1.15)) -> 143.93274
B53: 47 | C53: DUBAI | E53: 0221 e 0227 | H53: 2.6 | I53: =ROUNDUP(((AV53*$N$3)+AV53),1) -> 229.6 | K53: 0 | AA53: 128.4 | AB53: 138.7 | AC53: 152.6 | AE53: =AC53*1.06 -> 161.756 | AG53: =AE53*1.18 -> 190.87208 | AH53: =AG53*1.08 -> 206.14185 | AI53: =AH53*1.05 -> 216.44894 | AJ53: =AI53 -> 216.44894 | AK53: 216.5 | AL53: =AK53*1.06 -> 229.49 | AN53: =AL53 -> 229.49 | AO53: 229.49 | AP53: =AN53-AL53 -> 0 | AQ53: =AO53*1.07 -> 245.5543 | AU53: =AQ53*1.1 -> 270.10973 | AV53: =AU53+(AU53-(AU53*1.15)) -> 229.59327
B54: 48 | C54: MANHATTAN | E54: 0485 ao 0490 | H54: 2.8 | I54: =ROUNDUP(((AV54*$N$3)+AV54),1) -> 174.5 | K54: 0 | AA54: 0 | AB54: 124.3 | AC54: 136.8 | AE54: =AC54*1.06 -> 145.008 | AG54: =AE54*1.08 -> 156.60864 | AH54: =AG54 -> 156.60864 | AI54: =AH54*1.05 -> 164.43907 | AJ54: =AI54 -> 164.43907 | AK54: 164.5 | AL54: =AK54*1.06 -> 174.37 | AN54: =AL54 -> 174.37 | AO54: 174.37 | AP54: =AN54-AL54 -> 0 | AQ54: =AO54*1.07 -> 186.5759 | AU54: =AQ54*1.1 -> 205.23349 | AV54: =AU54+(AU54-(AU54*1.15)) -> 174.44847
B55: 49 | C55: SEVILHA | E55: 3354, 3355, 3356, 3357, 3358, 3359, 3360, 3361 | H55: 2.5 | I55: =ROUNDUP(((AV55*$N$3)+AV55),1) -> 144 | K55: 0 | AO55: 143.9 | AQ55: =AO55*1.07 -> 153.973 | AU55: =AQ55*1.1 -> 169.3703 | AV55: =AU55+(AU55-(AU55*1.15)) -> 143.96476
B56: 50 | C56: FINESSE BK | E56: 6500 ao 6808 | H56: 3 | I56: =ROUNDUP(((AV56*$N$3)+AV56),1) -> 218.6 | K56: 0 | AQ56: 233.7 | AU56: =AQ56*1.1 -> 257.07 | AV56: =AU56+(AU56-(AU56*1.15)) -> 218.5095
B57: 51 | C57: TRANCOSO | E57: 8800 ao 8804 - LANÇAMENTOS | H57: 3 | I57: =ROUNDUP(((AV57*$N$3)+AV57),1) -> 150.3 | K57: 0 | AU57: 176.8 | AV57: =AU57+(AU57-(AU57*1.15)) -> 150.28 | BI57: 147.3
B58: 52 | C58: CARAÍVA BK | E58: 8900 ao 8904 - LANÇAMENTOS | H58: 3 | I58: =ROUNDUP(((AV58*$N$3)+AV58),1) -> 208.2 | K58: 0 | AU58: 244.9 | AV58: =AU58+(AU58-(AU58*1.15)) -> 208.165 | BI58: 204.1
B59: 53 | C59: CAMBURI BK | E59: 9200 ao 9209 - LANÇAMENTOS | H59: 3 | I59: =ROUNDUP(((AV59*$N$3)+AV59),1) -> 208.2 | K59: 0 | AU59: 244.9 | AV59: =AU59+(AU59-(AU59*1.15)) -> 208.165 | BI59: 204.1
B60: 54 | C60: IPANEMA | E60: 7800 ao 7804 - LANÇAMENTOS | H60: 2.8 | I60: =ROUNDUP(((AV60*$N$3)+AV60),1) -> 191 | K60: 0 | AU60: 224.7 | AV60: =AU60+(AU60-(AU60*1.15)) -> 190.995 | BI60: 187.2
B61: 55 | C61: NORONHA | E61: 8600 ao 8606 - LANÇAMENTOS | H61: 2.8 | I61: =ROUNDUP(((AV61*$N$3)+AV61),1) -> 191 | K61: 0 | AU61: 224.7 | AV61: =AU61+(AU61-(AU61*1.15)) -> 190.995 | BI61: 187.2
B62: 56 | C62: LEBLON | E62: 8200 ao 8205 - LANÇAMENTOS | H62: 2.8 | I62: =ROUNDUP(((AV62*$N$3)+AV62),1) -> 191 | K62: 0 | AU62: 224.7 | AV62: =AU62+(AU62-(AU62*1.15)) -> 190.995 | BI62: 187.2
B63: 57
B64: 58 | C64: *** OS TECIDOS PROMOCIONAIS SÃO CONDICIONADOS A DISPONIBILIDADE NO ESTOQUE.
B65: 59 | C65: *** SOB ESTES VALORES PROMOCIONAIS NÃO INCIDIRÃO EVENTUAIS DESCONTOS. DESCONTO NÃO SE APLICA A ACESSÓRIOS SOLICITADOS COM A PEÇA.
B66: 60 | C66: ROMANA CLASSIC: VALOR DO M² DA CORTINA MAIS O ACRÉSCIMO DE 40%.
K67: Página 13 - | L67: =Rolô!$L$2 -> 2026 - v.03
B68: CORTINA ROMANA | N68: * DIGITE A PORCENTAGEM PARA MARKUP - ACESSÓRIOS
B69: PRODUTO EM CONFORMIDADE COM A NORMA ABNT NBR 16234: 2014 | N69: 0
B71: 61 | C71: ACESSÓRIOS
B72: 62 | C72: DESCRIÇÃO DO ACESSÓRIO | H72: COR | I72: UNIDADE | J72: VALOR À VISTA (R$) | L72: IPI | N72: * Legenda de Cores: | AA72: 42491 | AB72: 43026 | AC72: 43258 | AE72: 43862 | AF72: 43891 | AG72: 43952 | AH72: 44105 | AI72: 44256 | AJ72: 44287 | AK72: 44501
B73: 63 | C73: BASES: Chata, Redonda e Slim | AN73: 45658
B74: 64 | C74: SUPORTE AFASTADOR 4 X 6 | H74: B - M - P | I74: UN | J74: =ROUNDUP(((AN74*$N$69)+AN74),1) -> 6.4 | L74: 0.1 | N74: B = Branco | AA74: 2.4 | AB74: 2.6 | AC74: 2.9 | AE74: 3.43 | AG74: =AE74*1.1 -> 3.773 | AH74: =AG74*1.05 -> 3.96165 | AI74: =AH74*1.1 -> 4.357815 | AJ74: =AI74*1.15 -> 5.0114873 | AK74: 5.1 | AL74: =AK74*1.06 -> 5.406 | AM74: =AL74*1.07 -> 5.78442 | AN74: =AM74*1.1 -> 6.362862
B75: 65 | C75: SUPORTE AFASTADOR 6 X 9 | H75: B - M - P | I75: UN | J75: =ROUNDUP(((AN75*$N$69)+AN75),1) -> 8 | L75: 0.1 | N75: M = Marfim | AA75: 3 | AB75: 3.3 | AC75: 3.63 | AE75: =AC75*1.2 -> 4.356 | AG75: =AE75*1.1 -> 4.7916 | AH75: =AG75*1.05 -> 5.03118 | AI75: =AH75*1.1 -> 5.534298 | AJ75: =AI75*1.15 -> 6.3644427 | AK75: 6.4 | AL75: =AK75*1.06 -> 6.784 | AM75: =AL75*1.07 -> 7.25888 | AN75: =AM75*1.1 -> 7.984768
B76: 66 | C76: ACIONAMENTO MONOCONTROLE SEM MOLDURA | H76: B - M - P | I76: UN | J76: =ROUNDUP(((AN76*$N$69)+AN76),1) -> 68.5 | L76: 0 | N76: P = Preto | AA76: 30 | AB76: 32.4 | AC76: 35.7 | AE76: =AC76*1.1 -> 39.27 | AG76: =AE76*1.1 -> 43.197 | AH76: =AG76*1.05 -> 45.35685 | AI76: =AH76*1.1 -> 49.892535 | AJ76: =AI76*1.1 -> 54.881789 | AK76: 54.9 | AL76: =AK76*1.06 -> 58.194 | AM76: =AL76*1.07 -> 62.26758 | AN76: =AM76*1.1 -> 68.494338
B77: 67 | C77: ACIONAMENTO MONOCONTROLE COM MOLDURA | H77: B - M - P | I77: UN | J77: =ROUNDUP(((AN77*$N$69)+AN77),1) -> 102.7 | L77: 0 | N77: C = Cinza | AA77: 45 | AB77: 48.6 | AC77: 53.5 | AE77: =AC77*1.1 -> 58.85 | AG77: =AE77*1.1 -> 64.735 | AH77: =AG77*1.05 -> 67.97175 | AI77: =AH77*1.1 -> 74.768925 | AJ77: =AI77*1.1 -> 82.245818 | AK77: 82.3 | AL77: =AK77*1.06 -> 87.238 | AM77: =AL77*1.07 -> 93.34466 | AN77: =AM77*1.1 -> 102.67913
B78: 68 | C78: ACIONAMENTO EASY CONTROL SEM MOLDURA | H78: B - M - P | I78: UN | J78: =ROUNDUP(((AN78*$N$69)+AN78),1) -> 114.1 | L78: 0 | N78: MR = Marrom | AA78: 50 | AB78: 54 | AC78: 59.4 | AE78: =AC78*1.1 -> 65.34 | AG78: =AE78*1.1 -> 71.874 | AH78: =AG78*1.05 -> 75.4677 | AI78: =AH78*1.1 -> 83.01447 | AJ78: =AI78*1.1 -> 91.315917 | AK78: 91.4 | AL78: =AK78*1.06 -> 96.884 | AM78: =AL78*1.07 -> 103.66588 | AN78: =AM78*1.1 -> 114.03247
B79: 69 | C79: ACIONAMENTO EASY CONTROL COM MOLDURA | H79: B - M - P | I79: UN | J79: =ROUNDUP(((AN79*$N$69)+AN79),1) -> 148.3 | L79: 0 | N79: BZ = Bronze | AA79: 65 | AB79: 70.2 | AC79: 77.3 | AE79: =AC79*1.1 -> 85.03 | AG79: 93.4 | AH79: =AG79*1.05 -> 98.07 | AI79: =AH79*1.1 -> 107.877 | AJ79: 118.8 | AK79: 118.8 | AL79: =AK79*1.06 -> 125.928 | AM79: =AL79*1.07 -> 134.74296 | AN79: =AM79*1.1 -> 148.21726
B80: 70 | C80: ACIONAMENTO PLUS (Somente sem moldura) | H80: B - M - P | I80: UN | J80: =ROUNDUP(((AN80*$N$69)+AN80),1) -> 159.7 | L80: 0 | AA80: 70 | AB80: 75.6 | AC80: 83.2 | AE80: =AC80*1.1 -> 91.52 | AG80: =AE80*1.1 -> 100.672 | AH80: =AG80*1.05 -> 105.7056 | AI80: =AH80*1.1 -> 116.27616 | AJ80: =AI80*1.1 -> 127.90378 | AK80: 128 | AL80: =AK80*1.06 -> 135.68 | AM80: =AL80*1.07 -> 145.1776 | AN80: =AM80*1.1 -> 159.69536
B81: 71 | C81: CORRENTE METÁLICA - COBRADO 2x O TAMANHO DO COMANDO (TC) - (LANÇAMENTOS) DISPONÍVEL NOS ACIONAMENTOS MONOCONTROLE E EASY-CONTROL. | H81: Inox - Bronze - Ouro Velho - Preto Niquelado | I81: ML | J81: =ROUNDUP(((AN81*$N$69)+AN81),1) -> 17.4 | L81: 0 | AA81: 6.6 | AB81: 7.2 | AC81: 8 | AE81: 9.5 | AG81: =AE81*1.1 -> 10.45 | AH81: =AG81*1.05 -> 10.9725 | AI81: =AH81*1.1 -> 12.06975 | AJ81: =AI81*1.15 -> 13.880213 | AK81: 13.9 | AL81: =AK81*1.06 -> 14.734 | AM81: =AL81*1.07 -> 15.76538 | AN81: =AM81*1.1 -> 17.341918
B82: 72 | AJ82: =AI82*1.1 -> 0 | AM82: =AL82*1.07 -> 0 | AN82: =AM82*1.1 -> 0
B83: 73 | C83: BANDO CONJUGADO | H83: Ver linha 101 | I83: ML | J83: =ROUNDUP(((AN83*$N$69)+AN83),1) -> 106.6 | L83: 0 | AA83: 46.8 | AB83: 50.5 | AC83: 55.6 | AE83: =AC83*1.1 -> 61.16 | AG83: 67.23 | AH83: =AG83*1.05 -> 70.5915 | AI83: =AH83*1.1 -> 77.65065 | AJ83: 85.4 | AK83: 85.4 | AL83: =AK83*1.06 -> 90.524 | AM83: =AL83*1.07 -> 96.86068 | AN83: =AM83*1.1 -> 106.54675
B84: 74 | C84: BANDÔ FLAT | H84: Ver linha 101 | I84: ML | J84: =ROUNDUP(((AN84*$N$69)+AN84),1) -> 122.9 | L84: 0 | AG84: 77.5 | AH84: =AG84*1.05 -> 81.375 | AI84: =AH84*1.1 -> 89.5125 | AJ84: =AI84*1.1 -> 98.46375 | AK84: 98.5 | AL84: =AK84*1.06 -> 104.41 | AM84: =AL84*1.07 -> 111.7187 | AN84: =AM84*1.1 -> 122.89057
B85: 75 | C85: BANDÔ FLAT REVESTIDO | H85: Ver linha 101 | I85: ML | J85: =ROUNDUP(((AN85*$N$69)+AN85),1) -> 163.2 | L85: 0 | AG85: 102.9 | AH85: =AG85*1.05 -> 108.045 | AI85: =AH85*1.1 -> 118.8495 | AJ85: =AI85*1.1 -> 130.73445 | AK85: 130.8 | AL85: =AK85*1.06 -> 138.648 | AM85: =AL85*1.07 -> 148.35336 | AN85: =AM85*1.1 -> 163.1887
B86: 76 | C86: FITA DECORATIVA - 2 FITAS POR PEÇA - | H86: - | I86: UN | J86: =ROUNDUP(((AN86*$N$69)+AN86),1) -> 167 | L86: 0 | AA86: 70 | AB86: 75.6 | AC86: 83.2 | AE86: =AC86*1.1 -> 91.52 | AG86: =AE86*1.1 -> 100.672 | AH86: =AG86*1.05 -> 105.7056 | AI86: =AH86*1.1 -> 116.27616 | AJ86: =AI86*1.15 -> 133.71758 | AK86: 133.8 | AL86: =AK86*1.06 -> 141.828 | AM86: =AL86*1.07 -> 151.75596 | AN86: =AM86*1.1 -> 166.93156
B87: 77 | C87: FITA DECORATIVA - 3 FITAS POR PEÇA - | H87: - | I87: UN | J87: =ROUNDUP(((AN87*$N$69)+AN87),1) -> 226.5 | L87: 0 | AA87: 95 | AB87: 102.6 | AC87: 112.9 | AE87: =AC87*1.1 -> 124.19 | AG87: =AE87*1.1 -> 136.609 | AH87: =AG87*1.05 -> 143.43945 | AI87: =AH87*1.1 -> 157.7834 | AJ87: =AI87*1.15 -> 181.4509 | AK87: 181.5 | AL87: =AK87*1.06 -> 192.39 | AM87: =AL87*1.07 -> 205.8573 | AN87: =AM87*1.1 -> 226.44303
B88: 78 | C88: O VALOR DO ACESSÓRIO SOLICITADO A PARTE É SOB CONSULTA. O VALOR QUE CONSTA NA TABELA É PARA ACESSÓRIO SOLICITADO COM O PRODUTO MONTADO.
B89: 79
B90: 80 | C90: INFORMAÇÕES TÉCNICAS
B91: 81 | C91: - | D91: MONOCONTROLE | F91: PLUS | H91: EASY CONTROL
B92: 82 | C92: LARG. MÁX | D92: 2,00M | F92: 2,50M | H92: 3,00M
B93: 83 | C93: ALT. MÁX. | D93: 3,50M | F93: 3,50M | H93: 3,50M
B94: 84 | C94: M² MÁX. | D94: 5,00M² | F94: 5,00M² | H94: 6,00M²
B95: 85 | C95: LARG. MÍN. | D95: 0,30M | F95: 0,30M | H95: 0,30M
B96: 86 | C96: ALT. MÍN. | D96: 0,40M | F96: 0,40M | H96: 0,40M
B97: 87 | C97: TABELA DE GOMOS
B98: 88 | C98: ALTURA | D98: 60CM ATÉ 1,10M | F98: 1,11CM ATÉ 1,80M | H98: 1,81CM ATÉ 2,50M | J98: 2,51CM ATÉ 3,20M
B99: 89 | C99: QTD. GOMOS | D99: 3 GOMOS / 2 HASTES | F99: 5 GOMOS / 4 HASTES | H99: 7 GOMOS / 6 HASTES | J99: 9 GOMOS / 8 HASTES
B100: 90 | C100: O TECIDO É UM OBJETO DE SUPERFÍCIE MALEÁVEL QUE APRESENTA PEQUENAS ONDULAÇÕES EM SUA EXTENSÃO. COM A INCIDÊNCIA DE LUZ SOBRE O TECIDO, PODE OCORRER EFEITOS DE SOMBRA EVIDENCIANDO AS ONDULAÇÕES CONFORME ORIGEM DA ILUMINAÇÃO. ESTE EFEITO É UMA CARACTERÍSTICA NATURAL DO PRODUTO E NÃO ESTARÁ COBERTO PELA GARANTIA.
B101: 91
B102: 92
B103: 93 | C103: INFORMAÇÕES GERAIS
...

Sheet Painel
AF1: #NAME?
K2: Página 14 - | L2: =Rolô!$L$2 -> 2026 - v.03 | N2: * DIGITE A PORCENTAGEM PARA MARKUP
B3: CORTINA PAINEL EUROPA | N3: 0
B7: ITEM | C7: COLEÇÃO | E7: COR | H7: VALOR À VISTA (R$)/M² SEM HASTE | J7: VALOR À VISTA (R$)/M² COM HASTE | L7: IPI | AA7: MAI/2016 - SEM HASTE | AB7: MAI/2016 - COM HASTE | AC7: OUT/2017 - SEM HASTE | AD7: OUT/2017 - COM HASTE | AE7: JUN/2018 - SEM HASTE | AF7: JUN/2018 - COM HASTE | AG7: FEV/2020 - SEM HASTE | AH7: FEV/2020 - COM HASTE | AJ7: MAI/2020 - SEM HASTE | AK7: MAI/2020 - COM HASTE | AP7: OUT/2020 - SEM HASTE | AQ7: OUT/2020 - COM HASTE | AR7: MAR/2021 - SEM HASTE | AS7: MAR/2021 - COM HASTE | AU7: JUL/2021 - SEM HASTE | AV7: JUL/2021 - COM HASTE | AW7: JUL/2021 - SEM HASTE | AY7: JUL/2021 - COM HASTE
BD8: 45658 | BF8: 45717
B9: 1 | C9: SCREEN 1% | E9: 0001, 0005, 0006, 1010, 1030 e 1031 | H9: =ROUNDUP(((BF9*$N$3)+BF9),1) -> 157.5 | J9: =ROUNDUP(((BG9*$N$3)+BG9),1) -> 188.9 | L9: 0 | AA9: 103.2 | AB9: 123.8 | AC9: 111.5 | AD9: 133.8 | AE9: =AC9*1.1 -> 122.65 | AF9: =AD9*1.1 -> 147.18 | AG9: =AE9*1.1 -> 134.915 | AH9: =AF9*1.1 -> 161.898 | AJ9: =AG9*1.1 -> 148.4065 | AK9: =AH9*1.1 -> 178.0878 | AP9: =AJ9 -> 148.4065 | AQ9: =AK9 -> 178.0878 | AR9: =AP9 -> 148.4065 | AS9: =AQ9 -> 178.0878 | AU9: =AR9 -> 148.4065 | AV9: =AS9 -> 178.0878 | AW9: 148.5 | AX9: =AW9*1.06 -> 157.41 | AY9: 178.1 | AZ9: =AY9*1.06 -> 188.786 | BB9: =AX9*1.07 -> 168.4287 | BC9: =AZ9*1.07 -> 202.00102 | BD9: =BB9*1.1 -> 185.27157 | BE9: =BC9*1.1 -> 222.20112 | BF9: =BD9+(BD9-(BD9*1.15)) -> 157.48083 | BG9: =BE9+(BE9-(BE9*1.15)) -> 188.87095
B10: 2 | C10: SCREEN FIBER GLASS 1% | E10: 6001 | H10: =ROUNDUP(((BF10*$N$3)+BF10),1) -> 268.7 | J10: =ROUNDUP(((BG10*$N$3)+BG10),1) -> 322.5 | L10: 0 | AA10: 148.6 | AB10: 178.4 | AC10: 160.5 | AD10: 192.7 | AE10: =AC10*1.1 -> 176.55 | AF10: =AD10*1.1 -> 211.97 | AG10: =AE10*1.1 -> 194.205 | AH10: =AF10*1.1 -> 233.167 | AJ10: =AG10*1.15 -> 223.33575 | AK10: =AH10*1.15 -> 268.14205 | AP10: =AJ10*1.08 -> 241.20261 | AQ10: =AK10*1.08 -> 289.59341 | AR10: =AP10*1.05 -> 253.26274 | AS10: =AQ10*1.05 -> 304.07308 | AU10: =AR10 -> 253.26274 | AV10: =AS10 -> 304.07308 | AW10: 253.3 | AX10: =AW10*1.06 -> 268.498 | AY10: 304.1 | AZ10: =AY10*1.06 -> 322.346 | BB10: =AX10*1.07 -> 287.29286 | BC10: =AZ10*1.07 -> 344.91022 | BD10: =BB10*1.1 -> 316.02215 | BE10: =BC10*1.1 -> 379.40124 | BF10: =BD10+(BD10-(BD10*1.15)) -> 268.61882 | BG10: =BE10+(BE10-(BE10*1.15)) -> 322.49106
B11: 3 | C11: SCREEN 3% | E11: 3001, 3002, 3008, 3017, 3060 e 3061 | H11: =ROUNDUP(((BF11*$N$3)+BF11),1) -> 145.9 | J11: =ROUNDUP(((BG11*$N$3)+BG11),1) -> 175.2 | L11: 0 | AA11: 94.5 | AB11: 113.6 | AC11: 102.1 | AD11: 122.7 | AE11: =AC11*1.1 -> 112.31 | AF11: =AD11*1.1 -> 134.97 | AG11: =AE11*1.1 -> 123.541 | AH11: =AF11*1.1 -> 148.467 | AJ11: =AG11*1.08 -> 133.42428 | AK11: =AH11*1.08 -> 160.34436 | AP11: =AJ11 -> 133.42428 | AQ11: =AK11 -> 160.34436 | AR11: =AP11 -> 133.42428 | AS11: =AQ11 -> 160.34436 | AU11: =AR11*1.03 -> 137.42701 | AV11: =AS11*1.03 -> 165.15469 | AW11: 137.5 | AX11: =AW11*1.06 -> 145.75 | AY11: 165.2 | AZ11: =AY11*1.06 -> 175.112 | BB11: =AX11*1.07 -> 155.9525 | BC11: =AZ11*1.07 -> 187.36984 | BD11: =BB11*1.1 -> 171.54775 | BE11: =BC11*1.1 -> 206.10682 | BF11: =BD11+(BD11-(BD11*1.15)) -> 145.81559 | BG11: =BE11+(BE11-(BE11*1.15)) -> 175.1908
B12: 4 | E12: 3009 ao 3011, 3018 e 3019 | H12: =ROUNDUP(((BF12*$N$3)+BF12),1) -> 156.2 | J12: =ROUNDUP(((BG12*$N$3)+BG12),1) -> 187.5 | L12: 0 | AA12: 94.5 | AB12: 113.6 | AC12: 102.1 | AD12: 122.7 | AE12: =AC12*1.1 -> 112.31 | AF12: =AD12*1.1 -> 134.97 | AG12: =AE12*1.1 -> 123.541 | AH12: =AF12*1.1 -> 148.467 | AJ12: =AG12*1.08 -> 133.42428 | AK12: =AH12*1.08 -> 160.34436 | AP12: =AJ12 -> 133.42428 | AQ12: =AK12 -> 160.34436 | AR12: =AP12*1.05 -> 140.09549 | AS12: =AQ12*1.05 -> 168.36158 | AU12: =AR12*1.05 -> 147.10027 | AV12: =AS12*1.05 -> 176.77966 | AW12: 147.2 | AX12: =AW12*1.06 -> 156.032 | AY12: 176.8 | AZ12: =AY12*1.06 -> 187.408 | BB12: =AX12*1.07 -> 166.95424 | BC12: =AZ12*1.07 -> 200.52656 | BD12: =BB12*1.1 -> 183.64966 | BE12: =BC12*1.1 -> 220.57922 | BF12: =BD12+(BD12-(BD12*1.15)) -> 156.10221 | BG12: =BE12+(BE12-(BE12*1.15)) -> 187.49233
B13: 5 | E13: 3012 e 3013 | H13: =ROUNDUP(((BF13*$N$3)+BF13),1) -> 148.6 | J13: =ROUNDUP(((BG13*$N$3)+BG13),1) -> 178.6 | L13: 0 | AU13: 140.1 | AV13: 168.36 | AW13: 140.1 | AX13: =AW13*1.06 -> 148.506 | AY13: 168.4 | AZ13: =AY13*1.06 -> 178.504 | BB13: =AX13*1.07 -> 158.90142 | BC13: =AZ13*1.07 -> 190.99928 | BD13: =BB13*1.1 -> 174.79156 | BE13: =BC13*1.1 -> 210.09921 | BF13: =BD13+(BD13-(BD13*1.15)) -> 148.57283 | BG13: =BE13+(BE13-(BE13*1.15)) -> 178.58433
B14: 6 | E14: 3014, 3015 | H14: =ROUNDUP(((BF14*$N$3)+BF14),1) -> 163 | J14: =ROUNDUP(((BG14*$N$3)+BG14),1) -> 195.9 | L14: 0 | AG14: 123.54 | AH14: 148.47 | AJ14: =AG14*1.15 -> 142.071 | AK14: =AH14*1.15 -> 170.7405 | AP14: =AJ14 -> 142.071 | AQ14: =AK14 -> 170.7405 | AR14: =AP14*1.05 -> 149.17455 | AS14: =AQ14*1.05 -> 179.27752 | AU14: =AR14*1.03 -> 153.64979 | AV14: =AS14*1.03 -> 184.65585 | AW14: 153.7 | AX14: =AW14*1.06 -> 162.922 | AY14: 184.7 | AZ14: =AY14*1.06 -> 195.782 | BB14: =AX14*1.07 -> 174.32654 | BC14: =AZ14*1.07 -> 209.48674 | BD14: =BB14*1.1 -> 191.75919 | BE14: =BC14*1.1 -> 230.43541 | BF14: =BD14+(BD14-(BD14*1.15)) -> 162.99531 | BG14: =BE14+(BE14-(BE14*1.15)) -> 195.8701
B15: 7 | C15: SCREEN FIBER GLASS 3% | E15: 6101 | H15: =ROUNDUP(((BF15*$N$3)+BF15),1) -> 246.7 | J15: =ROUNDUP(((BG15*$N$3)+BG15),1) -> 295.9 | L15: 0 | AA15: 136.4 | AB15: 163.7 | AC15: 147.4 | AD15: 176.8 | AE15: =AC15*1.1 -> 162.14 | AF15: =AD15*1.1 -> 194.48 | AG15: =AE15*1.1 -> 178.354 | AH15: =AF15*1.1 -> 213.928 | AJ15: =AG15*1.15 -> 205.1071 | AK15: =AH15*1.15 -> 246.0172 | AP15: =AJ15*1.08 -> 221.51567 | AQ15: =AK15*1.08 -> 265.69858 | AR15: =AP15*1.05 -> 232.59145 | AS15: =AQ15*1.05 -> 278.9835 | AU15: =AR15 -> 232.59145 | AV15: =AS15 -> 278.9835 | AW15: 232.6 | AX15: =AW15*1.06 -> 246.556 | AY15: 279 | AZ15: =AY15*1.06 -> 295.74 | BB15: =AX15*1.07 -> 263.81492 | BC15: =AZ15*1.07 -> 316.4418 | BD15: =BB15*1.1 -> 290.19641 | BE15: =BC15*1.1 -> 348.08598 | BF15: =BD15+(BD15-(BD15*1.15)) -> 246.66695 | BG15: =BE15+(BE15-(BE15*1.15)) -> 295.87308
B16: 8 | C16: SCREEN 5% | E16: 3070 ao 3076, 3078 e 3079, 3096,3097 e 3098 | H16: =ROUNDUP(((BF16*$N$3)+BF16),1) -> 136.7 | J16: =ROUNDUP(((BG16*$N$3)+BG16),1) -> 164.1 | L16: 0 | AA16: 88.6 | AB16: 106.3 | AC16: 95.7 | AD16: 114.9 | AE16: =AC16*1.1 -> 105.27 | AF16: =AD16*1.1 -> 126.39 | AG16: =AE16*1.1 -> 115.797 | AH16: =AF16*1.1 -> 139.029 | AJ16: =AG16*1.08 -> 125.06076 | AK16: =AH16*1.08 -> 150.15132 | AP16: =AJ16 -> 125.06076 | AQ16: =AK16 -> 150.15132 | AR16: =AP16 -> 125.06076 | AS16: =AQ16 -> 150.15132 | AU16: =AR16*1.03 -> 128.81258 | AV16: =AS16*1.03 -> 154.65586 | AW16: 128.9 | AX16: =AW16*1.06 -> 136.634 | AY16: 154.7 | AZ16: =AY16*1.06 -> 163.982 | BB16: =AX16*1.07 -> 146.19838 | BC16: =AZ16*1.07 -> 175.46074 | BD16: =BB16*1.1 -> 160.81822 | BE16: =BC16*1.1 -> 193.00681 | BF16: =BD16+(BD16-(BD16*1.15)) -> 136.69549 | BG16: =BE16+(BE16-(BE16*1.15)) -> 164.05579
B17: 9 | C17: SCREEN FIBER GLASS 5% | E17: 6202 | H17: =ROUNDUP(((BF17*$N$3)+BF17),1) -> 230.9 | J17: =ROUNDUP(((BG17*$N$3)+BG17),1) -> 277 | L17: 0 | AA17: 127.6 | AB17: 153.2 | AC17: 137.9 | AD17: 165.5 | AE17: =AC17*1.1 -> 151.69 | AF17: =AD17*1.1 -> 182.05 | AG17: =AE17*1.1 -> 166.859 | AH17: =AF17*1.1 -> 200.255 | AJ17: =AG17*1.15 -> 191.88785 | AK17: =AH17*1.15 -> 230.29325 | AP17: =AJ17*1.08 -> 207.23888 | AQ17: =AK17*1.08 -> 248.71671 | AR17: =AP17*1.05 -> 217.60082 | AS17: =AQ17*1.05 -> 261.15255 | AU17: =AR17 -> 217.60082 | AV17: =AS17 -> 261.15255 | AW17: 217.7 | AX17: =AW17*1.06 -> 230.762 | AY17: 261.2 | AZ17: =AY17*1.06 -> 276.872 | BB17: =AX17*1.07 -> 246.91534 | BC17: =AZ17*1.07 -> 296.25304 | BD17: =BB17*1.1 -> 271.60687 | BE17: =BC17*1.1 -> 325.87834 | BF17: =BD17+(BD17-(BD17*1.15)) -> 230.86584 | BG17: =BE17+(BE17-(BE17*1.15)) -> 276.99659
B18: 10 | C18: SCREEN CRISTAL 5% | E18: 3100 | H18: =ROUNDUP(((BF18*$N$3)+BF18),1) -> 168.3 | J18: =ROUNDUP(((BG18*$N$3)+BG18),1) -> 202 | L18: 0 | AA18: 103.2 | AB18: 123.8 | AC18: 111.5 | AD18: 133.8 | AE18: =AC18*1.1 -> 122.65 | AF18: =AD18*1.1 -> 147.18 | AG18: =AE18*1.1 -> 134.915 | AH18: =AF18*1.1 -> 161.898 | AJ18: =AG18*1.12 -> 151.1048 | AK18: =AH18*1.12 -> 181.32576 | AP18: =AJ18 -> 151.1048 | AQ18: =AK18 -> 181.32576 | AR18: =AP18*1.05 -> 158.66004 | AS18: =AQ18*1.05 -> 190.39205 | AU18: =AR18 -> 158.66004 | AV18: =AS18 -> 190.39205 | AW18: 158.7 | AX18: =AW18*1.06 -> 168.222 | AY18: 190.4 | AZ18: =AY18*1.06 -> 201.824 | BB18: =AX18*1.07 -> 179.99754 | BC18: =AZ18*1.07 -> 215.95168 | BD18: =BB18*1.1 -> 197.99729 | BE18: =BC18*1.1 -> 237.54685 | BF18: =BD18+(BD18-(BD18*1.15)) -> 168.2977 | BG18: =BE18+(BE18-(BE18*1.15)) -> 201.91482
B19: 11 | C19: SCREEN RÚSTICO 3% | E19: 3150, 3151 e 3153 | H19: =ROUNDUP(((BF19*$N$3)+BF19),1) -> 172.9 | J19: =ROUNDUP(((BG19*$N$3)+BG19),1) -> 207.4 | L19: 0 | AA19: 103.2 | AB19: 123.8 | AC19: 111.5 | AD19: 133.8 | AE19: =AC19*1.1 -> 122.65 | AF19: =AD19*1.1 -> 147.18 | AG19: =AE19*1.1 -> 134.915 | AH19: =AF19*1.1 -> 161.898 | AJ19: =AG19*1.15 -> 155.15225 | AK19: =AH19*1.15 -> 186.1827 | AP19: =AJ19 -> 155.15225 | AQ19: =AK19 -> 186.1827 | AR19: =AP19*1.05 -> 162.90986 | AS19: =AQ19*1.05 -> 195.49184 | AU19: =AR19 -> 162.90986 | AV19: =AS19 -> 195.49184 | AW19: 163 | AX19: =AW19*1.06 -> 172.78 | AY19: 195.5 | AZ19: =AY19*1.06 -> 207.23 | BB19: =AX19*1.07 -> 184.8746 | BC19: =AZ19*1.07 -> 221.7361 | BD19: =BB19*1.1 -> 203.36206 | BE19: =BC19*1.1 -> 243.90971 | BF19: =BD19+(BD19-(BD19*1.15)) -> 172.85775 | BG19: =BE19+(BE19-(BE19*1.15)) -> 207.32325
B20: 12 | C20: SCREEN RÚSTICO 5% | E20: 3159, 3160, 3161, 3162 e 3163 | H20: =ROUNDUP(((BF20*$N$3)+BF20),1) -> 170.5 | J20: =ROUNDUP(((BG20*$N$3)+BG20),1) -> 204.5 | L20: 0 | AG20: 134.92 | AH20: 161.9 | AJ20: =AG20*1.08 -> 145.7136 | AK20: =AH20*1.08 -> 174.852 | AP20: =AJ20*1.05 -> 152.99928 | AQ20: =AK20*1.05 -> 183.5946 | AR20: =AP20*1.05 -> 160.64924 | AS20: =AQ20*1.05 -> 192.77433 | AU20: =AR20 -> 160.64924 | AV20: =AS20 -> 192.77433 | AW20: 160.7 | AX20: =AW20*1.06 -> 170.342 | AY20: 192.8 | AZ20: =AY20*1.06 -> 204.368 | BB20: =AX20*1.07 -> 182.26594 | BC20: =AZ20*1.07 -> 218.67376 | BD20: =BB20*1.1 -> 200.49253 | BE20: =BC20*1.1 -> 240.54114 | BF20: =BD20+(BD20-(BD20*1.15)) -> 170.41865 | BG20: =BE20+(BE20-(BE20*1.15)) -> 204.45997
B21: 13 | E21: 3155 e 3156 | H21: =ROUNDUP(((BF21*$N$3)+BF21),1) -> 190.2 | J21: =ROUNDUP(((BG21*$N$3)+BG21),1) -> 228.2 | L21: 0 | AA21: 103.2 | AB21: 123.8 | AC21: 111.5 | AD21: 133.8 | AE21: =AC21*1.1 -> 122.65 | AF21: =AD21*1.1 -> 147.18 | AG21: =AE21*1.1 -> 134.915 | AH21: =AF21*1.1 -> 161.898 | AJ21: =AG21*1.15 -> 155.15225 | AK21: =AH21*1.15 -> 186.1827 | AP21: =AJ21*1.05 -> 162.90986 | AQ21: =AK21*1.05 -> 195.49184 | AR21: =AP21*1.1 -> 179.20085 | AS21: =AQ21*1.1 -> 215.04102 | AU21: =AR21 -> 179.20085 | AV21: =AS21 -> 215.04102 | AW21: 179.3 | AX21: =AW21*1.06 -> 190.058 | AY21: 215.1 | AZ21: =AY21*1.06 -> 228.006 | BB21: =AX21*1.07 -> 203.36206 | BC21: =AZ21*1.07 -> 243.96642 | BD21: =BB21*1.1 -> 223.69827 | BE21: =BC21*1.1 -> 268.36306 | BF21: =BD21+(BD21-(BD21*1.15)) -> 190.14353 | BG21: =BE21+(BE21-(BE21*1.15)) -> 228.1086
B22: 14 | C22: SCREEN REFLEX | E22: 3121, 3122 e 3123 | H22: =ROUNDUP(((BF22*$N$3)+BF22),1) -> 179.8 | J22: =ROUNDUP(((BG22*$N$3)+BG22),1) -> 200.7 | L22: 0 | AA22: 105.2 | AB22: 117.5 | AC22: 113.7 | AD22: 126.9 | AE22: =AC22*1.1 -> 125.07 | AF22: =AD22*1.1 -> 139.59 | AG22: =AE22*1.1 -> 137.577 | AH22: =AF22*1.1 -> 153.549 | AJ22: =AG22*1.12 -> 154.08624 | AK22: =AH22*1.12 -> 171.97488 | AP22: =AJ22 -> 154.08624 | AQ22: =AK22 -> 171.97488 | AR22: =AP22*1.1 -> 169.49486 | AS22: =AQ22*1.1 -> 189.17237 | AU22: =AR22 -> 169.49486 | AV22: =AS22 -> 189.17237 | AW22: 169.5 | AX22: =AW22*1.06 -> 179.67 | AY22: 189.2 | AZ22: =AY22*1.06 -> 200.552 | BB22: =AX22*1.07 -> 192.2469 | BC22: =AZ22*1.07 -> 214.59064 | BD22: =BB22*1.1 -> 211.47159 | BE22: =BC22*1.1 -> 236.0497 | BF22: =BD22+(BD22-(BD22*1.15)) -> 179.75085 | BG22: =BE22+(BE22-(BE22*1.15)) -> 200.64225
B23: 15 | C23: SCREEN BK | E23: 3200, 3201 e 3203 | H23: indisponível | J23: =ROUNDUP(((BG23*$N$3)+BG23),1) -> 206.5 | L23: 0 | AZ23: 206.4 | BB23: =AX23*1.07 -> 0 | BC23: =AZ23*1.07 -> 220.848 | BD23: =BB23*1.1 -> 0 | BE23: =BC23*1.1 -> 242.9328 | BF23: =BD23+(BD23-(BD23*1.15)) -> 0 | BG23: =BE23+(BE23-(BE23*1.15)) -> 206.49288
B24: 16 | C24: IBIZA | E24: 3350, 3351 e 3353 | H24: =ROUNDUP(((BF24*$N$3)+BF24),1) -> 175 | J24: =ROUNDUP(((BG24*$N$3)+BG24),1) -> 201.5 | L24: 0 | AA24: 92.4 | AB24: 106.3 | AC24: 99.8 | AD24: 114.9 | AE24: =AC24*1.1 -> 109.78 | AF24: =AD24*1.1 -> 126.39 | AG24: =AE24*1.1 -> 120.758 | AH24: =AF24*1.1 -> 139.029 | AJ24: =AG24*1.15 -> 138.8717 | AK24: =AH24*1.15 -> 159.88335 | AP24: =AJ24*1.08 -> 149.98144 | AQ24: =AK24*1.08 -> 172.67402 | AR24: =AP24*1.1 -> 164.97958 | AS24: =AQ24*1.1 -> 189.94142 | AU24: =AR24 -> 164.97958 | AV24: =AS24 -> 189.94142 | AW24: 165 | AX24: =AW24*1.06 -> 174.9 | AY24: 190 | AZ24: =AY24*1.06 -> 201.4 | BB24: =AX24*1.07 -> 187.143 | BC24: =AZ24*1.07 -> 215.498 | BD24: =BB24*1.1 -> 205.8573 | BE24: =BC24*1.1 -> 237.0478 | BF24: =BD24+(BD24-(BD24*1.15)) -> 174.97871 | BG24: =BE24+(BE24-(BE24*1.15)) -> 201.49063
B25: 17 | C25: BK PINPOINT | E25: 0180 ao 0183 e 0186 ao 0190 | H25: indisponível | J25: =ROUNDUP(((BG25*$N$3)+BG25),1) -> 177 | L25: 0.1 | AA25: 0 | AB25: 93.9 | AC25: 0 | AD25: 101.5 | AE25: =AC25*1.1 -> 0 | AF25: =AD25*1.1 -> 111.65 | AG25: =AE25*1.1 -> 0 | AH25: =AF25*1.1 -> 122.815 | AJ25: =AG25*1.12 -> 0 | AK25: =AH25*1.12 -> 137.5528 | AP25: =AJ25 -> 0 | AQ25: =AK25*1.05 -> 144.43044 | AR25: =AP25*1.05 -> 0 | AS25: =AQ25*1.1 -> 158.87348 | AU25: =AR25 -> 0 | AV25: =AS25*1.05 -> 166.81716 | AW25: 0 | AX25: =AW25*1.06 -> 0 | AY25: 166.9 | AZ25: =AY25*1.06 -> 176.914 | BB25: =AX25*1.07 -> 0 | BC25: =AZ25*1.07 -> 189.29798 | BD25: =BB25*1.1 -> 0 | BE25: =BC25*1.1 -> 208.22778 | BF25: =BD25+(BD25-(BD25*1.15)) -> 0 | BG25: =BE25+(BE25-(BE25*1.15)) -> 176.99361
B26: 18 | H26: indisponível | L26: 0.1 | AD26: 101.5 | AE26: =AC26*1.1 -> 0 | AF26: =AD26*1.1 -> 111.65 | AG26: =AE26*1.1 -> 0 | AH26: =AF26*1.1 -> 122.815 | AJ26: =AG26*1.12 -> 0 | AK26: =AH26*1.12 -> 137.5528 | AP26: =AJ26 -> 0 | AQ26: =AK26*1.05 -> 144.43044 | AR26: =AP26*1.05 -> 0 | AS26: =AQ26*1.1 -> 158.87348 | AU26: =AR26 -> 0 | AV26: =AS26*1.05 -> 166.81716 | AW26: 0 | AX26: =AW26*1.06 -> 0 | AZ26: =AY26*1.06 -> 0 | BB26: =AX26*1.07 -> 0 | BC26: =AZ26*1.07 -> 0 | BD26: =BB26*1.1 -> 0 | BE26: =BC26*1.1 -> 0 | BF26: =BD26+(BD26-(BD26*1.15)) -> 0 | BG26: =BE26+(BE26-(BE26*1.15)) -> 0
B27: 19 | C27: REQUINTE BLACKOUT | E27: 0088 | H27: indisponível | J27: =ROUNDUP(((BG27*$N$3)+BG27),1) -> 178.8 | L27: 0 | AA27: 0 | AB27: 93.1 | AC27: 0 | AD27: 100.6 | AE27: =AC27*1.1 -> 0 | AF27: =AD27*1.1 -> 110.66 | AG27: =AE27*1.1 -> 0 | AH27: =AF27*1.1 -> 121.726 | AJ27: =AG27*1.12 -> 0 | AK27: =AH27*1.12 -> 136.33312 | AP27: =AJ27 -> 0 | AQ27: =AK27*1.08 -> 147.23977 | AR27: =AP27*1.05 -> 0 | AS27: =AQ27*1.05 -> 154.60176 | AU27: =AR27 -> 0 | AV27: =AS27*1.05 -> 162.33185 | AW27: 0 | AX27: =AW27*1.06 -> 0 | AY27: 162.4 | AZ27: =AY27*1.1 -> 178.64 | BB27: =AX27*1.07 -> 0 | BC27: =AZ27*1.07 -> 191.1448 | BD27: =BB27*1.1 -> 0 | BE27: =BC27*1.1 -> 210.25928 | BF27: =BD27+(BD27-(BD27*1.15)) -> 0 | BG27: =BE27+(BE27-(BE27*1.15)) -> 178.72039
B28: 20 | E28: 0090 e 0096 | H28: indisponível | J28: =ROUNDUP(((BG28*$N$3)+BG28),1) -> 165.5 | L28: 0 | AG28: =AE28*1.1 -> 0 | AH28: 121.73 | AJ28: =AG28*1.08 -> 0 | AK28: =AH28*1.08 -> 131.4684 | AP28: =AJ28 -> 0 | AQ28: =AK28*1.08 -> 141.98587 | AR28: =AP28*1.05 -> 0 | AS28: =AQ28*1.05 -> 149.08517 | AU28: =AR28 -> 0 | AV28: 150.3 | AW28: 0 | AX28: =AW28*1.06 -> 0 | AY28: 150.3 | AZ28: =AY28*1.1 -> 165.33 | BB28: =AX28*1.07 -> 0 | BC28: =AZ28*1.07 -> 176.9031 | BD28: =BB28*1.1 -> 0 | BE28: =BC28*1.1 -> 194.59341 | BF28: =BD28+(BD28-(BD28*1.15)) -> 0 | BG28: =BE28+(BE28-(BE28*1.15)) -> 165.4044
B29: 21 | E29: 0101 ao 0103, 7517 ao 7523 | H29: indisponível | J29: =ROUNDUP(((BG29*$N$3)+BG29),1) -> 159.4 | L29: 0 | AA29: 0 | AB29: 96.7 | AC29: 0 | AD29: 104.5 | AE29: =AC29*1.1 -> 0 | AF29: =AD29*1.1 -> 114.95 | AG29: =AE29*1.1 -> 0 | AH29: =AF29*1.1 -> 126.445 | AJ29: =AG29*1.08 -> 0 | AK29: =AH29*1.08 -> 136.5606 | AP29: =AJ29 -> 0 | AQ29: =AK29 -> 136.5606 | AR29: =AP29*1.05 -> 0 | AS29: =AQ29*1.1 -> 150.21666 | AU29: =AR29 -> 0 | AV29: =AS29 -> 150.21666 | AW29: 0 | AX29: =AW29*1.06 -> 0 | AY29: 150.3 | AZ29: =AY29*1.06 -> 159.318 | BB29: =AX29*1.07 -> 0 | BC29: =AZ29*1.07 -> 170.47026 | BD29: =BB29*1.1 -> 0 | BE29: =BC29*1.1 -> 187.51729 | BF29: =BD29+(BD29-(BD29*1.15)) -> 0 | BG29: =BE29+(BE29-(BE29*1.15)) -> 159.38969
B30: 22 | E30: 0105 ao 0107 7511 ao 7516 | H30: indisponível | J30: =ROUNDUP(((BG30*$N$3)+BG30),1) -> 166.7 | L30: 0 | AQ30: 136.56 | AS30: =AQ30*1.15 -> 157.044 | AU30: =AR30 -> 0 | AV30: =AS30 -> 157.044 | AW30: 0 | AX30: =AW30*1.06 -> 0 | AY30: 157.1 | AZ30: =AY30*1.06 -> 166.526 | BB30: =AX30*1.07 -> 0 | BC30: =AZ30*1.07 -> 178.18282 | BD30: =BB30*1.1 -> 0 | BE30: =BC30*1.1 -> 196.0011 | BF30: =BD30+(BD30-(BD30*1.15)) -> 0 | BG30: =BE30+(BE30-(BE30*1.15)) -> 166.60094
B31: 23 | E31: 3031 | H31: indisponível | J31: =ROUNDUP(((BG31*$N$3)+BG31),1) -> 165.2 | L31: 0 | AA31: 0 | AB31: 95.9 | AC31: 0 | AD31: 103.6 | AE31: =AC31*1.1 -> 0 | AF31: =AD31*1.1 -> 113.96 | AG31: =AE31*1.1 -> 0 | AH31: =AF31*1.1 -> 125.356 | AJ31: =AG31*1.08 -> 0 | AK31: =AH31*1.08 -> 135.38448 | AP31: =AJ31 -> 0 | AQ31: =AK31 -> 135.38448 | AR31: =AP31*1.05 -> 0 | AS31: =AQ31*1.15 -> 155.69215 | AU31: =AR31 -> 0 | AV31: =AS31 -> 155.69215 | AW31: 0 | AX31: =AW31*1.06 -> 0 | AY31: 155.7 | AZ31: =AY31*1.06 -> 165.042 | BB31: =AX31*1.07 -> 0 | BC31: =AZ31*1.07 -> 176.59494 | BD31: =BB31*1.1 -> 0 | BE31: =BC31*1.1 -> 194.25443 | BF31: =BD31+(BD31-(BD31*1.15)) -> 0 | BG31: =BE31+(BE31-(BE31*1.15)) -> 165.11627
B32: 24 | E32: 3037 e 3038 | H32: indisponível | J32: =ROUNDUP(((BG32*$N$3)+BG32),1) -> 191.7 | L32: 0 | AA32: 0 | AB32: 96.7 | AC32: 0 | AD32: 104.5 | AE32: =AC32*1.1 -> 0 | AF32: =AD32*1.1 -> 114.95 | AG32: =AE32*1.1 -> 0 | AH32: =AF32*1.1 -> 126.445 | AJ32: =AG32*1.12 -> 0 | AK32: =AH32*1.12 -> 141.6184 | AP32: =AJ32 -> 0 | AQ32: =AK32*1.08 -> 152.94787 | AR32: =AP32*1.05 -> 0 | AS32: =AQ32*1.15 -> 175.89005 | AU32: =AR32 -> 0 | AV32: 180.7 | AW32: 0 | AX32: =AW32*1.06 -> 0 | AY32: 180.7 | AZ32: =AY32*1.06 -> 191.542 | BB32: =AX32*1.07 -> 0 | BC32: =AZ32*1.07 -> 204.94994 | BD32: =BB32*1.1 -> 0 | BE32: =BC32*1.1 -> 225.44493 | BF32: =BD32+(BD32-(BD32*1.15)) -> 0 | BG32: =BE32+(BE32-(BE32*1.15)) -> 191.62819
B33: 25 | E33: 3039 ao 3040 | H33: indisponível | J33: =ROUNDUP(((BG33*$N$3)+BG33),1) -> 191.7 | L33: 0 | AB33: 96.7 | AD33: 104.5 | AE33: =AC33*1.1 -> 0 | AF33: =AD33*1.1 -> 114.95 | AG33: =AE33*1.1 -> 0 | AH33: =AF33*1.1 -> 126.445 | AJ33: =AG33*1.15 -> 0 | AK33: =AH33*1.15 -> 145.41175 | AP33: =AJ33 -> 0 | AQ33: =AK33*1.08 -> 157.04469 | AR33: =AP33*1.05 -> 0 | AS33: =AQ33*1.15 -> 180.60139 | AU33: =AR33 -> 0 | AV33: =AS33 -> 180.60139 | AW33: 0 | AX33: =AW33*1.06 -> 0 | AY33: 180.7 | AZ33: =AY33*1.06 -> 191.542 | BB33: =AX33*1.07 -> 0 | BC33: =AZ33*1.07 -> 204.94994 | BD33: =BB33*1.1 -> 0 | BE33: =BC33*1.1 -> 225.44493 | BF33: =BD33+(BD33-(BD33*1.15)) -> 0 | BG33: =BE33+(BE33-(BE33*1.15)) -> 191.62819
B34: 26 | E34: 3042 e 3044 | H34: indisponível | J34: =ROUNDUP(((BG34*$N$3)+BG34),1) -> 159.4 | L34: 0 | AB34: 96.7 | AD34: 104.5 | AE34: =AC34*1.1 -> 0 | AF34: =AD34*1.1 -> 114.95 | AG34: =AE34*1.1 -> 0 | AH34: =AF34*1.1 -> 126.445 | AJ34: =AG34*1.08 -> 0 | AP34: =AJ34 -> 0 | AQ34: =AK35 -> 136.5606 | AR34: =AP34*1.05 -> 0 | AS34: =AQ34*1.1 -> 150.21666 | AU34: =AR34 -> 0 | AV34: =AS34 -> 150.21666 | AW34: 0 | AX34: =AW34*1.06 -> 0 | AY34: 150.3 | AZ34: =AY34*1.06 -> 159.318 | BB34: =AX34*1.07 -> 0 | BC34: =AZ34*1.07 -> 170.47026 | BD34: =BB34*1.1 -> 0 | BE34: =BC34*1.1 -> 187.51729 | BF34: =BD34+(BD34-(BD34*1.15)) -> 0 | BG34: =BE34+(BE34-(BE34*1.15)) -> 159.38969
B35: 27 | E35: 3041 | H35: indisponível | J35: =ROUNDUP(((BG35*$N$3)+BG35),1) -> 166.7 | L35: 0.1 | AJ35: =AG35*1.08 -> 0 | AK35: =AH34*1.08 -> 136.5606 | AP35: =AJ35 -> 0 | AQ35: =AK36*1.08 -> 147.23977 | AR35: =AP35*1.05 -> 0 | AS35: =AQ35*1.05 -> 154.60176 | AU35: =AR35 -> 0 | AV35: 157.1 | AW35: 0 | AX35: =AW35*1.06 -> 0 | AY35: 157.1 | AZ35: =AY35*1.06 -> 166.526 | BB35: =AX35*1.07 -> 0 | BC35: =AZ35*1.07 -> 178.18282 | BD35: =BB35*1.1 -> 0 | BE35: =BC35*1.1 -> 196.0011 | BF35: =BD35+(BD35-(BD35*1.15)) -> 0 | BG35: =BE35+(BE35-(BE35*1.15)) -> 166.60094
B36: 28 | E36: 7500 e 7501 | H36: indisponível | J36: =ROUNDUP(((BG36*$N$3)+BG36),1) -> 178.8 | L36: 0 | AB36: 93.1 | AD36: 100.6 | AE36: =AC36*1.1 -> 0 | AF36: =AD36*1.1 -> 110.66 | AG36: =AE36*1.1 -> 0 | AH36: =AF36*1.1 -> 121.726 | AJ36: =AG36*1.12 -> 0 | AK36: =AH36*1.12 -> 136.33312 | AP36: =AJ36 -> 0 | AQ36: =AK36*1.08 -> 147.23977 | AR36: =AP36*1.05 -> 0 | AS36: =AQ36*1.05 -> 154.60176 | AU36: =AR36 -> 0 | AV36: =AS36*1.05 -> 162.33185 | AW36: 0 | AX36: =AW36*1.06 -> 0 | AY36: 162.4 | AZ36: =AY36*1.1 -> 178.64 | BB36: =AX36*1.07 -> 0 | BC36: =AZ36*1.07 -> 191.1448 | BD36: =BB36*1.1 -> 0 | BE36: =BC36*1.1 -> 210.25928 | BF36: =BD36+(BD36-(BD36*1.15)) -> 0 | BG36: =BE36+(BE36-(BE36*1.15)) -> 178.72039
B37: 29 | E37: 7504, 7506 e 7508 | H37: indisponível | J37: =ROUNDUP(((BG37*$N$3)+BG37),1) -> 172.9 | L37: 0 | AG37: =AE37*1.1 -> 0 | AH37: 121.73 | AJ37: =AG37*1.08 -> 0 | AK37: =AH37*1.08 -> 131.4684 | AP37: =AJ37 -> 0 | AQ37: =AK37*1.08 -> 141.98587 | AR37: =AP37*1.05 -> 0 | AS37: =AQ37*1.05 -> 149.08517 | AU37: =AR37 -> 0 | AV37: 157.1 | AW37: 0 | AX37: =AW37*1.06 -> 0 | AY37: 157.1 | AZ37: =AY37*1.1 -> 172.81 | BB37: =AX37*1.07 -> 0 | BC37: =AZ37*1.07 -> 184.9067 | BD37: =BB37*1.1 -> 0 | BE37: =BC37*1.1 -> 203.39737 | BF37: =BD37+(BD37-(BD37*1.15)) -> 0 | BG37: =BE37+(BE37-(BE37*1.15)) -> 172.88776
B38: 30 | C38: OXFORD BLACKOUT | E38: 0410, 0411 e 0414 | H38: indisponível | J38: =ROUNDUP(((BG38*$N$3)+BG38),1) -> 140.9 | L38: 0 | AA38: 0 | AB38: 96.7 | AC38: 0 | AD38: 104.5 | AE38: =AC38*1.1 -> 0 | AF38: =AD38*1.1 -> 114.95 | AG38: =AE38*1.1 -> 0 | AH38: =AF38*1.1 -> 126.445 | AJ38: =AG38 -> 0 | AK38: =AH38 -> 126.445 | AP38: =AJ38 -> 0 | AQ38: =AK38*1.05 -> 132.76725 | AR38: =AP38*1.05 -> 0 | AS38: =AQ38 -> 132.76725 | AU38: =AR38 -> 0 | AV38: =AS38 -> 132.76725 | AW38: 0 | AX38: =AW38*1.06 -> 0 | AY38: 132.8 | AZ38: =AY38*1.06 -> 140.768 | BB38: =AX38*1.07 -> 0 | BC38: =AZ38*1.07 -> 150.62176 | BD38: =BB38*1.1 -> 0 | BE38: =BC38*1.1 -> 165.68394 | BF38: =BD38+(BD38-(BD38*1.15)) -> 0 | BG38: =BE38+(BE38-(BE38*1.15)) -> 140.83135
B39: 31 | C39: FLORENÇA | E39: 0356 | H39: =ROUNDUP(((BF39*$N$3)+BF39),1) -> 111.8 | J39: =ROUNDUP(((BG39*$N$3)+BG39),1) -> 134.1 | L39: 0 | AA39: 66.5 | AB39: 79.9 | AC39: 71.9 | AD39: 86.3 | AE39: =AC39*1.1 -> 79.09 | AF39: =AD39*1.1 -> 94.93 | AG39: =AE39*1.1 -> 86.999 | AH39: =AF39*1.1 -> 104.423 | AJ39: =AG39*1.08 -> 93.95892 | AK39: =AH39*1.08 -> 112.77684 | AP39: =AJ39*1.08 -> 101.47563 | AQ39: =AK39*1.08 -> 121.79899 | AR39: =AP39 -> 101.47563 | AS39: =AQ39 -> 121.79899 | AU39: =AR39 -> 101.47563 | AV39: =AS39 -> 121.79899 | AW39: 101.5 | AX39: =AW39*1.1 -> 111.65 | AY39: 121.8 | AZ39: =AY39*1.1 -> 133.98 | BB39: =AX39*1.07 -> 119.4655 | BC39: =AZ39*1.07 -> 143.3586 | BD39: =BB39*1.1 -> 131.41205 | BE39: =BC39*1.1 -> 157.69446 | BF39: =BD39+(BD39-(BD39*1.15)) -> 111.70024 | BG39: =BE39+(BE39-(BE39*1.15)) -> 134.04029
B40: 32 | C40: RUSTIC | E40: 0053 | H40: =ROUNDUP(((BF40*$N$3)+BF40),1) -> 107.8 | J40: =ROUNDUP(((BG40*$N$3)+BG40),1) -> 129.7 | L40: 0 | AA40: 69.3 | AB40: 83.4 | AC40: 74.9 | AD40: 90.1 | AE40: =AC40*1.1 -> 82.39 | AF40: =AD40*1.1 -> 99.11 | AG40: =AE40*1.1 -> 90.629 | AH40: =AF40*1.1 -> 109.021 | AJ40: =AG40 -> 90.629 | AK40: =AH40 -> 109.021 | AP40: =AJ40*1.08 -> 97.87932 | AQ40: =AK40*1.08 -> 117.74268 | AR40: =AP40 -> 97.87932 | AS40: =AQ40 -> 117.74268 | AU40: =AR40 -> 97.87932 | AV40: =AS40 -> 117.74268 | AW40: 97.9 | AX40: =AW40*1.1 -> 107.69 | AY40: 117.8 | AZ40: =AY40*1.1 -> 129.58 | BB40: =AX40*1.07 -> 115.2283 | BC40: =AZ40*1.07 -> 138.6506 | BD40: =BB40*1.1 -> 126.75113 | BE40: =BC40*1.1 -> 152.51566 | BF40: =BD40+(BD40-(BD40*1.15)) -> 107.73846 | BG40: =BE40+(BE40-(BE40*1.15)) -> 129.63831
B41: 33 | C41: ELEGANCY | E41: 0161 e 0162 | H41: =ROUNDUP(((BF41*$N$3)+BF41),1) -> 123.4 | J41: =ROUNDUP(((BG41*$N$3)+BG41),1) -> 148.3 | L41: 0 | AA41: 73.5 | AB41: 88.3 | AC41: 79.4 | AD41: 95.4 | AE41: =AC41*1.1 -> 87.34 | AF41: =AD41*1.1 -> 104.94 | AG41: =AE41*1.1 -> 96.074 | AH41: =AF41*1.1 -> 115.434 | AJ41: =AG41*1.08 -> 103.75992 | AK41: =AH41*1.08 -> 124.66872 | AP41: =AJ41*1.08 -> 112.06071 | AQ41: =AK41*1.08 -> 134.64222 | AR41: =AP41 -> 112.06071 | AS41: =AQ41 -> 134.64222 | AU41: =AR41 -> 112.06071 | AV41: =AS41 -> 134.64222 | AW41: 112.1 | AX41: =AW41*1.1 -> 123.31 | AY41: 134.7 | AZ41: =AY41*1.1 -> 148.17 | BB41: =AX41*1.07 -> 131.9417 | BC41: =AZ41*1.07 -> 158.5419 | BD41: =BB41*1.1 -> 145.13587 | BE41: =BC41*1.1 -> 174.39609 | BF41: =BD41+(BD41-(BD41*1.15)) -> 123.36549 | BG41: =BE41+(BE41-(BE41*1.15)) -> 148.23668
B42: 34 | E42: 0126 e 0128 | H42: =ROUNDUP(((BF42*$N$3)+BF42),1) -> 123.4 | J42: =ROUNDUP(((BG42*$N$3)+BG42),1) -> 142.9 | L42: 0 | AA42: 73.5 | AB42: 88.3 | AC42: 79.4 | AD42: 95.4 | AE42: =AC42*1.1 -> 87.34 | AF42: =AD42*1.1 -> 104.94 | AG42: =AE42*1.1 -> 96.074 | AH42: =AF42*1.1 -> 115.434 | AJ42: =AG42*1.08 -> 103.75992 | AK42: =AH42*1.08 -> 124.66872 | AP42: =AJ42*1.08 -> 112.06071 | AQ42: =AK42*1.08 -> 134.64222 | AR42: =AP42 -> 112.06071 | AS42: =AQ42 -> 134.64222 | AU42: =AR42 -> 112.06071 | AV42: =AS42 -> 134.64222 | AW42: 112.1 | AX42: =AW42*1.1 -> 123.31 | AY42: 134.7 | AZ42: =AY42*1.06 -> 142.782 | BB42: =AX42*1.07 -> 131.9417 | BC42: =AZ42*1.07 -> 152.77674 | BD42: =BB42*1.1 -> 145.13587 | BE42: =BC42*1.1 -> 168.05441 | BF42: =BD42+(BD42-(BD42*1.15)) -> 123.36549 | BG42: =BE42+(BE42-(BE42*1.15)) -> 142.84625
B43: 35 | E43: 0169, 0170, 0171, 0177 e 0178 | H43: =ROUNDUP(((BF43*$N$3)+BF43),1) -> 123.4 | J43: =ROUNDUP(((BG43*$N$3)+BG43),1) -> 148.3 | L43: 0 | AX43: 123.4 | AZ43: 148.2 | BB43: =AX43*1.07 -> 132.038 | BC43: =AZ43*1.07 -> 158.574 | BD43: 145.2 | BE43: 174.4 | BF43: 123.4 | BG43: =BE43+(BE43-(BE43*1.15)) -> 148.24
B44: 36 | C44: VENEZA | E44: 0060 | H44: =ROUNDUP(((BF44*$N$3)+BF44),1) -> 114.3 | J44: =ROUNDUP(((BG44*$N$3)+BG44),1) -> 137.3 | L44: 0 | AA44: 73.5 | AB44: 88.3 | AC44: 79.4 | AD44: 95.4 | AE44: =AC44*1.1 -> 87.34 | AF44: =AD44*1.1 -> 104.94 | AG44: =AE44*1.1 -> 96.074 | AH44: =AF44*1.1 -> 115.434 | AJ44: =AG44 -> 96.074 | AK44: =AH44 -> 115.434 | AP44: =AJ44*1.08 -> 103.75992 | AQ44: =AK44*1.08 -> 124.66872 | AR44: =AP44 -> 103.75992 | AS44: =AQ44 -> 124.66872 | AU44: =AR44 -> 103.75992 | AV44: =AS44 -> 124.66872 | AW44: 103.8 | AX44: =AW44*1.1 -> 114.18 | AY44: 124.7 | AZ44: =AY44*1.1 -> 137.17 | BB44: =AX44*1.07 -> 122.1726 | BC44: =AZ44*1.07 -> 146.7719 | BD44: =BB44*1.1 -> 134.38986 | BE44: =BC44*1.1 -> 161.44909 | BF44: =BD44+(BD44-(BD44*1.15)) -> 114.23138 | BG44: =BE44+(BE44-(BE44*1.15)) -> 137.23173
B45: 37 | E45: 0076 ao 0077 | H45: =ROUNDUP(((BF45*$N$3)+BF45),1) -> 110.1 | J45: =ROUNDUP(((BG45*$N$3)+BG45),1) -> 132.3 | L45: 0 | AW45: 103.8 | AX45: =AW45*1.06 -> 110.028 | AY45: 124.7 | AZ45: =AY45*1.06 -> 132.182 | BB45: =AX45*1.07 -> 117.72996 | BC45: =AZ45*1.07 -> 141.43474 | BD45: =BB45*1.1 -> 129.50296 | BE45: =BC45*1.1 -> 155.57821 | BF45: =BD45+(BD45-(BD45*1.15)) -> 110.07751 | BG45: =BE45+(BE45-(BE45*1.15)) -> 132.24148
B46: 38 | C46: DUBAI | E46: 0221 e 0227 | H46: =ROUNDUP(((BF46*$N$3)+BF46),1) -> 179.1 | J46: =ROUNDUP(((BG46*$N$3)+BG46),1) -> 214.9 | L46: 0 | AA46: 96.4 | AB46: 115.8 | AC46: 104.2 | AD46: 125.1 | AE46: =AC46*1.1 -> 114.62 | AF46: =AD46*1.1 -> 137.61 | AG46: =AE46*1.1 -> 126.082 | AH46: =AF46*1.1 -> 151.371 | AJ46: =AG46*1.18 -> 148.77676 | AK46: =AH46*1.18 -> 178.61778 | AP46: =AJ46*1.08 -> 160.6789 | AQ46: =AK46*1.08 -> 192.9072 | AR46: =AP46*1.05 -> 168.71285 | AS46: =AQ46*1.05 -> 202.55256 | AU46: =AR46 -> 168.71285 | AV46: =AS46 -> 202.55256 | AW46: 168.8 | AX46: =AW46*1.06 -> 178.928 | AY46: 202.6 | AZ46: =AY46*1.06 -> 214.756 | BB46: =AX46*1.07 -> 191.45296 | BC46: =AZ46*1.07 -> 229.78892 | BD46: =BB46*1.1 -> 210.59826 | BE46: =BC46*1.1 -> 252.76781 | BF46: =BD46+(BD46-(BD46*1.15)) -> 179.00852 | BG46: =BE46+(BE46-(BE46*1.15)) -> 214.85264
B47: 39 | C47: ÁGATA | E47: 0473 | H47: =ROUNDUP(((BF47*$N$3)+BF47),1) -> 110.9 | J47: indisponível | L47: 0 | AA47: 72.6 | AB47: - | AC47: 78.5 | AE47: =AC47*1.1 -> 86.35 | AF47: =AD47*1.1 -> 0 | AG47: =AE47*1.1 -> 94.985 | AH47: =AF47*1.1 -> 0 | AJ47: =AG47*1.1 -> 104.4835 | AK47: =AH47*1.1 -> 0 | AP47: =AJ47 -> 104.4835 | AQ47: =AK47 -> 0 | AR47: =AP47 -> 104.4835 | AS47: =AQ47*1.05 -> 0 | AU47: =AR47 -> 104.4835 | AV47: =AS47 -> 0 | AW47: 104.5 | AX47: =AW47*1.06 -> 110.77 | AY47: 0 | AZ47: =AY47*1.06 -> 0 | BB47: =AX47*1.07 -> 118.5239 | BC47: =AZ47*1.07 -> 0 | BD47: =BB47*1.1 -> 130.37629 | BE47: =BC47*1.1 -> 0 | BF47: =BD47+(BD47-(BD47*1.15)) -> 110.81985 | BG47: =BE47+(BE47-(BE47*1.15)) -> 0
B48: 40 | C48: MONASTREL | E48: 0442 - Desconto de 50% *** | H48: =ROUNDUP(((BF48*$N$3)+BF48),1) -> 157.6 | J48: indisponível | L48: 0 | AA48: 103.3 | AB48: - | AC48: 111.6 | AE48: =AC48*1.1 -> 122.76 | AF48: =AD48*1.1 -> 0 | AG48: =AE48*1.1 -> 135.036 | AH48: =AF48*1.1 -> 0 | AJ48: =AG48*1.1 -> 148.5396 | AK48: =AH48*1.1 -> 0 | AP48: =AJ48 -> 148.5396 | AQ48: =AK48 -> 0 | AR48: =AP48 -> 148.5396 | AS48: =AQ48 -> 0 | AU48: =AR48 -> 148.5396 | AV48: =AS48 -> 0 | AW48: 148.6 | AX48: =AW48*1.06 -> 157.516 | AY48: 0 | AZ48: =AY48*1.06 -> 0 | BB48: =AX48*1.07 -> 168.54212 | BC48: =AZ48*1.07 -> 0 | BD48: =BB48*1.1 -> 185.39633 | BE48: =BC48*1.1 -> 0 | BF48: =BD48+(BD48-(BD48*1.15)) -> 157.58688 | BG48: =BE48+(BE48-(BE48*1.15)) -> 0
B49: 41 | C49: MANHATTAN | E49: 0485 ao 0490 | H49: =ROUNDUP(((BF49*$N$3)+BF49),1) -> 151.7 | J49: =ROUNDUP(((BG49*$N$3)+BG49),1) -> 182.1 | L49: 0 | AB49: - | AC49: 104.2 | AD49: 125.1 | AE49: =AC49*1.1 -> 114.62 | AF49: =AD49*1.1 -> 137.61 | AG49: =AE49*1.1 -> 126.082 | AH49: =AF49*1.1 -> 151.371 | AJ49: =AG49*1.08 -> 136.16856 | AK49: =AH49*1.08 -> 163.48068 | AP49: =AJ49 -> 136.16856 | AQ49: =AK49 -> 163.48068 | AR49: =AP49*1.05 -> 142.97699 | AS49: =AQ49*1.05 -> 171.65471 | AU49: =AR49 -> 142.97699 | AV49: =AS49 -> 171.65471 | AW49: 143 | AX49: =AW49*1.06 -> 151.58 | AY49: 171.7 | AZ49: =AY49*1.06 -> 182.002 | BB49: =AX49*1.07 -> 162.1906 | BC49: =AZ49*1.07 -> 194.74214 | BD49: =BB49*1.1 -> 178.40966 | BE49: =BC49*1.1 -> 214.21635 | BF49: =BD49+(BD49-(BD49*1.15)) -> 151.64821 | BG49: =BE49+(BE49-(BE49*1.15)) -> 182.0839
B50: 42 | C50: SEVILHA | E50: 3354, 3355, 3356, 3357, 3358, 3359, 3360, 3361 | H50: =ROUNDUP(((BF50*$N$3)+BF50),1) -> 110.2 | J50: =ROUNDUP(((BG50*$N$3)+BG50),1) -> 132.3 | L50: 0 | AX50: 110.1 | AZ50: 132.2 | BB50: =AX50*1.07 -> 117.807 | BC50: =AZ50*1.07 -> 141.454 | BD50: =BB50*1.1 -> 129.5877 | BE50: =BC50*1.1 -> 155.5994 | BF50: =BD50+(BD50-(BD50*1.15)) -> 110.14955 | BG50: =BE50+(BE50-(BE50*1.15)) -> 132.25949
B51: 43 | C51: LISBOA | E51: 3380, 3381, 3382, 3383, 3384, 3385, 3386 | H51: =ROUNDUP(((BF51*$N$3)+BF51),1) -> 123.5 | J51: indisponível | L51: 0 | AX51: 123.4 | AZ51: 148.2 | BB51: =AX51*1.07 -> 132.038 | BC51: =AZ51*1.07 -> 158.574 | BD51: =BB51*1.1 -> 145.2418 | BE51: =BC51*1.1 -> 174.4314 | BF51: =BD51+(BD51-(BD51*1.15)) -> 123.45553 | BG51: =BE51+(BE51-(BE51*1.15)) -> 148.26669
B52: 44 | C52: BARCELONA | E52: 3390, 3391, 3392, 3393, 3394 | H52: =ROUNDUP(((BF52*$N$3)+BF52),1) -> 151.7 | J52: indisponível | L52: 0 | AX52: 151.6 | AZ52: 182.1 | BB52: =AX52*1.07 -> 162.212 | BC52: =AZ52*1.07 -> 194.847 | BD52: =BB52*1.1 -> 178.4332 | BE52: =BC52*1.1 -> 214.3317 | BF52: =BD52+(BD52-(BD52*1.15)) -> 151.66822 | BG52: =BE52+(BE52-(BE52*1.15)) -> 182.18195
B53: 45 | C53: FINESSE BK | E53: 6500 ao 6808 | H53: indisponível | J53: =ROUNDUP(((BG53*$N$3)+BG53),1) -> 191.7 | L53: 0 | BC53: 205 | BD53: =BB53*1.1 -> 0 | BE53: =BC53*1.1 -> 225.5 | BF53: =BD53+(BD53-(BD53*1.15)) -> 0 | BG53: =BE53+(BE53-(BE53*1.15)) -> 191.675
B54: 46 | C54: TRANCOSO | E54: 8800 ao 8804 | H54: =ROUNDUP(((BF54*$N$3)+BF54),1) -> 112.8 | J54: =ROUNDUP(((BG54*$N$3)+BG54),1) -> 135.4 | L54: 0 | BD54: 132.6 | BE54: 159.2 | BF54: =BD54+(BD54-(BD54*1.15)) -> 112.71 | BG54: =BE54+(BE54-(BE54*1.15)) -> 135.32
B55: 47 | C55: CARAÍVA BK | E55: 8900 ao 8904 | H55: indisponível | J55: =ROUNDUP(((BG55*$N$3)+BG55),1) -> 187.5 | L55: 0 | BD55: 183.7 | BE55: 220.5 | BF55: =BD55+(BD55-(BD55*1.15)) -> 156.145 | BG55: =BE55+(BE55-(BE55*1.15)) -> 187.425
B56: 48 | C56: CAMBURI BK | E56: 9200 ao 9209 | H56: indisponível | J56: =ROUNDUP(((BG56*$N$3)+BG56),1) -> 187.5 | L56: 0 | BD56: 183.7 | BE56: 220.5 | BF56: =BD56+(BD56-(BD56*1.15)) -> 156.145 | BG56: =BE56+(BE56-(BE56*1.15)) -> 187.425
B57: 49 | C57: IPANEMA | E57: 7800 ao 7804 | H57: =ROUNDUP(((BF57*$N$3)+BF57),1) -> 143.3 | J57: =ROUNDUP(((BG57*$N$3)+BG57),1) -> 171.9 | L57: 0 | BD57: 168.5 | BE57: 202.2 | BF57: =BD57+(BD57-(BD57*1.15)) -> 143.225 | BG57: =BE57+(BE57-(BE57*1.15)) -> 171.87
B58: 50 | C58: NORONHA | E58: 8600 ao 8606 | H58: =ROUNDUP(((BF58*$N$3)+BF58),1) -> 143.3 | J58: =ROUNDUP(((BG58*$N$3)+BG58),1) -> 171.9 | L58: 0 | BD58: 168.5 | BE58: 202.2 | BF58: =BD58+(BD58-(BD58*1.15)) -> 143.225 | BG58: =BE58+(BE58-(BE58*1.15)) -> 171.87
B59: 51 | C59: LEBLON | E59: 8200 ao 8205 | H59: =ROUNDUP(((BF59*$N$3)+BF59),1) -> 143.3 | J59: =ROUNDUP(((BG59*$N$3)+BG59),1) -> 171.9 | L59: 0 | BD59: 168.5 | BE59: 202.2 | BF59: =BD59+(BD59-(BD59*1.15)) -> 143.225 | BG59: =BE59+(BE59-(BE59*1.15)) -> 171.87
B60: 52
B61: 53
B62: 54
B63: 55
B64: 56
B65: 57 | C65: *** CORTINA PAINEL EM TECIDOS BLACKOUT SOMENTE SÃO PRODUZIDAS COM HASTES. *** ITENS DESTACADOS NA COR VERDE, POSSUEM DESCONTO DE 50% NO VALOR DE TABELA. *** OS TECIDOS PROMOCIONAIS SÃO CONDICIONADOS A DISPONIBILIDADE NO ESTOQUE. *** SOB ESTES VALORES PROMOCIONAIS NÃO INCIDIRÃO EVENTUAIS DESCONTOS. DESCONTO NÃO SE APLICA A ACESSÓRIOS SOLICITADOS COM A PEÇA.
B66: 58
B67: 59 | C67: * GARANTIA DE 3 ANOS - ANTES DE ENVIAR O PEDIDO CONSULTE A PÁGINA DE INFORMAÇÕES TÉCNICAS.
B68: 60 | C68: TECIDO SCREEN REFLEX 5% COM CAMADA REFLETORA NA PARTE DE TRÁS - REFLETE O SOL REDUZINDO O CALOR INTERNO DO AMBIENTE.
K69: Página 15 - | L69: =Rolô!$L$2 -> 2026 - v.03 | N69: * DIGITE A PORCENTAGEM PARA MARKUP - ACESSÓRIOS
B70: CORTINA PAINEL EUROPA | N70: 0
B73: 61 | C73: ACESSÓRIOS
B74: 62 | C74: DESCRIÇÃO DO ACESSÓRIO | H74: COR | I74: UNIDADE | J74: VALOR À VISTA (R$) | L74: IPI | N74: * Legenda de Cores: | AA74: 42491 | AB74: 43026 | AC74: 43258 | AD74: 43862 | AE74: 43952 | AF74: 44105 | AG74: 44256 | AH74: 44378 | AI74: 44409 | AJ74: 44501 | AM74: 45658
B75: 63 | C75: TRILHO DESLIZANTES DE 2 VIAS | H75: B - M - P | I75: ML | J75: =ROUNDUP(((AM75*$N$70)+AM75),1) -> 101.4 | L75: 0 | N75: B = Branco | AA75: 42.5 | AB75: 45.9 | AC75: =AB75*1.1 -> 50.49 | AD75: =AC75*1.1 -> 55.539 | AE75: =AD75*1.1 -> 61.0929 | AF75: =AE75*1.05 -> 64.147545 | AG75: =AF75*1.1 -> 70.5623 | AH75: =AG75*1.15 -> 81.146644 | AJ75: 81.2 | AK75: =AJ75*1.06 -> 86.072 | AL75: =AK75*1.07 -> 92.09704 | AM75: =AL75*1.1 -> 101.30674
B76: 64 | C76: TRILHO DESLIZANTES DE 3 VIAS | H76: B - M - P | I76: ML | J76: =ROUNDUP(((AM76*$N$70)+AM76),1) -> 120.3 | L76: 0 | N76: M = Marfim | AA76: 50.4 | AB76: 54.5 | AC76: =AB76*1.1 -> 59.95 | AD76: =AC76*1.1 -> 65.945 | AE76: =AD76*1.1 -> 72.5395 | AF76: =AE76*1.05 -> 76.166475 | AG76: =AF76*1.1 -> 83.783123 | AH76: =AG76*1.15 -> 96.350591 | AJ76: 96.4 | AK76: =AJ76*1.06 -> 102.184 | AL76: =AK76*1.07 -> 109.33688 | AM76: =AL76*1.1 -> 120.27057
B77: 65 | C77: TRILHO DESLIZANTES DE 4 VIAS | H77: B - M - P | I77: ML | J77: =ROUNDUP(((AM77*$N$70)+AM77),1) -> 136.4 | L77: 0 | N77: P = Preto | AA77: 57.2 | AB77: 61.8 | AC77: =AB77*1.1 -> 67.98 | AD77: =AC77*1.1 -> 74.778 | AE77: =AD77*1.1 -> 82.2558 | AF77: =AE77*1.05 -> 86.36859 | AG77: =AF77*1.1 -> 95.005449 | AH77: =AG77*1.15 -> 109.25627 | AJ77: 109.3 | AK77: =AJ77*1.06 -> 115.858 | AL77: =AK77*1.07 -> 123.96806 | AM77: =AL77*1.1 -> 136.36487
B78: 66 | C78: TRILHO DESLIZANTES DE 5 VIAS | H78: B - M - P | I78: ML | J78: =ROUNDUP(((AM78*$N$70)+AM78),1) -> 156.3 | L78: 0 | N78: C = Cinza | AA78: 65.5 | AB78: 70.8 | AC78: =AB78*1.1 -> 77.88 | AD78: =AC78*1.1 -> 85.668 | AE78: =AD78*1.1 -> 94.2348 | AF78: =AE78*1.05 -> 98.94654 | AG78: =AF78*1.1 -> 108.84119 | AH78: =AG78*1.15 -> 125.16737 | AJ78: 125.2 | AK78: =AJ78*1.06 -> 132.712 | AL78: =AK78*1.07 -> 142.00184 | AM78: =AL78*1.1 -> 156.20202
B79: 67 | C79: BANDO DE PERSIANA VERTICAL REVESTIDO COM TECIDO DE COLEÇÕES¹ | H79: Natural | I79: ML | J79: =ROUNDUP(((AM79*$N$70)+AM79),1) -> 48.5 | L79: 0 | AA79: 21.2 | AB79: 22.9 | AC79: =AB79*1.1 -> 25.19 | AD79: =AC79*1.1 -> 27.709 | AE79: =AD79*1.1 -> 30.4799 | AF79: =AE79*1.05 -> 32.003895 | AG79: =AF79*1.1 -> 35.204285 | AH79: =AG79*1.1 -> 38.724713 | AJ79: 38.8 | AK79: =AJ79*1.06 -> 41.128 | AL79: =AK79*1.07 -> 44.00696 | AM79: =AL79*1.1 -> 48.407656
B80: 68 | C80: BANDO DE PERSIANA VERTICAL REVESTIDO COM TECIDO DE COLEÇÕES¹ | H80: B - M - P | I80: ML | J80: =ROUNDUP(((AM80*$N$70)+AM80),1) -> 50.3 | L80: 0 | AA80: 22 | AB80: 23.8 | AC80: =AB80*1.1 -> 26.18 | AD80: =AC80*1.1 -> 28.798 | AE80: =AD80*1.1 -> 31.6778 | AF80: =AE80*1.05 -> 33.26169 | AG80: =AF80*1.1 -> 36.587859 | AH80: =AG80*1.1 -> 40.246645 | AJ80: 40.3 | AK80: =AJ80*1.06 -> 42.718 | AL80: =AK80*1.07 -> 45.70826 | AM80: =AL80*1.1 -> 50.279086
B81: 69 | C81: BANDO PARA CORTINA PAINEL | H81: B - M - P | I81: ML | J81: =ROUNDUP(((AM81*$N$70)+AM81),1) -> 19.9 | L81: 0 | AC81: 10.3 | AD81: =AC81*1.1 -> 11.33 | AE81: =AD81*1.1 -> 12.463 | AF81: =AE81*1.05 -> 13.08615 | AG81: =AF81*1.1 -> 14.394765 | AH81: =AG81*1.1 -> 15.834242 | AJ81: 15.9 | AK81: =AJ81*1.06 -> 16.854 | AL81: =AK81*1.07 -> 18.03378 | AM81: =AL81*1.1 -> 19.837158
B82: 70 | C82: BASTÃO DE ACRÍLICO PARA CORTINAS COM ALTURA MÁXIMA DE 2,00M - COBRADO SEPARADAMENTE CONFORME A QUANTIDADE DE FOLHAS | H82: Branco | I82: UN | J82: =ROUNDUP(((AM82*$N$70)+AM82),1) -> 25.8 | L82: 0 | AA82: 10.7 | AB82: 11.6 | AC82: =AB82*1.1 -> 12.76 | AD82: =AC82*1.1 -> 14.036 | AE82: =AD82*1.1 -> 15.4396 | AF82: =AE82*1.05 -> 16.21158 | AG82: =AF82*1.1 -> 17.832738 | AH82: =AG82*1.15 -> 20.507649 | AJ82: 20.6 | AK82: =AJ82*1.06 -> 21.836 | AL82: =AK82*1.07 -> 23.36452 | AM82: =AL82*1.1 -> 25.700972
B83: 71 | AK83: =AJ83*1.06 -> 0 | AL83: =AK83*1.07 -> 0 | AM83: =AL83*1.1 -> 0
B84: 72 | C84: SUPORTE AFASTADOR 4 X 6 | H84: B - M - P | I84: UN | J84: =ROUNDUP(((AM84*$N$70)+AM84),1) -> 6.4 | L84: 0.1 | AA84: 2.4 | AB84: 2.6 | AC84: =AB84*1.1 -> 2.86 | AD84: =AC84*1.2 -> 3.432 | AE84: =AD84*1.1 -> 3.7752 | AF84: =AE84*1.05 -> 3.96396 | AG84: =AF84*1.1 -> 4.360356 | AH84: =AG84*1.15 -> 5.0144094 | AJ84: 5.1 | AK84: =AJ84*1.06 -> 5.406 | AL84: =AK84*1.07 -> 5.78442 | AM84: =AL84*1.1 -> 6.362862
B85: 73 | C85: SUPORTEAFASTADOR 6 X 9 | H85: B - M - P | I85: UN | J85: =ROUNDUP(((AM85*$N$70)+AM85),1) -> 8 | L85: 0.1 | AA85: 3 | AB85: 3.3 | AC85: =AB85*1.1 -> 3.63 | AD85: =AC85*1.2 -> 4.356 | AE85: =AD85*1.1 -> 4.7916 | AF85: =AE85*1.05 -> 5.03118 | AG85: =AF85*1.1 -> 5.534298 | AH85: =AG85*1.15 -> 6.3644427 | AJ85: 6.4 | AK85: =AJ85*1.06 -> 6.784 | AL85: =AK85*1.07 -> 7.25888 | AM85: =AL85*1.1 -> 7.984768
B86: 74 | C86: SUPORTE 8 X 13 COM ENCAIXE PARA BANDÔ | H86: Natural | I86: UN | J86: =ROUNDUP(((AM86*$N$70)+AM86),1) -> 6.2 | L86: 0.1 | AA86: 1.8 | AB86: 2 | AC86: =AB86*1.1 -> 2.2 | AD86: =AC86*1.5 -> 3.3 | AE86: =AD86*1.1 -> 3.63 | AF86: =AE86*1.05 -> 3.8115 | AG86: =AF86*1.1 -> 4.19265 | AH86: =AG86*1.15 -> 4.8215475 | AJ86: 4.9 | AK86: =AJ86*1.06 -> 5.194 | AL86: =AK86*1.07 -> 5.55758 | AM86: =AL86*1.1 -> 6.113338
B87: 75 | C87: SUPORTE 8 X 13 COM ENCAIXE PARA GALERIA DE MADEIRA | H87: Natural | I87: UN | J87: =ROUNDUP(((AM87*$N$70)+AM87),1) -> 6.4 | L87: 0.1 | AA87: 1.9 | AB87: 2.1 | AC87: =AB87*1.1 -> 2.31 | AD87: =AC87*1.5 -> 3.465 | AE87: =AD87*1.1 -> 3.8115 | AF87: =AE87*1.05 -> 4.002075 | AG87: =AF87*1.1 -> 4.4022825 | AH87: =AG87*1.15 -> 5.0626249 | AJ87: 5.1 | AK87: =AJ87*1.06 -> 5.406 | AL87: =AK87*1.07 -> 5.78442 | AM87: =AL87*1.1 -> 6.362862
B88: 76 | C88: FITA DECORATIVA - 2 FITAS POR FOLHA | H88: Ver linha 111 | I88: UN | J88: =ROUNDUP(((AM88*$N$70)+AM88),1) -> 166.9 | L88: 0 | AA88: 70 | AB88: 75.6 | AC88: =AB88*1.1 -> 83.16 | AD88: =AC88*1.1 -> 91.476 | AE88: =AD88*1.1 -> 100.6236 | AF88: =AE88*1.05 -> 105.65478 | AG88: =AF88*1.1 -> 116.22026 | AH88: =AG88*1.15 -> 133.6533 | AJ88: 133.7 | AK88: =AJ88*1.06 -> 141.722 | AL88: =AK88*1.07 -> 151.64254 | AM88: =AL88*1.1 -> 166.80679
B89: 77 | C89: FITA DECORATIVA - 3 FITAS POR FOLHA | H89: Ver linha 111 | I89: UN | J89: =ROUNDUP(((AM89*$N$70)+AM89),1) -> 226.4 | L89: 0 | AA89: 95 | AB89: 102.6 | AC89: =AB89*1.1 -> 112.86 | AD89: =AC89*1.1 -> 124.146 | AE89: =AD89*1.1 -> 136.5606 | AF89: =AE89*1.05 -> 143.38863 | AG89: =AF89*1.1 -> 157.72749 | AH89: =AG89*1.15 -> 181.38662 | AJ89: 181.4 | AK89: =AJ89*1.06 -> 192.284 | AL89: =AK89*1.07 -> 205.74388 | AM89: =AL89*1.1 -> 226.31827
B90: 78 | C90: O VALOR DO ACESSÓRIO SOLICITADO A PARTE É SOB CONSULTA. O VALOR QUE CONSTA NA TABELA É PARA ACESSÓRIO SOLICITADO COM O PRODUTO MONTADO.
B91: 79
B92: 80 | C92: INFORMAÇÕES TÉCNICAS
B93: 81
B94: 82
B95: 83
B96: 84
B97: 85
B98: 86
B99: 87
B100: 88
B101: 89
B102: 90
B103: 91
B104: 92
... B106: 94
...

Sheet Teto
K2: Página 16 - | L2: =Rolô!L2 -> 2026 - v.03
B3: CORTINA DE TETO
N6: * DIGITE A PORCENTAGEM PARA MARKUP
B7: ITEM | C7: COLEÇÃO | E7: COR | H7: VALOR À VISTA (R$)/M² ALLURE (STANDARD) | J7: VALOR À VISTA (R$)/M² MONOCONTROLE | L7: IPI | N7: 0 | AA7: MAI/2016 - ALLURE | AB7: MAI/2016 - MONO | AC7: OUT/2016 - ALLURE | AD7: OUT/2016 - MONO | AE7: JUN/2018 - ALLURE | AF7: JUN/2018 - MONO | AG7: fev/2020 - MONO | AH7: mai/2020- ALLURE | AI7: mai/2020 - MONO | AJ7: mar/2021- ALLURE | AK7: mar/2021 - MONO | AL7: nov/2021- ALLURE | AN7: nov/2021 - MONO | AX7: 45658
AR8: allure | AS8: mono | AX8: allure | AY8: mono
B9: 1 | C9: SCREEN 1% | E9: 0001, 0005, 0006, 1010, 1030 e 1031 | H9: =ROUNDUP(((AX9*$N$7)+AX9),1) -> 502 | J9: =ROUNDUP(((AY9*$N$7)+AY9),1) -> 557.1 | L9: 0 | AA9: 293.1 | AB9: 342.5 | AC9: 316.6 | AD9: 369.9 | AE9: =AC9*1.1 -> 348.26 | AF9: =AD9*1.1 -> 406.89 | AG9: =(((AF9*95)/100)-AF9)+AF9 -> 386.5455 | AH9: =AE9*1.1 -> 383.086 | AI9: =AG9*1.1 -> 425.20005 | AJ9: =AH9*1.05 -> 402.2403 | AK9: =AI9*1.05 -> 446.46005 | AL9: 402.3 | AM9: =AL9*1.06 -> 426.438 | AN9: 446.5 | AO9: =AN9*1.06 -> 473.29 | AR9: =AM9*1.07 -> 456.28866 | AS9: =AO9*1.07 -> 506.4203 | AX9: =AR9*1.1 -> 501.91753 | AY9: =AS9*1.1 -> 557.06233
B10: 2 | C10: SCREEN FIBER GLASS 1% | E10: 6001, 6002 e 6003 | H10: =ROUNDUP(((AX10*$N$7)+AX10),1) -> 681.5 | J10: =ROUNDUP(((AY10*$N$7)+AY10),1) -> 780.3 | L10: 0 | AA10: 398.05 | AB10: 479.7 | AC10: 429.9 | AD10: 518.1 | AE10: =AC10*1.1 -> 472.89 | AF10: =AD10*1.1 -> 569.91 | AG10: =(((AF10*95)/100)-AF10)+AF10 -> 541.4145 | AH10: =AE10*1.1 -> 520.179 | AI10: =AG10*1.1 -> 595.55595 | AJ10: =AH10*1.05 -> 546.18795 | AK10: =AI10*1.05 -> 625.33375 | AL10: 546.2 | AM10: =AL10*1.06 -> 578.972 | AN10: 625.4 | AO10: =AN10*1.06 -> 662.924 | AR10: =AM10*1.07 -> 619.50004 | AS10: =AO10*1.07 -> 709.32868 | AX10: =AR10*1.1 -> 681.45004 | AY10: =AS10*1.1 -> 780.26155
B11: 3 | C11: SCREEN 3% | E11: 3001, 3002, 3008, 3009, 3060 e 3061 | H11: =ROUNDUP(((AX11*$N$7)+AX11),1) -> 472.1 | J11: =ROUNDUP(((AY11*$N$7)+AY11),1) -> 529.2 | L11: 0 | AA11: 275.7 | AB11: 325.2 | AC11: 297.8 | AD11: 351.3 | AE11: =AC11*1.1 -> 327.58 | AF11: =AD11*1.1 -> 386.43 | AG11: =(((AF11*95)/100)-AF11)+AF11 -> 367.1085 | AH11: =AE11*1.1 -> 360.338 | AI11: =AG11*1.1 -> 403.81935 | AJ11: =AH11*1.05 -> 378.3549 | AK11: =AI11*1.05 -> 424.01032 | AL11: 378.4 | AM11: =AL11*1.06 -> 401.104 | AN11: 424.1 | AO11: =AN11*1.06 -> 449.546 | AR11: =AM11*1.07 -> 429.18128 | AS11: =AO11*1.07 -> 481.01422 | AX11: =AR11*1.1 -> 472.09941 | AY11: =AS11*1.1 -> 529.11564
B12: 4 | E12: 3010 ao 3015, 3017 ao 3019 | H12: =ROUNDUP(((AX12*$N$7)+AX12),1) -> 472.1 | J12: =ROUNDUP(((AY12*$N$7)+AY12),1) -> 529.2 | L12: 0 | AA12: 275.7 | AB12: 325.2 | AC12: 297.8 | AD12: 351.3 | AE12: =AC12*1.1 -> 327.58 | AF12: =AD12*1.1 -> 386.43 | AG12: =(((AF12*95)/100)-AF12)+AF12 -> 367.1085 | AH12: =AE12*1.1 -> 360.338 | AI12: =AG12*1.1 -> 403.81935 | AJ12: =AH12*1.05 -> 378.3549 | AK12: =AI12*1.05 -> 424.01032 | AL12: 378.4 | AM12: =AL12*1.06 -> 401.104 | AN12: 424.1 | AO12: =AN12*1.06 -> 449.546 | AR12: =AM12*1.07 -> 429.18128 | AS12: =AO12*1.07 -> 481.01422 | AX12: =AR12*1.1 -> 472.09941 | AY12: =AS12*1.1 -> 529.11564
B13: 5 | C13: SCREEN FIBER GLASS 3% | E13: 6101, 6102 e 6103 | H13: =ROUNDUP(((AX13*$N$7)+AX13),1) -> 599.9 | J13: =ROUNDUP(((AY13*$N$7)+AY13),1) -> 672.6 | L13: 0 | AA13: 350.37 | AB13: 413.44 | AC13: 378.4 | AD13: 446.6 | AE13: =AC13*1.1 -> 416.24 | AF13: =AD13*1.1 -> 491.26 | AG13: =(((AF13*95)/100)-AF13)+AF13 -> 466.697 | AH13: =AE13*1.1 -> 457.864 | AI13: =AG13*1.1 -> 513.3667 | AJ13: =AH13*1.05 -> 480.7572 | AK13: =AI13*1.05 -> 539.03504 | AL13: 480.8 | AM13: =AL13*1.06 -> 509.648 | AN13: 539.1 | AO13: =AN13*1.06 -> 571.446 | AR13: =AM13*1.07 -> 545.32336 | AS13: =AO13*1.07 -> 611.44722 | AX13: =AR13*1.1 -> 599.8557 | AY13: =AS13*1.1 -> 672.59194
B14: 6 | C14: SCREEN 5% | E14: 3070 ao 3076, 3077, 3078 e 3079, 3096, 3097 e 3098 | H14: =ROUNDUP(((AX14*$N$7)+AX14),1) -> 470.2 | J14: =ROUNDUP(((AY14*$N$7)+AY14),1) -> 527 | L14: 0 | AA14: 274.5 | AB14: 323.9 | AC14: 296.5 | AD14: 349.9 | AE14: =AC14*1.1 -> 326.15 | AF14: =AD14*1.1 -> 384.89 | AG14: =(((AF14*95)/100)-AF14)+AF14 -> 365.6455 | AH14: =AE14*1.1 -> 358.765 | AI14: =AG14*1.1 -> 402.21005 | AJ14: =AH14*1.05 -> 376.70325 | AK14: =AI14*1.05 -> 422.32055 | AL14: 376.8 | AM14: =AL14*1.06 -> 399.408 | AN14: 422.4 | AO14: =AN14*1.06 -> 447.744 | AR14: =AM14*1.07 -> 427.36656 | AS14: =AO14*1.07 -> 479.08608 | AX14: =AR14*1.1 -> 470.10322 | AY14: =AS14*1.1 -> 526.99469
B15: 7 | C15: SCREEN FIBER GLASS 5% | E15: 6201, 6202 e 6203 | H15: =ROUNDUP(((AX15*$N$7)+AX15),1) -> 568.1 | J15: =ROUNDUP(((AY15*$N$7)+AY15),1) -> 672.6 | L15: 0 | AA15: 331.71 | AB15: 413.44 | AC15: 358.3 | AD15: 446.6 | AE15: =AC15*1.1 -> 394.13 | AF15: =AD15*1.1 -> 491.26 | AG15: =(((AF15*95)/100)-AF15)+AF15 -> 466.697 | AH15: =AE15*1.1 -> 433.543 | AI15: =AG15*1.1 -> 513.3667 | AJ15: =AH15*1.05 -> 455.22015 | AK15: =AI15*1.05 -> 539.03504 | AL15: 455.3 | AM15: =AL15*1.06 -> 482.618 | AN15: 539.1 | AO15: =AN15*1.06 -> 571.446 | AR15: =AM15*1.07 -> 516.40126 | AS15: =AO15*1.07 -> 611.44722 | AX15: =AR15*1.1 -> 568.04139 | AY15: =AS15*1.1 -> 672.59194
B16: 8 | C16: SCREEN CRISTAL 5% | E16: 3100 | H16: =ROUNDUP(((AX16*$N$7)+AX16),1) -> 502 | J16: =ROUNDUP(((AY16*$N$7)+AY16),1) -> 557.1 | L16: 0 | AA16: 293.1 | AB16: 342.5 | AC16: 316.6 | AD16: 369.9 | AE16: =AC16*1.1 -> 348.26 | AF16: =AD16*1.1 -> 406.89 | AG16: =(((AF16*95)/100)-AF16)+AF16 -> 386.5455 | AH16: =AE16*1.1 -> 383.086 | AI16: =AG16*1.1 -> 425.20005 | AJ16: =AH16*1.05 -> 402.2403 | AK16: =AI16*1.05 -> 446.46005 | AL16: 402.3 | AM16: =AL16*1.06 -> 426.438 | AN16: 446.5 | AO16: =AN16*1.06 -> 473.29 | AR16: =AM16*1.07 -> 456.28866 | AS16: =AO16*1.07 -> 506.4203 | AX16: =AR16*1.1 -> 501.91753 | AY16: =AS16*1.1 -> 557.06233
B17: 9 | C17: SCREEN RÚSTICO 3% | E17: 3150, 3151, 3153 | H17: =ROUNDUP(((AX17*$N$7)+AX17),1) -> 487 | J17: =ROUNDUP(((AY17*$N$7)+AY17),1) -> 543.1 | L17: 0 | AA17: 284.4 | AB17: 333.8 | AC17: 307.2 | AD17: 360.6 | AE17: =AC17*1.1 -> 337.92 | AF17: =AD17*1.1 -> 396.66 | AG17: =(((AF17*95)/100)-AF17)+AF17 -> 376.827 | AH17: =AE17*1.1 -> 371.712 | AI17: =AG17*1.1 -> 414.5097 | AJ17: =AH17*1.05 -> 390.2976 | AK17: =AI17*1.05 -> 435.23519 | AL17: 390.3 | AM17: =AL17*1.06 -> 413.718 | AN17: 435.3 | AO17: =AN17*1.06 -> 461.418 | AR17: =AM17*1.07 -> 442.67826 | AS17: =AO17*1.07 -> 493.71726 | AX17: =AR17*1.1 -> 486.94609 | AY17: =AS17*1.1 -> 543.08899
B18: 10 | C18: SCREEN RÚSTICO 5% | E18: 3159, 3160, 3161, 3162 e 3163 | H18: =ROUNDUP(((AX18*$N$7)+AX18),1) -> 487 | J18: =ROUNDUP(((AY18*$N$7)+AY18),1) -> 543.1 | L18: 0 | AA18: 284.4 | AB18: 333.8 | AC18: 307.2 | AD18: 360.6 | AE18: =AC18*1.1 -> 337.92 | AF18: =AD18*1.1 -> 396.66 | AG18: =(((AF18*95)/100)-AF18)+AF18 -> 376.827 | AH18: =AE18*1.1 -> 371.712 | AI18: =AG18*1.1 -> 414.5097 | AJ18: =AH18*1.05 -> 390.2976 | AK18: =AI18*1.05 -> 435.23519 | AL18: 390.3 | AM18: =AL18*1.06 -> 413.718 | AN18: 435.3 | AO18: =AN18*1.06 -> 461.418 | AR18: =AM18*1.07 -> 442.67826 | AS18: =AO18*1.07 -> 493.71726 | AX18: =AR18*1.1 -> 486.94609 | AY18: =AS18*1.1 -> 543.08899
B19: 11 | E19: 3155 e 3156 | H19: =ROUNDUP(((AX19*$N$7)+AX19),1) -> 487 | J19: =ROUNDUP(((AY19*$N$7)+AY19),1) -> 543.1 | L19: 0 | AA19: 284.4 | AB19: 333.8 | AC19: 307.2 | AD19: 360.6 | AE19: =AC19*1.1 -> 337.92 | AF19: =AD19*1.1 -> 396.66 | AG19: =(((AF19*95)/100)-AF19)+AF19 -> 376.827 | AH19: =AE19*1.1 -> 371.712 | AI19: =AG19*1.1 -> 414.5097 | AJ19: =AH19*1.05 -> 390.2976 | AK19: =AI19*1.05 -> 435.23519 | AL19: 390.3 | AM19: =AL19*1.06 -> 413.718 | AN19: 435.3 | AO19: =AN19*1.06 -> 461.418 | AR19: =AM19*1.07 -> 442.67826 | AS19: =AO19*1.07 -> 493.71726 | AX19: =AR19*1.1 -> 486.94609 | AY19: =AS19*1.1 -> 543.08899
B20: 12 | C20: SCREEN REFLEX | E20: 3121, 3122 e 3123 | H20: =ROUNDUP(((AX20*$N$7)+AX20),1) -> 584.7 | J20: =ROUNDUP(((AY20*$N$7)+AY20),1) -> 632 | L20: 0 | AA20: 341.4 | AB20: 388.5 | AC20: 368.8 | AD20: 419.6 | AE20: =AC20*1.1 -> 405.68 | AF20: =AD20*1.1 -> 461.56 | AG20: =(((AF20*95)/100)-AF20)+AF20 -> 438.482 | AH20: =AE20*1.1 -> 446.248 | AI20: =AG20*1.1 -> 482.3302 | AJ20: =AH20*1.05 -> 468.5604 | AK20: =AI20*1.05 -> 506.44671 | AL20: 468.6 | AM20: =AL20*1.06 -> 496.716 | AN20: 506.5 | AO20: =AN20*1.06 -> 536.89 | AR20: =AM20*1.07 -> 531.48612 | AS20: =AO20*1.07 -> 574.4723 | AX20: =AR20*1.1 -> 584.63473 | AY20: =AS20*1.1 -> 631.91953
B21: 13 | C21: SCREEN BK | E21: 3200, 3201 e 3203 | H21: =ROUNDUP(((AX21*$N$7)+AX21),1) -> 584.7 | J21: =ROUNDUP(((AY21*$N$7)+AY21),1) -> 632 | L21: 0 | AM21: 496.8 | AO21: 536.9 | AR21: =AM21*1.07 -> 531.576 | AS21: =AO21*1.07 -> 574.483 | AX21: 584.7 | AY21: =AS21*1.1 -> 631.9313
B22: 14 | C22: BK PINPOINT | E22: 180 ao 183 e 186 ao 190 | H22: =ROUNDUP(((AX22*$N$7)+AX22),1) -> 434.1 | J22: =ROUNDUP(((AY22*$N$7)+AY22),1) -> 493 | L22: 0.1 | AA22: 253.5 | AB22: 303 | AC22: 273.8 | AD22: 327.3 | AE22: =AC22*1.1 -> 301.18 | AF22: =AD22*1.1 -> 360.03 | AG22: =(((AF22*95)/100)-AF22)+AF22 -> 342.0285 | AH22: =AE22*1.1 -> 331.298 | AI22: =AG22*1.1 -> 376.23135 | AJ22: =AH22*1.05 -> 347.8629 | AK22: =AI22*1.05 -> 395.04292 | AL22: 347.9 | AM22: =AL22*1.06 -> 368.774 | AN22: 395.1 | AO22: =AN22*1.06 -> 418.806 | AR22: =AM22*1.07 -> 394.58818 | AS22: =AO22*1.07 -> 448.12242 | AX22: =AR22*1.1 -> 434.047 | AY22: =AS22*1.1 -> 492.93466
B23: 15 | AA23: 293.1 | AB23: 342.5 | AC23: 316.6 | AD23: 369.9 | AE23: =AC23*1.1 -> 348.26 | AF23: =AD23*1.1 -> 406.89 | AG23: =(((AF23*95)/100)-AF23)+AF23 -> 386.5455 | AH23: =AE23*1.1 -> 383.086 | AI23: =AG23*1.1 -> 425.20005 | AJ23: =AH23*1.05 -> 402.2403 | AK23: =AI23*1.05 -> 446.46005 | AL23: 0 | AM23: 0 | AN23: 0 | AO23: 0 | AR23: =AM23*1.07 -> 0 | AS23: =AO23*1.07 -> 0 | AX23: =AR23*1.1 -> 0 | AY23: =AS23*1.1 -> 0
B24: 16 | C24: CORTINA DE TETO CELULAR 25MM SINGLE CELL (MONO CÉLULA) | AM24: =AL24*1.06 -> 0 | AN24: 0 | AO24: 0 | AR24: =AM24*1.07 -> 0 | AS24: =AO24*1.07 -> 0 | AX24: =AR24*1.1 -> 0 | AY24: =AS24*1.1 -> 0
B25: 17 | C25: TRANSLÚCIDA PLS - 210 | E25: 0001, 0004 e 0030 | H25: =ROUNDUP(((AX25*$N$7)+AX25),1) -> 592.7 | J25: Indisponível | L25: 0 | AA25: 346.1 | AB25: 0 | AC25: 373.8 | AE25: =AC25*1.1 -> 411.18 | AH25: =AE25*1.1 -> 452.298 | AJ25: =AH25*1.05 -> 474.9129 | AK25: =AI25*1.05 -> 0 | AL25: 475 | AM25: =AL25*1.06 -> 503.5 | AN25: 0 | AO25: 0 | AR25: =AM25*1.07 -> 538.745 | AS25: =AO25*1.07 -> 0 | AX25: =AR25*1.1 -> 592.6195 | AY25: =AS25*1.1 -> 0
B26: 18 | AN26: 0 | AO26: 0 | AR26: =AM26*1.07 -> 0 | AS26: =AO26*1.07 -> 0 | AX26: =AR26*1.1 -> 0 | AY26: =AS26*1.1 -> 0
B27: 19 | C27: BLACKOUT - 220 | E27: 0001, 0003, 0004 | H27: =ROUNDUP(((AX27*$N$7)+AX27),1) -> 698.5 | J27: Indisponível | L27: 0 | AA27: 407.9 | AB27: 0 | AC27: 440.6 | AE27: =AC27*1.1 -> 484.66 | AH27: =AE27*1.1 -> 533.126 | AJ27: =AH27*1.05 -> 559.7823 | AK27: =AI27*1.05 -> 0 | AL27: 559.8 | AM27: =AL27*1.06 -> 593.388 | AN27: 0 | AO27: 0 | AR27: =AM27*1.07 -> 634.92516 | AS27: =AO27*1.07 -> 0 | AX27: =AR27*1.1 -> 698.41768 | AY27: =AS27*1.1 -> 0
B28: 20 | N28: * DIGITE A PORCENTAGEM PARA MARKUP - ACESSÓRIOS
B29: 21 | C29: ACESSÓRIOS | N29: 0
B30: 22 | C30: DESCRIÇÃO DO ACESSÓRIO | H30: COR | I30: UNIDADE | J30: VALOR À VISTA (R$) | L30: IPI | AA30: 42491 | AC30: 43026 | AE30: 43258 | AG30: 43862 | AI30: 43952 | AK30: 44105 | AL30: 44256 | AM30: 44501 | AR30: 45536 | AS30: 45658
B31: 23 | C31: BASTÃO DE ALUMÍNIO PARA CORTINA DE TETO ALLURE COM 1,00M | H31: Natural | I31: UN | J31: =ROUNDUP(((AS31*$N$29)+AS31),1) -> 66 | L31: 0.1 | N31: * Legenda de Cores: | AA31: 31.79 | AC31: 34.4 | AE31: =AC31*1.1 -> 37.84 | AG31: =AE31*1.1 -> 41.624 | AI31: =AG31*1.1 -> 45.7864 | AK31: =AI31*1.05 -> 48.07572 | AL31: =AK31*1.1 -> 52.883292 | AM31: 52.9 | AN31: =AM31*1.06 -> 56.074 | AR31: =AN31*1.07 -> 59.99918 | AS31: =AR31*1.1 -> 65.999098
B32: 24 | C32: BASTÃO DE ALUMÍNIO PARA CORTINA DE TETO ALLURE COM 1,50M | H32: Natural | I32: UN | J32: =ROUNDUP(((AS32*$N$29)+AS32),1) -> 97.7 | L32: 0.1 | N32: B = Branco | AA32: 47.08 | AC32: 50.9 | AE32: =AC32*1.1 -> 55.99 | AG32: =AE32*1.1 -> 61.589 | AI32: =AG32*1.1 -> 67.7479 | AK32: =AI32*1.05 -> 71.135295 | AL32: =AK32*1.1 -> 78.248825 | AM32: 78.3 | AN32: =AM32*1.06 -> 82.998 | AR32: =AN32*1.07 -> 88.80786 | AS32: =AR32*1.1 -> 97.688646
B33: 25 | C33: BASTÃO DE ALUMÍNIO PARA CORTINA DE TETO ALLURE COM 2,00M | H33: Natural | I33: UN | J33: =ROUNDUP(((AS33*$N$29)+AS33),1) -> 122.1 | L33: 0.1 | N33: M = Marfim | AA33: 58.85 | AC33: 63.6 | AE33: =AC33*1.1 -> 69.96 | AG33: =AE33*1.1 -> 76.956 | AI33: =AG33*1.1 -> 84.6516 | AK33: =AI33*1.05 -> 88.88418 | AL33: =AK33*1.1 -> 97.772598 | AM33: 97.8 | AN33: =AM33*1.06 -> 103.668 | AR33: =AN33*1.07 -> 110.92476 | AS33: =AR33*1.1 -> 122.01724
B34: 26 | C34: BASTÃO DE FERRO PARA CORTINA DE TETO ALLURE COM 2,50M | H34: Natural | I34: UN | J34: =ROUNDUP(((AS34*$N$29)+AS34),1) -> 161.2 | L34: 0.1 | N34: P = Preto | AA34: 77.77 | AC34: 84 | AE34: =AC34*1.1 -> 92.4 | AG34: =AE34*1.1 -> 101.64 | AI34: =AG34*1.1 -> 111.804 | AK34: =AI34*1.05 -> 117.3942 | AL34: =AK34*1.1 -> 129.13362 | AM34: 129.2 | AN34: =AM34*1.06 -> 136.952 | AR34: =AN34*1.07 -> 146.53864 | AS34: =AR34*1.1 -> 161.1925
B35: 27 | C35: BASTÃO DE FERRO PARA CORTINA DE TETO ALLURE COM 3,50M | H35: Natural | I35: UN | J35: =ROUNDUP(((AS35*$N$29)+AS35),1) -> 185.8 | L35: 0.1 | N35: C = Cinza | AA35: 89.54 | AC35: 96.8 | AE35: =AC35*1.1 -> 106.48 | AG35: =AE35*1.1 -> 117.128 | AI35: =AG35*1.1 -> 128.8408 | AK35: =AI35*1.05 -> 135.28284 | AL35: =AK35*1.1 -> 148.81112 | AM35: 148.9 | AN35: =AM35*1.06 -> 157.834 | AR35: =AN35*1.07 -> 168.88238 | AS35: =AR35*1.1 -> 185.77062
B36: 28 | C36: CORRENTE METÁLICA - COBRADO 2X O TAMANHO DO COMANDO (TC). (LANÇAMENTOS) | H36: Inox - Bronze - Ouro Velho - Preto Niquelado | I36: ML | J36: =ROUNDUP(((AS36*$N$29)+AS36),1) -> 17.4 | L36: 0 | N36: MR = Marrom | AA36: 6.6 | AC36: 7.2 | AE36: =AC36*1.1 -> 7.92 | AG36: =AE36*1.2 -> 9.504 | AI36: =AG36*1.1 -> 10.4544 | AK36: =AI36*1.05 -> 10.97712 | AL36: =AK36*1.1 -> 12.074832 | AM36: 12.1 | AN36: =AM36*1.06 -> 12.826 | AR36: 15.8 | AS36: =AR36*1.1 -> 17.38
B37: 29
B38: 30 | C38: O VALOR DO ACESSÓRIO SOLICITADO A PARTE É SOB CONSULTA. O VALOR QUE CONSTA NA TABELA É PARA ACESSÓRIO SOLICITADO COM O PRODUTO MONTADO. | N38: BZ = Bronze
B39: 31
B40: 32 | C40: * GARANTIA DE 3 ANOS
B41: 33 | C41: ANTES DE ENVIAR O PEDIDO CONSULTE AS INFORMAÇÕES GERAIS.
B42: 34 | C42: TECIDO SCREEN REFLEX 5% COM CAMADA REFLETORA NA PARTE DE TRÁS - REFLETE O SOL REDUZINDO O CALOR INTERNO DO AMBIENTE.
B43: 35
B44: 36 | C44: INFORMAÇÕES TÉCNICAS
B45: 37
B46: 38 | G46: Teto Allure | H46: Teto Mono | I46: Teto Celular
B47: 39
B48: 40 | E48: Larg. Mínima | G48: 0,40m | H48: 0,40m | I48: 0,30m
B49: 41 | E49: Larg. Máxima | G49: 1,50m | H49: 1,60m | I49: 1,30m
B50: 42 | E50: Comprimento Mínimo | G50: 0,20m | H50: 0,40m | I50: 0,40m
B51: 43 | E51: Comprimento Máximo | G51: 6,00m | H51: 4,50m | I51: 5,00m
B52: 44 | E52: Metragem Mínima | G52: 1,50m² | H52: 1,50m² | I52: 1,50m²
B53: 45 | E53: Metragem Máxima | G53: 6,50m² | H53: 5,00m² | I53: 4,50m²
B54: 46
B55: 47
B56: 48
B57: 49
B58: 50
B59: 51
B60: 52
B61: 53
B62: 54
B63: 55 | C63: O TECIDO É UM OBJETO DE SUPERFÍCIE MALEÁVEL QUE APRESENTA PEQUENAS ONDULAÇÕES EM SUA EXTENSÃO. COM A INCIDÊNCIA DE LUZ SOBRE O TECIDO, PODE OCORRER EFEITOS DE SOMBRA EVIDENCIANDO AS ONDULAÇÕES CONFORME ORIGEM DA ILUMINAÇÃO. ESTE EFEITO É UMA CARACTERÍSTICA NATURAL DO PRODUTO E NÃO ESTARÁ COBERTO PELA GARANTIA.
B64: 56
B65: 57
B66: 58
K67: Página 17 - | L67: =Rolô!L2 -> 2026 - v.03
B68: CORTINA DE TETO
B71: 59 | C71: INFORMAÇÕES GERAIS
B72: 60 | C72: METRAGEM MÍNIMA COBRADA POR PEÇA 1,50M².
B73: 61 | C73: CORTINA DE TETO ALLURE POSSUI TENSOR NO QUAL PERMITE QUE A CORTINA SEJA AJUSTADA NO NÍVEL DESEJADO MESMO QUANDO INSTALADA EM ÁREA INCLINADA.
B74: 62
B75: 63 | C75: CORTINA DE TETO QUANDO INSTALADA DENTRO DE VÃO, É NECESSÁRIO CANTONEIRAS LATERAIS PARA EFETUAR A INSTALAÇÃO. A INFORMAÇÃO DE INSTALAÇÃO DEVE CONSTAR NO PEDIDO, CASO SEJA DENTRO DE VÃO, ENVIAREMOS AS CANTONEIRAS LATERAIS SEM CUSTO ADICIONAL.
B76: 64
B77: 65 | C77: PARA ALINHAMENTO DOS GOMOS EM PEÇAS LADO A LADO, DEVE CONSTAR NO PEDIDO A SOLICITAÇÃO DE ALINHAMENTO DAS HASTES, NO QUAL PODERÁ TER CUSTOS ADICIONAIS DEPENDENDO DA MEDIDA.
B78: 66
B79: 67 | C79: CORTINAS DE TETO SÃO PRODUZIDAS DE 2MM A 3MM MENORES NA LARGURA E ALTURA, ESTE DESCONTO É NECESSÁRIO PARA ALINHAMENTO E ESPAÇO DOS PARAFUSOS DE INSTALAÇÃO. QUANDO NECESSÁRIO DESCONTOS EXTRAS, FAVOR CONSIDERAR ESTA FOLGA. TODA CORTINA DE TETO INSTALADA DENTRO DE VÃO APRESENTARÁ FOLGA ENTRE A CANTONEIRA DE INSTALAÇÃO E O TRILHO, ISSO É UMA CARACTERISTICA DO PRODUTO.
B80: 68
B81: 69
B82: 70 | C82: PEÇAS INSTALADAS FORA DO VÃO, NÃO HÁ NECESSIDADE DE CANTONEIRAS.
B83: 71 | C83: CORTINA DE TETO ALLURE MOTORIZADA POSSUI LARGURA MÁXIMA DE 2,20M E COMPRIMENTO MÁXIMO DE 6,00M.
B84: 72 | C84: CORTINA DE TETO ALLURE MOTORIZADA SERÁ ENVIADA DESMONTADA, SENDO QUE PARA EFETUAR A INSTALAÇÃO, OS CLIPES DEVERÃO SER FIXADOS EM CADA LADO DO TRILHO E EM SEGUIDA O TRILHO DEVERÁ SER FIXADO. A BARRA DE VELCRO TAMBÉM DEVERÁ SER FIXADA PARA PRENDER O TECIDO. POR FIM, O TECIDO DEVERÁ SER PRESO AOS CARRINHOS.
B85: 73
B86: 74
B87: 75 | C87: CORTINA DE TETO MONOCONTROLE SERÁ ENVIADA DESMONTADA, SENDO QUE PARA EFETUAR A INSTALAÇÃO, OS CLIPES DEVERÃO SER INSTALADOS E DEPOIS FIXADO OS TRILHOS. O EIXO É ENCAIXADO NAS DUAS PONTAS DOS TRILHO E DO LADO QUE VAI FICAR A CORRENTE DE ACIONAMENTO, ENCAIXA-SE O COMANDO, APÓS ISSO, TRAVE OS EIXOS. POR FIM, O TECIDO DEVERÁ SER PRESO AOS CARRINHOS.
B88: 76
B89: 77
B90: 78 | C90: CORTINA DE TETO MOTORIZADO SERÁ ENVIADA DESMONTADA, SENDO QUE PARA EFETUAR A INSTALAÇÃO, OS CLIPES DEVERÃO SER INSTALADOS E DEPOIS FIXADO OS TRILHOS. A CABECEIRA ONDE ESTÁ O MOTOR DEVERÁ SER INSTALADA ENTRE OS TRILHO, PARA O EIXO QUE É ENCAIXADO NO MOTOR, GIRE OS DOIS TRILHOS AO MESMO TEMPO, TRAVE OS EIXOS NO TRILHO. POR FIM, O TECIDO DEVERÁ SER PRESO AOS CARRINHOS.
B91: 79
B92: 80
B93: 81
B94: 82 | C94: INFORMAÇÕES GERAIS
B95: 83 | C95: PODEM EXISTIR EMENDAS NAS CANTONEIRAS DE INSTALAÇÃO.
B96: 84 | C96: PEÇAS INSTALADAS LADO A LADO PODEM APRESENTAR DESALINHAMENTO NAS HASTES.
B97: 85 | C97: ATENÇÃO AO TRANSPORTAR E MANUSEAR AS CORTINAS COM GRANDES DIMENSÕES. AS CORTINAS DE TETO SAEM DA FABRICA DEVIDAMENTE MONTADAS.
B98: 86 | C98: AS CORTINAS DE TETO SÃO FABRICADAS SOMENTE NOS TECIDOS E MATERIAIS QUE CONSTAM EM TABELA.
B99: 87 | C99: AS CORTINAS DE TETO NÃO EVITAM CONDENSAÇÃO, QUE OCASIONA GOTEIRAS.
B100: 88 | C100: A CORRENTE CONTÍNUA DA CORTINA DE TETO MONOCONTROLE, POSSUI TAMANHO MÁXIMO DE 3,00M, ACIMA DESTA ALTURA É OBRIGATÓRIO O USO DA CORRENTE METÁLICA COM CUSTO ADICIONAL.
B101: 89
B102: 90 | C102: CORTINA DE TETO NO MODELO CELULAR POSSUI CORDAS APARENTES NO MEIO DO MÓDULO. ESTA CORDA SERVE PARA SUSTENTAÇÃO, EVITANDO QUE O TECIDO FORME ONDULAÇÃO.
B103: 91
B104: 92 | C104: CORTINAS MOTORIZADAS, CONSULTE A PÁGINA DE MOTORIZAÇÃO.
B105: 93 | C105: TETOS COM RECORTES CONSIDERAMOS A VISUALIZAÇÃO DO DESENHO DE BAIXO PARA CIMA.
...

Sheet Soltis (Ferrari®)
K2: Página 18 - | L2: =Rolô!L2 -> 2026 - v.03 | N2: * DIGITE A PORCENTAGEM PARA MARKUP - CORTINA ROLÔ
B3: LINHA DE CORTINAS NA COLEÇÃO SOLTIS | N3: 0
B4: PRODUTO EM CONFORMIDADE COM A NORMA ABNT NBR 16234: 2014
B6: CORTINA ROLÔ | AA6: 42491 | AB6: 43026 | AC6: 43258 | AD6: 43862 | AE6: 43952 | AF6: 43983 | AG6: 44105 | AH6: 44136 | AI6: 44256 | AJ6: 44287 | AK6: 44501
B7: ITEM | C7: COLEÇÃO | E7: COR | H7: LAR. MAX. | I7: VALOR À VISTA (R$)/M² | K7: IPI | AT7: 45658 | AU7: 46082
B8: 1 | C8: SOLTIS 86 | E8: 3600 ao 3606 (FERRARI®) | H8: 2.67 | I8: =ROUNDUP(((AU8*$N$3)+AU8),1) -> 499.5 | K8: 0 | AA8: 205 | AB8: 221.4 | AC8: =AB8*1.1 -> 243.54 | AD8: =AC8*1.2 -> 292.248 | AE8: =AD8*1.25 -> 365.31 | AG8: =AE8*1.08 -> 394.5348 | AH8: =AF8*1.08 -> 0 | AI8: =AG8*1.15 -> 453.71502 | AK8: 453.8 | AL8: =AK8*1.1 -> 499.18 | AP8: =AL8*1.07 -> 534.1226 | AT8: =AP8*1.1 -> 587.53486 | AU8: =AT8+(AT8-(AT8*1.15)) -> 499.40463
B9: 2 | C9: SOLTIS 96 | E9: 3700 ao 3704 (FERRARI®) | H9: 2.67 | I9: =ROUNDUP(((AU9*$N$3)+AU9),1) -> 402 | K9: 0 | AA9: 165 | AB9: 178.2 | AC9: =AB9*1.1 -> 196.02 | AD9: =AC9*1.2 -> 235.224 | AE9: =AD9*1.25 -> 294.03 | AG9: =AE9*1.08 -> 317.5524 | AI9: =AG9*1.15 -> 365.18526 | AK9: 365.2 | AL9: =AK9*1.1 -> 401.72 | AP9: =AL9*1.07 -> 429.8404 | AT9: =AP9*1.1 -> 472.82444 | AU9: =AT9+(AT9-(AT9*1.15)) -> 401.90077
B10: 3 | C10: SOLTIS W96 | E10: 3800 ao 3802 (FERRARI®) | H10: 2.67 | I10: =ROUNDUP(((AU10*$N$3)+AU10),1) -> 572.5 | K10: 0 | AA10: 235 | AB10: 253.8 | AC10: =AB10*1.1 -> 279.18 | AD10: =AC10*1.2 -> 335.016 | AE10: =AD10*1.25 -> 418.77 | AG10: =AE10*1.08 -> 452.2716 | AI10: =AG10*1.15 -> 520.11234 | AK10: 520.2 | AL10: =AK10*1.1 -> 572.22 | AP10: =AL10*1.07 -> 612.2754 | AT10: =AP10*1.1 -> 673.50294 | AU10: =AT10+(AT10-(AT10*1.15)) -> 572.4775
B11: 4 | C11: SOLTIS 99 | E11: 3500 ao 3504 (FERRARI®) | H11: 2.67 | I11: =ROUNDUP(((AU11*$N$3)+AU11),1) -> 572.5 | K11: 0 | AA11: 235 | AB11: 253.8 | AC11: =AB11*1.1 -> 279.18 | AD11: =AC11*1.2 -> 335.016 | AE11: =AD11*1.25 -> 418.77 | AG11: =AE11*1.08 -> 452.2716 | AI11: =AG11*1.15 -> 520.11234 | AK11: 520.2 | AL11: =AK11*1.1 -> 572.22 | AP11: =AL11*1.07 -> 612.2754 | AT11: =AP11*1.1 -> 673.50294 | AU11: =AT11+(AT11-(AT11*1.15)) -> 572.4775
B12: 5 | C12: SOLTIS B99 | E12: 3400 ao 3402 (FERRARI®) | H12: 1.7 | I12: =ROUNDUP(((AU12*$N$3)+AU12),1) -> 572.5 | K12: 0 | AA12: 235 | AB12: 253.8 | AC12: =AB12*1.1 -> 279.18 | AD12: =AC12*1.2 -> 335.016 | AE12: =AD12*1.25 -> 418.77 | AG12: =AE12*1.08 -> 452.2716 | AI12: =AG12*1.15 -> 520.11234 | AK12: 520.2 | AL12: =AK12*1.1 -> 572.22 | AP12: =AL12*1.07 -> 612.2754 | AT12: =AP12*1.1 -> 673.50294 | AU12: =AT12+(AT12-(AT12*1.15)) -> 572.4775
B13: CORTINA ROMANA | N13: * DIGITE A PORCENTAGEM PARA MARKUP - CORTINA ROMANA | AP13: =AL13*1.07 -> 0 | AT13: =AP13*1.1 -> 0 | AU13: =AT13+(AT13-(AT13*1.15)) -> 0
B14: ITEM | C14: COLEÇÃO | E14: COR | H14: LAR. MAX. | I14: VALOR À VISTA (R$)/M² | K14: IPI | N14: 0 | AP14: =AL14*1.07 -> 0 | AT14: =AP14*1.1 -> 0 | AU14: =AT14+(AT14-(AT14*1.15)) -> 0
B15: 6 | C15: SOLTIS 86 | E15: 3600 ao 3606 (FERRARI®) | H15: 2.67 | I15: =ROUNDUP(((AU15*$N$14)+AU15),1) -> 447.1 | K15: 0 | AA15: 183.5 | AB15: 198.2 | AC15: =AB15*1.1 -> 218.02 | AD15: =AC15*1.2 -> 261.624 | AE15: =AD15*1.25 -> 327.03 | AG15: =AE15*1.08 -> 353.1924 | AI15: =AG15*1.15 -> 406.17126 | AK15: 406.2 | AL15: =AK15*1.1 -> 446.82 | AP15: =AL15*1.07 -> 478.0974 | AT15: =AP15*1.1 -> 525.90714 | AU15: =AT15+(AT15-(AT15*1.15)) -> 447.02107
B16: 7 | C16: SOLTIS 96 | E16: 3700 ao 3704 (FERRARI®) | H16: 2.67 | I16: =ROUNDUP(((AU16*$N$14)+AU16),1) -> 360 | K16: 0 | AA16: 147.7 | AB16: 159.6 | AC16: =AB16*1.1 -> 175.56 | AD16: =AC16*1.2 -> 210.672 | AE16: =AD16*1.25 -> 263.34 | AG16: =AE16*1.08 -> 284.4072 | AI16: =AG16*1.15 -> 327.06828 | AK16: 327.1 | AL16: =AK16*1.1 -> 359.81 | AP16: =AL16*1.07 -> 384.9967 | AT16: =AP16*1.1 -> 423.49637 | AU16: =AT16+(AT16-(AT16*1.15)) -> 359.97191
B17: 8 | C17: SOLTIS W96 | E17: 3800 ao 3802 (FERRARI®) | H17: 2.67 | I17: =ROUNDUP(((AU17*$N$14)+AU17),1) -> 512.8 | K17: 0 | AA17: 210.4 | AB17: 227.3 | AC17: =AB17*1.1 -> 250.03 | AD17: =AC17*1.2 -> 300.036 | AE17: =AD17*1.25 -> 375.045 | AG17: =AE17*1.08 -> 405.0486 | AI17: =AG17*1.15 -> 465.80589 | AK17: 465.9 | AL17: =AK17*1.1 -> 512.49 | AP17: =AL17*1.07 -> 548.3643 | AT17: =AP17*1.1 -> 603.20073 | AU17: =AT17+(AT17-(AT17*1.15)) -> 512.72062
B18: 9 | C18: SOLTIS 99 | E18: 3500 ao 3504 (FERRARI®) | H18: 2.67 | I18: =ROUNDUP(((AU18*$N$14)+AU18),1) -> 512.8 | K18: 0 | AA18: 210.4 | AB18: 227.3 | AC18: =AB18*1.1 -> 250.03 | AD18: =AC18*1.2 -> 300.036 | AE18: =AD18*1.25 -> 375.045 | AG18: =AE18*1.08 -> 405.0486 | AI18: =AG18*1.15 -> 465.80589 | AK18: 465.9 | AL18: =AK18*1.1 -> 512.49 | AP18: =AL18*1.07 -> 548.3643 | AT18: =AP18*1.1 -> 603.20073 | AU18: =AT18+(AT18-(AT18*1.15)) -> 512.72062
B19: 10 | C19: SOLTIS B99 | E19: 3400 ao 3402 (FERRARI®) | H19: 1.7 | I19: =ROUNDUP(((AU19*$N$14)+AU19),1) -> 512.8 | K19: 0 | AA19: 210.4 | AB19: 227.3 | AC19: =AB19*1.1 -> 250.03 | AD19: =AC19*1.2 -> 300.036 | AE19: =AD19*1.25 -> 375.045 | AG19: =AE19*1.08 -> 405.0486 | AI19: =AG19*1.15 -> 465.80589 | AK19: 465.9 | AL19: =AK19*1.1 -> 512.49 | AP19: =AL19*1.07 -> 548.3643 | AT19: =AP19*1.1 -> 603.20073 | AU19: =AT19+(AT19-(AT19*1.15)) -> 512.72062
B20: CORTINA DE TETO | N20: * DIGITE A PORCENTAGEM PARA MARKUP - CORTINA DE TETO | AP20: =AL20*1.07 -> 0 | AT20: =AP20*1.1 -> 0 | AU20: =AT20+(AT20-(AT20*1.15)) -> 0
B21: ITEM | C21: COLEÇÃO | E21: COR | J21: VALOR À VISTA (R$)/M² ALLURE (STANDARD) | L21: IPI | N21: 0 | AP21: =AL21*1.07 -> 0 | AT21: =AP21*1.1 -> 0 | AU21: =AT21+(AT21-(AT21*1.15)) -> 0
AP22: =AL22*1.07 -> 0 | AT22: =AP22*1.1 -> 0 | AU22: =AT22+(AT22-(AT22*1.15)) -> 0
B23: 11 | C23: SOLTIS 86 | E23: 3600 ao 3606 (FERRARI®) | J23: =ROUNDUP(((AU23*$N$21)+AU23),1) -> 1175 | L23: 0 | AA23: 410 | AB23: 442.8 | AC23: =AB23*1.1 -> 487.08 | AD23: =AC23*1.2 -> 584.496 | AE23: =AD23*1.25 -> 730.62 | AG23: =AE23*1.08 -> 789.0696 | AI23: =AG23*1.15 -> 907.43004 | AK23: 907.5 | AL23: =AK23*1.1 -> 998.25 | AP23: =AL23*1.07 -> 1068.1275 | AT23: =AP23*1.1 -> 1174.9403 | AU23: =AT23 -> 1174.9403
B24: 12 | C24: SOLTIS 96 | E24: 3700 ao 3704 (FERRARI®) | J24: =ROUNDUP(((AU24*$N$21)+AU24),1) -> 945.7 | L24: 0 | AA24: 330 | AB24: 356.4 | AC24: =AB24*1.1 -> 392.04 | AD24: =AC24*1.2 -> 470.448 | AE24: =AD24*1.25 -> 588.06 | AG24: =AE24*1.08 -> 635.1048 | AI24: =AG24*1.15 -> 730.37052 | AK24: 730.4 | AL24: =AK24*1.1 -> 803.44 | AP24: =AL24*1.07 -> 859.6808 | AT24: =AP24*1.1 -> 945.64888 | AU24: =AT24 -> 945.64888
B25: 13 | C25: SOLTIS W96 | E25: 3800 ao 3802 (FERRARI®) | J25: =ROUNDUP(((AU25*$N$21)+AU25),1) -> 1346.9 | L25: 0 | AA25: 470 | AB25: 507.6 | AC25: =AB25*1.1 -> 558.36 | AD25: =AC25*1.2 -> 670.032 | AE25: =AD25*1.25 -> 837.54 | AG25: =AE25*1.08 -> 904.5432 | AI25: =AG25*1.15 -> 1040.2247 | AK25: 1040.3 | AL25: =AK25*1.1 -> 1144.33 | AP25: =AL25*1.07 -> 1224.4331 | AT25: =AP25*1.1 -> 1346.8764 | AU25: =AT25 -> 1346.8764
B26: 14 | C26: SOLTIS 99 | E26: 3500 ao 3504 (FERRARI®) | J26: =ROUNDUP(((AU26*$N$21)+AU26),1) -> 1346.9 | L26: 0 | AA26: 470 | AB26: 507.6 | AC26: =AB26*1.1 -> 558.36 | AD26: =AC26*1.2 -> 670.032 | AE26: =AD26*1.25 -> 837.54 | AG26: =AE26*1.08 -> 904.5432 | AI26: =AG26*1.15 -> 1040.2247 | AK26: 1040.3 | AL26: =AK26*1.1 -> 1144.33 | AP26: =AL26*1.07 -> 1224.4331 | AT26: =AP26*1.1 -> 1346.8764 | AU26: =AT26 -> 1346.8764
B27: 15 | C27: SOLTIS B99 | E27: 3400 ao 3402 (FERRARI®) | J27: =ROUNDUP(((AU27*$N$21)+AU27),1) -> 1346.9 | L27: 0 | AA27: 470 | AB27: 507.6 | AC27: =AB27*1.1 -> 558.36 | AD27: =AC27*1.2 -> 670.032 | AE27: =AD27*1.25 -> 837.54 | AG27: =AE27*1.08 -> 904.5432 | AI27: =AG27*1.15 -> 1040.2247 | AK27: 1040.3 | AL27: =AK27*1.1 -> 1144.33 | AP27: =AL27*1.07 -> 1224.4331 | AT27: =AP27*1.1 -> 1346.8764 | AU27: =AT27 -> 1346.8764
B28: 16
B29: 17 | C29: CERTIFICADOS
B30: 18 | C30: SOLTIS 86 | E30: GREEN GUARD | GREEN GUARD GOLD | ISO 846 | M1 NFP 92-507 RETARDANTE DE CHAMAS
B31: 19 | C31: SOLTIS 96 | E31: M2 NFP 92-507 RETARDANTE DE CHAMAS
B32: 20 | C32: SOLTIS W96 | E32: M2 NFP 92-507 RETARDANTE DE CHAMAS
B33: 21 | C33: SOLTIS 99 | E33: GREEN GUARD | GREEN GUARD GOLD | M1 NFP 92-507 RETARDANTE DE CHAMAS
B34: 22 | C34: SOLTIS B99 | E34: GREEN GUARD | GREEN GUARD GOLD | M1 NFP 92-507 RETARDANTE DE CHAMAS
B35: 23
B36: 24
B37: 25
B38: 26
B39: 27
B40: 28
B41: 29
B42: 30
B43: 31
B44: 32 | C44: PARA ACESSÓRIOS E INFORMAÇÕES TÉCNICAS DA CORTINA ROLÔ, ACESSE A PÁGINA 6.
B45: 33 | C45: PARA ACESSÓRIOS E INFORMAÇÕES TÉCNICAS DA CORTINA ROMANA, ACESSE A PÁGINA 12.
B46: 34 | C46: PARA ACESSÓRIOS E INFORMAÇÕES TÉCNICAS DA CORTINA DE TETO, ACESSE A PÁGINA 16.
B47: 35
B48: 36 | C48: O TECIDO É UM OBJETO DE SUPERFÍCIE MALEÁVEL QUE APRESENTA PEQUENAS ONDULAÇÕES EM SUA EXTENSÃO. COM A INCIDÊNCIA DE LUZ SOBRE O TECIDO, PODE OCORRER EFEITOS DE SOMBRA EVIDENCIANDO AS ONDULAÇÕES CONFORME ORIGEM DA ILUMINAÇÃO. ESTE EFEITO É UMA CARACTERÍSTICA NATURAL DO PRODUTO E NÃO ESTARÁ COBERTO PELA GARANTIA.
B49: 37
B50: 38
B51: 39
B52: 40 | C52: TECIDOS NO QUAL SÃO PERMITIDOS A INVERSÃO, PODEM APRESENTAR ONDULAÇÕES MAIS EVIDENTES. ESSA CARACTERÍSTICA OCORRE DEVIDO AO SENTIDO DE ENROLAMENTO DO TECIDO NA BOBINA.
B53: 41
B54: 42
B55: 43
B56: 44
B57: 45
B58: 46
B59: 47
B60: 48
B61: 49
B62: 50
B63: 51
B64: 52
... B66: 54

Sheet Vertical
K2: Página 19 - | L2: =Rolô!L2 -> 2026 - v.03 | N2: * DIGITE A PORCENTAGEM PARA MARKUP DE VERTICAL TECIDO
B3: PERSIANA VERTICAL | N3: 0
B7: ITEM | C7: COLEÇÃO | E7: COR | I7: VALOR À VISTA (R$)/M² | K7: IPI | Y7: 42491 | Z7: 43026 | AA7: 43258 | AB7: 43862 | AC7: 43952 | AD7: 44105 | AE7: 44256 | AF7: 44378 | AK7: 44682 | AP7: 45658
B8: 1 | C8: ARGENTINA | E8: 0006, 0007, 0009, 0011, 0013, 0019, 0020, 0023 | I8: =ROUNDUP(((AR8*$N$3)+AR8),1) -> 71.1 | K8: 0 | Y8: 35.31 | Z8: 38.9 | AA8: =Z8*1.1 -> 42.79 | AB8: =AA8*1.12 -> 47.9248 | AC8: =AB8*1.08 -> 51.758784 | AD8: =AC8*1.08 -> 55.899487 | AE8: =AD8*1.1 -> 61.489435 | AF8: =AE8*1.08 -> 66.40859 | AG8: 66.5 | AH8: =AG8*1.06 -> 70.49 | AI8: =AH8*1.06 -> 74.7194 | AK8: 64.9 | AN8: =AK8*1.07 -> 69.443 | AP8: =AN8*1.1 -> 76.3873 | AR8: =(AP8*(-7%))+AP8 -> 71.040189
B9: 2 | E9: 0801, 0808, 0809, 0814 e 0818 | I9: =ROUNDUP(((AR9*$N$3)+AR9),1) -> 71.1 | K9: 0 | Y9: 35.31 | Z9: 38.9 | AA9: =Z9*1.1 -> 42.79 | AB9: =AA9*1.12 -> 47.9248 | AC9: =AB9*1.08 -> 51.758784 | AD9: =AC9*1.08 -> 55.899487 | AE9: =AD9*1.1 -> 61.489435 | AF9: =AE9*1.08 -> 66.40859 | AG9: 66.5 | AH9: =AG9*1.06 -> 70.49 | AI9: =AH9*1.06 -> 74.7194 | AK9: 64.9 | AN9: =AK9*1.07 -> 69.443 | AP9: =AN9*1.1 -> 76.3873 | AR9: =(AP9*(-7%))+AP9 -> 71.040189
B10: 3 | AC10: =AB10*1.108 -> 0 | AH10: =AG10*1.06 -> 0 | AI10: =AH10*1.06 -> 0 | AN10: =AK10*1.07 -> 0 | AP10: =AN10*1.1 -> 0 | AR10: =(AP10*(-7%))+AP10 -> 0
B11: 4 | C11: BOLÍVIA | E11: 0033 ao 0036 e 0043 | I11: =ROUNDUP(((AR11*$N$3)+AR11),1) -> 78.1 | K11: 0 | Y11: 39.93 | Z11: 44 | AA11: =Z11*1.1 -> 48.4 | AB11: =AA11*1.12 -> 54.208 | AC11: =AB11*1.08 -> 58.54464 | AD11: =AC11*1.08 -> 63.228211 | AE11: =AD11*1.1 -> 69.551032 | AF11: =AE11*1.05 -> 73.028584 | AG11: 73.1 | AH11: =AG11*1.06 -> 77.486 | AI11: =AH11*1.06 -> 82.13516 | AK11: 69.8 | AN11: =AK11*1.07 -> 74.686 | AP11: =AN11*1.1 -> 82.1546 | AR11: =(AP11*(-5%))+AP11 -> 78.04687
B12: 7 | C12: PERU | E12: 0242 ao 0244, 0249, 0253 e 0254, 0256 e 0257 | I12: =ROUNDUP(((AR12*$N$3)+AR12),1) -> 68.8 | K12: 0 | Y12: 31.35 | Z12: 34.5 | AA12: =Z12*1.1 -> 37.95 | AB12: =AA12*1.12 -> 42.504 | AC12: =AB12*1.08 -> 45.90432 | AD12: =AC12*1.08 -> 49.576666 | AE12: =AD12*1.07 -> 53.047032 | AF12: =AE12*1.2 -> 63.656439 | AG12: 63.7 | AH12: =AG12*1.06 -> 67.522 | AI12: =AH12*1.06 -> 71.57332 | AK12: 64.9 | AN12: =AK12*1.07 -> 69.443 | AP12: =AN12*1.1 -> 76.3873 | AR12: =(AP12*(-10%))+AP12 -> 68.74857
B13: 8 | C13: VENEZUELA | E13: 0365, 0366 e 0371 | I13: =ROUNDUP(((AR13*$N$3)+AR13),1) -> 72.6 | K13: 0 | AE13: 71.22 | AF13: =AE13 -> 71.22 | AG13: 71.3 | AH13: =AG13*1.06 -> 75.578 | AI13: =AH13*1.06 -> 80.11268 | AK13: 64.9 | AN13: =AK13*1.07 -> 69.443 | AP13: =AN13*1.1 -> 76.3873 | AR13: =(AP13*(-5%))+AP13 -> 72.567935
B14: 9 | E14: 0363, 0372, 0375 ao 0380 | I14: =ROUNDUP(((AR14*$N$3)+AR14),1) -> 81.4 | AK14: 74.3 | AN14: =AK14*1.07 -> 79.501 | AP14: =AN14*1.1 -> 87.4511 | AR14: =(AP14*(-7%))+AP14 -> 81.329523
B15: 10 | E15: 0369 | I15: =ROUNDUP(((AR15*$N$3)+AR15),1) -> 91.5 | AK15: 77.7 | AN15: =AK15*1.07 -> 83.139 | AP15: =AN15*1.1 -> 91.4529 | AR15: =AP15 -> 91.4529
B16: 11 | E16: 0331, 0335 e 0336 | I16: =ROUNDUP(((AR16*$N$3)+AR16),1) -> 121.8 | AD16: =#REF!*1.08 -> #REF! | AE16: =AD16*1.25 -> #REF! | AF16: 101.6 | AG16: 101.6 | AH16: =AG16*1.06 -> 107.696 | AI16: =AH16*1.06 -> 114.15776 | AK16: 103.4 | AN16: =AK16*1.07 -> 110.638 | AP16: =AN16*1.1 -> 121.7018 | AR16: =AP16 -> 121.7018
B17: 12 | E17: 0359, 0364, 0370, e 0385 ao 0399 | I17: =ROUNDUP(((AR17*$N$3)+AR17),1) -> 83.4 | AD17: 77.45 | AE17: =AD17*1.05 -> 81.3225 | AF17: =AE17 -> 81.3225 | AG17: 81.4 | AH17: =AG17*1.06 -> 86.284 | AI17: =AH17*1.06 -> 91.46104 | AK17: 70.8 | AN17: =AK17*1.07 -> 75.756 | AP17: =AN17*1.1 -> 83.3316 | AR17: =AP17 -> 83.3316
B18: 13 | E18: 0338, 0343, 0360, 0361, 0362, 0373 e 0374 | I18: =ROUNDUP(((AR18*$N$3)+AR18),1) -> 77.6 | AH18: =AG18*1.06 -> 0 | AI18: =AH18*1.06 -> 0 | AN18: =AK18*1.07 -> 0 | AP18: 83.4 | AR18: =(AP18*(-7%))+AP18 -> 77.562
B19: 14 | AH19: =AG19*1.06 -> 0 | AI19: =AH19*1.06 -> 0 | AN19: =AK19*1.07 -> 0 | AP19: 83.4 | AR19: =(AP19*(-7%))+AP19 -> 77.562
B20: 15 | C20: FRANÇA BLACKOUT | E20: 0485 ao 0488 | I20: =ROUNDUP(((AR20*$N$3)+AR20),1) -> 148.4 | K20: 0 | Y20: 61.6 | Z20: 67.8 | AA20: =Z20*1.1 -> 74.58 | AB20: =AA20*1.12 -> 83.5296 | AC20: =AB20*1.08 -> 90.211968 | AD20: =AC20*1.08 -> 97.428925 | AE20: 113.4 | AF20: =AE20*1.182 -> 134.0388 | AG20: 134.1 | AH20: =AG20*1.06 -> 142.146 | AI20: =AH20*1.06 -> 150.67476 | AK20: 135.5 | AN20: =AK20*1.07 -> 144.985 | AP20: =AN20*1.1 -> 159.4835 | AR20: =(AP20*(-7%))+AP20 -> 148.31966 | AS20: verificar com Kleber
B21: 16 | E21: 0673, 0680, 0682,e 0688 ao 0696 | I21: =ROUNDUP(((AR21*$N$3)+AR21),1) -> 159.5 | AH21: =AG21*1.06 -> 0 | AI21: =AH21*1.06 -> 0 | AN21: =AK21*1.07 -> 0 | AP21: 159.48 | AR21: =AP21 -> 159.48
B22: 17 | AH22: =AG22*1.06 -> 0 | AI22: =AH22*1.06 -> 0 | AN22: =AK22*1.07 -> 0 | AP22: =AN22*1.1 -> 0 | AR22: =(AP22*(-7%))+AP22 -> 0
B23: 18 | E23: 0483 | I23: =ROUNDUP(((AR23*$N$3)+AR23),1) -> 182.7 | K23: 0 | Y23: 68.2 | Z23: 75.1 | AA23: =Z23*1.1 -> 82.61 | AB23: =AA23*1.12 -> 92.5232 | AC23: =AB23*1.08 -> 99.925056 | AD23: =AC23*1.08 -> 107.91906 | AE23: 132.4 | AF23: =AE23*1.25 -> 165.5 | AG23: 165.5 | AH23: =AG23*1.06 -> 175.43 | AI23: =AH23*1.06 -> 185.9558 | AK23: 166.8 | AN23: =AK23*1.07 -> 178.476 | AP23: =AN23*1.1 -> 196.3236 | AR23: 182.7
B24: 19 | E24: 0472, 0474 e 0481 | I24: =ROUNDUP(((AR24*$N$3)+AR24),1) -> 136.8 | K24: 0 | AF24: 128 | AG24: 128 | AH24: =AG24*1.06 -> 135.68 | AI24: =AH24*1.06 -> 143.8208 | AK24: 122.3 | AN24: =AK24*1.07 -> 130.861 | AP24: =AN24*1.1 -> 143.9471 | AR24: =(AP24*(-5%))+AP24 -> 136.74975
B25: 20 | E25: 0665 | I25: =ROUNDUP(((AR25*$N$3)+AR25),1) -> 154.6 | K25: 0 | AA25: 74.58 | AB25: =AA25*1.12 -> 83.5296 | AC25: =AB25*1.08 -> 90.211968 | AD25: =AC25*1.08 -> 97.428925 | AE25: 121.9 | AF25: =AE25*1.1 -> 134.09 | AG25: 134.1 | AH25: =AG25*1.06 -> 142.146 | AI25: =AH25*1.06 -> 150.67476 | AK25: 141.2 | AN25: =AK25*1.07 -> 151.084 | AP25: =AN25*1.1 -> 166.1924 | AR25: =(AP25*(-7%))+AP25 -> 154.55893
B26: 21 | E26: 0462, 0666, 0668, 0669, 0679, 0683, 0684, 0685, 0686 e 0687 | I26: =ROUNDUP(((AR26*$N$3)+AR26),1) -> 141.8 | K26: 0 | AK26: 129.4 | AN26: =AK26*1.07 -> 138.458 | AP26: =AN26*1.1 -> 152.3038 | AR26: 141.8
E27: 0681 | I27: =ROUNDUP(((AR27*$N$3)+AR27),1) -> 167.4 | K27: 0 | AK27: 142.2 | AN27: =AK27*1.07 -> 152.154 | AP27: =AN27*1.1 -> 167.3694 | AR27: =AP27 -> 167.3694
B28: 22 | E28: 675 | I28: =ROUNDUP(((AR28*$N$3)+AR28),1) -> 159.8 | K28: 0 | Y28: 75.9 | Z28: 83.5 | AA28: =Z28*1.1 -> 91.85 | AB28: =AA28*1.12 -> 102.872 | AC28: =AB28*1.08 -> 111.10176 | AD28: =AC28*1.08 -> 119.9899 | AE28: 102.4 | AF28: =AE28*1.25 -> 128 | AG28: 128 | AH28: =AG28*1.06 -> 135.68 | AI28: =AH28*1.06 -> 143.8208 | AK28: 135.7 | AN28: =AK28*1.07 -> 145.199 | AP28: =AN28*1.1 -> 159.7189 | AR28: =AP28 -> 159.7189
B29: 23 | C29: NORUEGA BLACKOUT | E29: 1080 e 1081 | I29: =ROUNDUP(((AR29*$N$3)+AR29),1) -> 121.8 | K29: 0 | Y29: 61.6 | Z29: 67.8 | AA29: =Z29*1.1 -> 74.58 | AB29: =AA29*1.12 -> 83.5296 | AC29: =AB29*1.08 -> 90.211968 | AD29: 97.5 | AE29: =AD29*1.05 -> 102.375 | AF29: =AE29 -> 102.375 | AG29: 102.4 | AH29: =AG29*1.06 -> 108.544 | AI29: =AH29*1.06 -> 115.05664 | AK29: 103.4 | AN29: =AK29*1.07 -> 110.638 | AP29: =AN29*1.1 -> 121.7018 | AR29: =AP29 -> 121.7018
B30: 24 | E30: 1088 ao 1092 | I30: =ROUNDUP(((AR30*$N$3)+AR30),1) -> 127.9 | K30: 0 | AA30: 74.58 | AB30: =AA30*1.12 -> 83.5296 | AC30: =AB30*1.08 -> 90.211968 | AD30: 97.5 | AE30: =AD30*1.25 -> 121.875 | AF30: =AE30 -> 121.875 | AG30: 121.9 | AH30: =AG30*1.06 -> 129.214 | AI30: =AH30*1.06 -> 136.96684 | AK30: 108.6 | AN30: =AK30*1.07 -> 116.202 | AP30: =AN30*1.1 -> 127.8222 | AR30: =AP30 -> 127.8222
B31: 26 | E31: 1082 e 1083 | I31: =ROUNDUP(((AR31*$N$3)+AR31),1) -> 159.5 | K31: 0 | Y31: 68.2 | Z31: 75.1 | AA31: =Z31*1.1 -> 82.61 | AB31: =AA31*1.12 -> 92.5232 | AC31: =AB31*1.08 -> 99.925056 | AD31: 108 | AE31: =AD31*1.15 -> 124.2 | AF31: =AE31*1.08 -> 134.136 | AG31: 134.2 | AH31: =AG31*1.06 -> 142.252 | AI31: =AH31*1.06 -> 150.78712 | AK31: 135.5 | AN31: =AK31*1.07 -> 144.985 | AP31: =AN31*1.1 -> 159.4835 | AR31: =AP31 -> 159.4835
B32: 27 | C32: TURQUIA (SCREEN 5%) | E32: 1041 ao 1043 | I32: =ROUNDUP(((AR32*$N$3)+AR32),1) -> 137.5 | K32: 0 | Y32: 59.4 | Z32: 65.4 | AA32: =Z32*1.1 -> 71.94 | AB32: =AA32*1.12 -> 80.5728 | AC32: =AB32*1.08 -> 87.018624 | AD32: =AC32*1.08 -> 93.980114 | AE32: =AD32*1.15 -> 108.07713 | AF32: =AE32*1.05 -> 113.48099 | AG32: 113.5 | AH32: =AG32*1.06 -> 120.31 | AI32: =AH32*1.06 -> 127.5286 | AK32: 116.8 | AN32: =AK32*1.07 -> 124.976 | AP32: =AN32*1.1 -> 137.4736 | AR32: =AP32 -> 137.4736
B33: 28 | E33: 1045 | I33: =ROUNDUP(((AR33*$N$3)+AR33),1) -> 166.2 | K33: 0 | Y33: 64.9 | Z33: 71.4 | AA33: =Z33*1.1 -> 78.54 | AB33: =AA33*1.12 -> 87.9648 | AC33: =AB33*1.08 -> 95.001984 | AD33: =AC33*1.08 -> 102.60214 | AE33: =AD33*1.3 -> 133.38279 | AF33: =AE33*1.05 -> 140.05192 | AG33: 140.1 | AH33: =AG33*1.06 -> 148.506 | AI33: =AH33*1.06 -> 157.41636 | AK33: 141.2 | AN33: =AK33*1.07 -> 151.084 | AP33: =AN33*1.1 -> 166.1924 | AR33: =AP33 -> 166.1924
B34: 30 | C34: TUNÍSIA (BK PINPOINT) | E34: 2020 ao 2022 e 2024 | I34: =ROUNDUP(((AR34*$N$3)+AR34),1) -> 121.8 | K34: 0 | Y34: 61.6 | Z34: 67.8 | AA34: =Z34*1.1 -> 74.58 | AB34: =AA34*1.12 -> 83.5296 | AC34: =AB34*1.08 -> 90.211968 | AD34: =AC34*1.08 -> 97.428925 | AE34: =AD34*1.05 -> 102.30037 | AF34: =AE34*1.05 -> 107.41539 | AG34: 107.5 | AH34: =AG34*1.06 -> 113.95 | AI34: =AH34*1.06 -> 120.787 | AK34: 103.4 | AN34: =AK34*1.07 -> 110.638 | AP34: =AN34*1.1 -> 121.7018 | AR34: =AP34 -> 121.7018
B35: 31 | C35: BÉLGICA BK | E35: 2058 | I35: =ROUNDUP(((AR35*$N$3)+AR35),1) -> 147.9 | K35: 0 | Y35: 75.9 | Z35: 83.5 | AA35: =Z35*1.1 -> 91.85 | AB35: =AA35*1.12 -> 102.872 | AC35: =AB35*1.08 -> 111.10176 | AD35: 120 | AE35: =AD35*1.05 -> 126 | AF35: =AE35 -> 126 | AG35: 126 | AH35: =AG35*1.06 -> 133.56 | AI35: =AH35*1.06 -> 141.5736 | AK35: 125.6 | AN35: =AK35*1.07 -> 134.392 | AP35: =AN35*1.1 -> 147.8312 | AR35: =AP35 -> 147.8312
B36: 32 | E36: 2050, 2055, 2059, 2060, 2062 | I36: =ROUNDUP(((AR36*$N$3)+AR36),1) -> 164.7 | K36: 0 | AD36: 120 | AE36: =AD36*1.1 -> 132 | AF36: =AE36*1.05 -> 138.6 | AG36: 138.6 | AH36: =AG36*1.06 -> 146.916 | AI36: =AH36*1.06 -> 155.73096 | AK36: 139.9 | AN36: =AK36*1.07 -> 149.693 | AP36: =AN36*1.1 -> 164.6623 | AR36: =AP36 -> 164.6623
B37: 33 | E37: 2056, 2063 e 2064 | I37: =ROUNDUP(((AR37*$N$3)+AR37),1) -> 179.1 | K37: 0 | AD37: 120 | AE37: =AD37*1.25 -> 150 | AF37: =AE37*1.05 -> 157.5 | AG37: 157.5 | AH37: =AG37*1.06 -> 166.95 | AI37: =AH37*1.06 -> 176.967 | AK37: 152.1 | AN37: =AK37*1.07 -> 162.747 | AP37: =AN37*1.1 -> 179.0217 | AR37: =AP37 -> 179.0217
B38: 34 | E38: 2061, 2053 | I38: =ROUNDUP(((AR38*$N$3)+AR38),1) -> 144 | K38: 0 | Y38: 61.6 | Z38: 67.8 | AA38: =Z38*1.1 -> 74.58 | AB38: =AA38*1.12 -> 83.5296 | AC38: =AB38*1.08 -> 90.211968 | AD38: 97.5 | AE38: =AD38*1.2 -> 117 | AF38: 126 | AG38: 126 | AH38: =AG38*1.06 -> 133.56 | AI38: =AH38*1.06 -> 141.5736 | AK38: 122.3 | AN38: =AK38*1.07 -> 130.861 | AP38: =AN38*1.1 -> 143.9471 | AR38: =AP38 -> 143.9471
B39: 35 | C39: CROÁCIA | E39: 2080 ao 2082 | I39: =ROUNDUP(((AR39*$N$3)+AR39),1) -> 117.6 | K39: 0 | Y39: 49 | Z39: 53.9 | AA39: =Z39*1.1 -> 59.29 | AB39: =AA39*1.12 -> 66.4048 | AC39: =AB39*1.08 -> 71.717184 | AD39: 77.5 | AE39: =AD39*1.3 -> 100.75 | AF39: =AE39*1.05 -> 105.7875 | AG39: 105.8 | AH39: =AG39*1.06 -> 112.148 | AI39: =AH39*1.06 -> 118.87688 | AK39: 99.9 | AN39: =AK39*1.07 -> 106.893 | AP39: =AN39*1.1 -> 117.5823 | AR39: =AP39 -> 117.5823
B40: 36 | E40: 2091 ao 2093 | I40: =ROUNDUP(((AR40*$N$3)+AR40),1) -> 117.6 | AD40: 77.5 | AE40: =AD40*1.05 -> 81.375 | AF40: =AE40 -> 81.375 | AG40: 81.4 | AH40: =AG40*1.06 -> 86.284 | AI40: =AH40*1.06 -> 91.46104 | AK40: 99.9 | AN40: =AK40*1.07 -> 106.893 | AP40: =AN40*1.1 -> 117.5823 | AR40: =AP40 -> 117.5823
B41: 37 | E41: 2084 e 2100 | I41: =ROUNDUP(((AR41*$N$3)+AR41),1) -> 91.5 | AE41: 81.38 | AF41: 89.2 | AG41: 89.2 | AH41: =AG41*1.06 -> 94.552 | AI41: =AH41*1.06 -> 100.22512 | AK41: 77.7 | AN41: =AK41*1.07 -> 83.139 | AP41: =AN41*1.1 -> 91.4529 | AR41: =AP41 -> 91.4529
B42: 38 | E42: 2098 e 2099 | I42: =ROUNDUP(((AR42*$N$3)+AR42),1) -> 105.9 | AK42: 89.9 | AN42: =AK42*1.07 -> 96.193 | AP42: =AN42*1.1 -> 105.8123 | AR42: =AP42 -> 105.8123
B43: 39 | E43: 2097 | I43: =ROUNDUP(((AR43*$N$3)+AR43),1) -> 100.3 | AK43: 85.2 | AN43: =AK43*1.07 -> 91.164 | AP43: =AN43*1.1 -> 100.2804 | AR43: =AP43 -> 100.2804
B44: 40 | E44: 2088 2089 | I44: =ROUNDUP(((AR44*$N$3)+AR44),1) -> 105.9 | N44: * DIGITE A PORCENTAGEM PARA MARKUP DE VERTICAL WAVE | AD44: 77.5 | AE44: =AD44*1.15 -> 89.125 | AF44: =AE44 -> 89.125 | AG44: 89.2 | AH44: =AG44*1.06 -> 94.552 | AI44: =AH44*1.06 -> 100.22512 | AK44: 89.9 | AN44: =AK44*1.07 -> 96.193 | AP44: =AN44*1.1 -> 105.8123 | AR44: =AP44 -> 105.8123
B45: 41 | C45: PERSIANA VERTICAL WAVE (LÂMINAS EM PVC ONDULADO) | N45: 0 | AH45: =AG45*1.06 -> 0 | AI45: =AH45*1.06 -> 0 | AN45: =AK45*1.07 -> 0 | AP45: =AN45*1.1 -> 0 | AR45: =(AP45*(-7%))+AP45 -> 0
B46: 42 | C46: PVC WAVE | E46: 4001, 4002, 4003 e 4009 | I46: =ROUNDUP(((AP46*$N$45)+AP46),1) -> 171.1 | K46: 0.05 | Y46: 68.09 | Z46: 74.9 | AA46: =Z46*1.1 -> 82.39 | AB46: =AA46*1.12 -> 92.2768 | AC46: =AB46*1.08 -> 99.658944 | AD46: =AC46*1.1 -> 109.62484 | AE46: =AD46*1.25 -> 137.03105 | AF46: =AE46 -> 137.03105 | AG46: 137.1 | AH46: =AG46*1.06 -> 145.326 | AI46: =AH46*1.06 -> 154.04556 | AN46: =AH46*1.07 -> 155.49882 | AP46: =AN46*1.1 -> 171.0487 | AR46: =(AP46*(-7%))+AP46 -> 159.07529
B47: 43 | AH47: =AG47*1.06 -> 0 | AI47: =AH47*1.06 -> 0 | AN47: =AK47*1.07 -> 0 | AP47: =AN47*1.1 -> 0
B48: 44 | C48: PERSIANA VERTICAL (LÂMINAS PVC) | N48: * DIGITE A PORCENTAGEM PARA MARKUP DE VERTICAL PVC | AH48: =AG48*1.06 -> 0 | AI48: =AH48*1.06 -> 0 | AN48: =AK48*1.07 -> 0 | AP48: =AN48*1.1 -> 0
